Workbook
Name IQ_CH: 110000
Name IQ_CQ: 5000
Name IQ_CY: 10000
Name IQ_DAILY: 500000
Name IQ_FH: 100000
Name IQ_FQ: 500
Name IQ_FY: 1000
Name IQ_LTM: 2000
Name IQ_MONTH: 15000
Name IQ_NTM: 6000
Name IQ_WEEK: 50000
Name IQ_YTD: 3000
Name UPDATE: 'Data Sheet'!$E$1

Sheet Financials>

Sheet HistoricalFS
B2: ="Historical Financial Statement -"&'Data Sheet'!B1 -> Historical Financial Statement -ASIAN PAINTS LTD
B3: Years | C3: ='Data Sheet'!B16 -> 42825 | D3: ='Data Sheet'!C16 -> 43190 | E3: ='Data Sheet'!D16 -> 43555 | F3: ='Data Sheet'!E16 -> 43921 | G3: ='Data Sheet'!F16 -> 44286 | H3: ='Data Sheet'!G16 -> 44651 | I3: ='Data Sheet'!H16 -> 45016 | J3: ='Data Sheet'!I16 -> 45382 | ... L3: ='Data Sheet'!K16 -> 46112
A5: # | B5: Income Statement
B6: Sales | C6: =IFERROR('Data Sheet'!B17,0) -> 15061.99 | D6: =IFERROR('Data Sheet'!C17,0) -> 16824.55 | E6: =IFERROR('Data Sheet'!D17,0) -> 19240.13 | F6: =IFERROR('Data Sheet'!E17,0) -> 20211.25 | G6: =IFERROR('Data Sheet'!F17,0) -> 21712.79 | H6: =IFERROR('Data Sheet'!G17,0) -> 29101.28 | I6: =IFERROR('Data Sheet'!H17,0) -> 34488.59 | J6: =IFERROR('Data Sheet'!I17,0) -> 35494.73 | ... L6: =IFERROR('Data Sheet'!K17,0) -> 35583.54
B7: Sales Growth | C7: - | D7: =D6/C6-1 -> 0.11702039 | E7: =E6/D6-1 -> 0.14357472 | F7: =F6/E6-1 -> 0.050473671 | G7: =G6/F6-1 -> 0.074292288 | H7: =H6/G6-1 -> 0.34028285 | I7: =I6/H6-1 -> 0.18512278 | J7: =J6/I6-1 -> 0.029173127 | K7: =K6/J6-1 -> -0.044770308 | L7: =L6/K6-1 -> 0.049487961
B9: COGS | C9: =IFERROR(SUM('Data Sheet'!B18,'Data Sheet'!B20,'Data Sheet'!B21)-1*'Data Sheet'!B19,0) -> 8692.77 | D9: =IFERROR(SUM('Data Sheet'!C18,'Data Sheet'!C20,'Data Sheet'!C21)-1*'Data Sheet'!C19,0) -> 10072.28 | E9: =IFERROR(SUM('Data Sheet'!D18,'Data Sheet'!D20,'Data Sheet'!D21)-1*'Data Sheet'!D19,0) -> 11663.12 | F9: =IFERROR(SUM('Data Sheet'!E18,'Data Sheet'!E20,'Data Sheet'!E21)-1*'Data Sheet'!E19,0) -> 11786.75 | G9: =IFERROR(SUM('Data Sheet'!F18,'Data Sheet'!F20,'Data Sheet'!F21)-1*'Data Sheet'!F19,0) -> 12487.46 | H9: =IFERROR(SUM('Data Sheet'!G18,'Data Sheet'!G20,'Data Sheet'!G21)-1*'Data Sheet'!G19,0) -> 18795.96 | I9: =IFERROR(SUM('Data Sheet'!H18,'Data Sheet'!H20,'Data Sheet'!H21)-1*'Data Sheet'!H19,0) -> 21730.29 | J9: =IFERROR(SUM('Data Sheet'!I18,'Data Sheet'!I20,'Data Sheet'!I21)-1*'Data Sheet'!I19,0) -> 20675.07 | ... L9: =IFERROR(SUM('Data Sheet'!K18,'Data Sheet'!K20,'Data Sheet'!K21)-1*'Data Sheet'!K19,0) -> 20679.9
B10: COGS % Sales | C10: =C9/C6 -> 0.5771329 | D10: =D9/D6 -> 0.59866564 | E10: =E9/E6 -> 0.60618717 | F10: =F9/F6 -> 0.58317769 | G10: =G9/G6 -> 0.57512001 | H10: =H9/H6 -> 0.64588087 | I10: =I9/I6 -> 0.63007186 | J10: =J9/J6 -> 0.58248281 | ... L10: =L9/L6 -> 0.58116477
B12: Gross Profit | C12: =C6-C9 -> 6369.22 | D12: =D6-D9 -> 6752.27 | E12: =E6-E9 -> 7577.01 | F12: =F6-F9 -> 8424.5 | G12: =G6-G9 -> 9225.33 | H12: =H6-H9 -> 10305.32 | I12: =I6-I9 -> 12758.3 | J12: =J6-J9 -> 14819.66 | ... L12: =L6-L9 -> 14903.64
B13: Gross Margins | C13: =C12/C6 -> 0.4228671 | D13: =D12/D6 -> 0.40133436 | E13: =E12/E6 -> 0.39381283 | F13: =F12/F6 -> 0.41682231 | G13: =G12/G6 -> 0.42487999 | H13: =H12/H6 -> 0.35411913 | I13: =I12/I6 -> 0.36992814 | J13: =J12/J6 -> 0.41751719 | ... L13: =L12/L6 -> 0.41883523
B15: Selling and admin expenses | C15: =IFERROR(SUM('Data Sheet'!B23:B24),0) -> 2335.57 | D15: =IFERROR(SUM('Data Sheet'!C23:C24),0) -> 2426.37 | E15: =IFERROR(SUM('Data Sheet'!D23:D24),0) -> 2569.38 | F15: =IFERROR(SUM('Data Sheet'!E23:E24),0) -> 2891.46 | G15: =IFERROR(SUM('Data Sheet'!F23:F24),0) -> 2822.12 | H15: =IFERROR(SUM('Data Sheet'!G23:G24),0) -> 3707.1 | I15: =IFERROR(SUM('Data Sheet'!H23:H24),0) -> 4462.05 | J15: =IFERROR(SUM('Data Sheet'!I23:I24),0) -> 4899.76 | ... L15: =IFERROR(SUM('Data Sheet'!K23:K24),0) -> 5394.18
B16: S&G as % Sales | C16: =C15/C6 -> 0.15506384 | D16: =D15/D6 -> 0.14421604 | E16: =E15/E6 -> 0.13354276 | F16: =F15/F6 -> 0.14306191 | G16: =G15/G6 -> 0.12997501 | H16: =H15/H6 -> 0.12738615 | I16: =I15/I6 -> 0.12937757 | J16: =J15/J6 -> 0.1380419 | ... L16: =L15/L6 -> 0.151592
B18: EBITDA | C18: =C12-C15 -> 4033.65 | D18: =D12-D15 -> 4325.9 | E18: =E12-E15 -> 5007.63 | F18: =F12-F15 -> 5533.04 | G18: =G12-G15 -> 6403.21 | H18: =H12-H15 -> 6598.22 | I18: =I12-I15 -> 8296.25 | J18: =J12-J15 -> 9919.9 | ... L18: =L12-L15 -> 9509.46
B19: EBITDA Margins | C19: =C18/C6 -> 0.26780326 | D19: =D18/D6 -> 0.25711832 | E19: =E18/E6 -> 0.26027007 | F19: =F18/F6 -> 0.27376041 | G19: =G18/G6 -> 0.29490498 | H19: =H18/H6 -> 0.22673298 | I19: =I18/I6 -> 0.24055057 | J19: =J18/J6 -> 0.27947529 | ... L19: =L18/L6 -> 0.26724323
B21: Interest | C21: ='Data Sheet'!B27 -> 37.33 | D21: ='Data Sheet'!C27 -> 41.47 | E21: ='Data Sheet'!D27 -> 110.47 | F21: ='Data Sheet'!E27 -> 102.33 | G21: ='Data Sheet'!F27 -> 91.63 | H21: ='Data Sheet'!G27 -> 95.41 | I21: ='Data Sheet'!H27 -> 144.45 | J21: ='Data Sheet'!I27 -> 205.17 | ... L21: ='Data Sheet'!K27 -> 195.41
B22: Interest % Sales | C22: =C21/C6 -> 0.0024784242 | D22: =D21/D6 -> 0.0024648505 | E22: =E21/E6 -> 0.0057416452 | F22: =F21/F6 -> 0.0050630218 | G22: =G21/G6 -> 0.0042200933 | H22: =H21/H6 -> 0.0032785499 | I22: =I21/I6 -> 0.0041883417 | J22: =J21/J6 -> 0.0057802947 | ... L22: =L21/L6 -> 0.005491584
B24: Depreciation | C24: ='Data Sheet'!B26 -> 334.79 | D24: ='Data Sheet'!C26 -> 360.47 | E24: ='Data Sheet'!D26 -> 622.14 | F24: ='Data Sheet'!E26 -> 780.5 | G24: ='Data Sheet'!F26 -> 791.27 | H24: ='Data Sheet'!G26 -> 816.36 | I24: ='Data Sheet'!H26 -> 858.02 | J24: ='Data Sheet'!I26 -> 853 | ... L24: ='Data Sheet'!K26 -> 1228.85
B25: Depreciation % Sales | C25: =C24/C6 -> 0.022227475 | D25: =D24/D6 -> 0.021425239 | E25: =E24/E6 -> 0.03233554 | F25: =F24/F6 -> 0.038617107 | G25: =G24/G6 -> 0.036442576 | H25: =H24/H6 -> 0.028052374 | I25: =I24/I6 -> 0.024878373 | J25: =J24/J6 -> 0.024031737 | ... L25: =L24/L6 -> 0.034534226
B27: Earnings before tax | C27: =IFERROR(C18-SUM(C21,C24),0) -> 3661.53 | D27: =IFERROR(D18-SUM(D21,D24),0) -> 3923.96 | E27: =IFERROR(E18-SUM(E21,E24),0) -> 4275.02 | F27: =IFERROR(F18-SUM(F21,F24),0) -> 4650.21 | G27: =IFERROR(G18-SUM(G21,G24),0) -> 5520.31 | H27: =IFERROR(H18-SUM(H21,H24),0) -> 5686.45 | I27: =IFERROR(I18-SUM(I21,I24),0) -> 7293.78 | J27: =IFERROR(J18-SUM(J21,J24),0) -> 8861.73 | ... L27: =IFERROR(L18-SUM(L21,L24),0) -> 8085.2
B28: EBT % Sales | C28: =C27/C6 -> 0.24309736 | D28: =D27/D6 -> 0.23322823 | E28: =E27/E6 -> 0.22219289 | F28: =F27/F6 -> 0.23008028 | G28: =G27/G6 -> 0.25424232 | H28: =H27/H6 -> 0.19540206 | I28: =I27/I6 -> 0.21148386 | J28: =J27/J6 -> 0.24966326 | ... L28: =L27/L6 -> 0.22721742
B30: Tax | C30: =IFERROR('Data Sheet'!B29,0) -> 943.29 | D30: =IFERROR('Data Sheet'!C29,0) -> 1040.96 | E30: =IFERROR('Data Sheet'!D29,0) -> 1098.06 | F30: =IFERROR('Data Sheet'!E29,0) -> 854.85 | G30: =IFERROR('Data Sheet'!F29,0) -> 1097.6 | H30: =IFERROR('Data Sheet'!G29,0) -> 1102.91 | I30: =IFERROR('Data Sheet'!H29,0) -> 1493.5 | J30: =IFERROR('Data Sheet'!I29,0) -> 1790.08 | ... L30: =IFERROR('Data Sheet'!K29,0) -> 1608.75
B31: Tax % Sales | C31: =C30/C27 -> 0.25762181 | D31: =D30/D27 -> 0.26528303 | E31: =E30/E27 -> 0.25685494 | F31: =F30/F27 -> 0.18383041 | G31: =G30/G27 -> 0.19882941 | H31: =H30/H27 -> 0.19395405 | I31: =I30/I27 -> 0.20476351 | J31: =J30/J27 -> 0.20200119 | ... L31: =L30/L27 -> 0.19897467
B33: Net Profit | C33: =C27-C30 -> 2718.24 | D33: =D27-D30 -> 2883 | E33: =E27-E30 -> 3176.96 | F33: =F27-F30 -> 3795.36 | G33: =G27-G30 -> 4422.71 | H33: =H27-H30 -> 4583.54 | I33: =I27-I30 -> 5800.28 | J33: =J27-J30 -> 7071.65 | ... L33: =L27-L30 -> 6476.45
B34: Net Margins | C34: =C33/C6 -> 0.18047018 | D34: =D33/D6 -> 0.17135674 | E34: =E33/E6 -> 0.16512155 | F34: =F33/F6 -> 0.18778453 | G34: =G33/G6 -> 0.20369146 | H34: =H33/H6 -> 0.15750304 | I34: =I33/I6 -> 0.16817968 | J34: =J33/J6 -> 0.19923098 | ... L34: =L33/L6 -> 0.18200691
B36: No. of Equity Shares | C36: =IFERROR('Data Sheet'!B93,0) -> 95.92 | D36: =IFERROR('Data Sheet'!C93,0) -> 95.92 | E36: =IFERROR('Data Sheet'!D93,0) -> 95.92 | F36: =IFERROR('Data Sheet'!E93,0) -> 95.92 | G36: =IFERROR('Data Sheet'!F93,0) -> 95.92 | H36: =IFERROR('Data Sheet'!G93,0) -> 95.92 | I36: =IFERROR('Data Sheet'!H93,0) -> 95.92 | J36: =IFERROR('Data Sheet'!I93,0) -> 95.92 | ... L36: =IFERROR('Data Sheet'!K93,0) -> 95.92
B38: Earnings per Share | C38: =IFERROR(C33/C36,0) -> 28.338616 | D38: =IFERROR(D33/D36,0) -> 30.056297 | E38: =IFERROR(E33/E36,0) -> 33.120934 | F38: =IFERROR(F33/F36,0) -> 39.567973 | G38: =IFERROR(G33/G36,0) -> 46.108319 | H38: =IFERROR(H33/H36,0) -> 47.785029 | I38: =IFERROR(I33/I36,0) -> 60.469975 | J38: =IFERROR(J33/J36,0) -> 73.724458 | ... L38: =IFERROR(L33/L36,0) -> 67.519287
B39: EPS Growth % | D39: =IFERROR((D38/C38)-1,0) -> 0.060612749 | E39: =IFERROR((E38/D38)-1,0) -> 0.10196323 | F39: =IFERROR((F38/E38)-1,0) -> 0.19465149 | G39: =IFERROR((G38/F38)-1,0) -> 0.16529394 | H39: =IFERROR((H38/G38)-1,0) -> 0.036364582 | I39: =IFERROR((I38/H38)-1,0) -> 0.26545858 | J39: =IFERROR((J38/I38)-1,0) -> 0.21919114 | K39: =IFERROR((K38/J38)-1,0) -> -0.15645288 | L39: =IFERROR((L38/K38)-1,0) -> 0.085692684
B41: Dividend per Share | C41: =IFERROR('Data Sheet'!B31/HistoricalFS!C38,0) -> 34.863383 | D41: =IFERROR('Data Sheet'!C31/HistoricalFS!D38,0) -> 27.764565 | E41: =IFERROR('Data Sheet'!D31/HistoricalFS!E38,0) -> 30.408563 | F41: =IFERROR('Data Sheet'!E31/HistoricalFS!F38,0) -> 29.090193 | G41: =IFERROR('Data Sheet'!F31/HistoricalFS!G38,0) -> 37.133646 | H41: =IFERROR('Data Sheet'!G31/HistoricalFS!H38,0) -> 38.440282 | I41: =IFERROR('Data Sheet'!H31/HistoricalFS!I38,0) -> 40.687134 | J41: =IFERROR('Data Sheet'!I31/HistoricalFS!J38,0) -> 43.325378 | ... L41: =IFERROR('Data Sheet'!K31/HistoricalFS!L38,0) -> 39.067356
B42: Dividened payout ratio | C42: =IFERROR(C41/C38,0) -> 1.230243 | D42: =IFERROR(D41/D38,0) -> 0.92375201 | E42: =IFERROR(E41/E38,0) -> 0.91810704 | F42: =IFERROR(F41/F38,0) -> 0.73519544 | G42: =IFERROR(G41/G38,0) -> 0.80535674 | H42: =IFERROR(H41/H38,0) -> 0.80444195 | I42: =IFERROR(I41/I38,0) -> 0.67284854 | J42: =IFERROR(J41/J38,0) -> 0.58766628 | ... L42: =IFERROR(L41/L38,0) -> 0.57861031
B44: Retained earnings | C44: =IFERROR(IF(C38>C41,(1-C42),0),0) -> 0 | D44: =IFERROR(1-D42,0) -> 0.07624799 | E44: =IFERROR(1-E42,0) -> 0.081892964 | F44: =IFERROR(1-F42,0) -> 0.26480456 | G44: =IFERROR(1-G42,0) -> 0.19464326 | H44: =IFERROR(1-H42,0) -> 0.19555805 | I44: =IFERROR(1-I42,0) -> 0.32715146 | J44: =IFERROR(1-J42,0) -> 0.41233372 | K44: =IFERROR(1-K42,0) -> 0.38493685 | L44: =IFERROR(1-L42,0) -> 0.42138969
A47: # | B47: Balance Sheet
B48: Equity Share Capital | C48: =IFERROR('Data Sheet'!B57,0) -> 95.92 | D48: =IFERROR('Data Sheet'!C57,0) -> 95.92 | E48: =IFERROR('Data Sheet'!D57,0) -> 95.92 | F48: =IFERROR('Data Sheet'!E57,0) -> 95.92 | G48: =IFERROR('Data Sheet'!F57,0) -> 95.92 | H48: =IFERROR('Data Sheet'!G57,0) -> 95.92 | I48: =IFERROR('Data Sheet'!H57,0) -> 95.92 | J48: =IFERROR('Data Sheet'!I57,0) -> 95.92 | ... L48: =IFERROR('Data Sheet'!K57,0) -> 95.92
B49: Reserves | C49: =IFERROR('Data Sheet'!B58,0) -> 7507.97 | D49: =IFERROR('Data Sheet'!C58,0) -> 8314.31 | E49: =IFERROR('Data Sheet'!D58,0) -> 9374.63 | F49: =IFERROR('Data Sheet'!E58,0) -> 10034.24 | G49: =IFERROR('Data Sheet'!F58,0) -> 12710.37 | H49: =IFERROR('Data Sheet'!G58,0) -> 13715.64 | I49: =IFERROR('Data Sheet'!H58,0) -> 15896.31 | J49: =IFERROR('Data Sheet'!I58,0) -> 18632.38 | ... L49: =IFERROR('Data Sheet'!K58,0) -> 21275.67
B50: Borrowings | C50: =IFERROR('Data Sheet'!B59,0) -> 560.34 | D50: =IFERROR('Data Sheet'!C59,0) -> 533.43 | E50: =IFERROR('Data Sheet'!D59,0) -> 1319.6 | F50: =IFERROR('Data Sheet'!E59,0) -> 1118.5 | G50: =IFERROR('Data Sheet'!F59,0) -> 1093.12 | H50: =IFERROR('Data Sheet'!G59,0) -> 1586.88 | I50: =IFERROR('Data Sheet'!H59,0) -> 1932.62 | J50: =IFERROR('Data Sheet'!I59,0) -> 2474.38 | ... L50: =IFERROR('Data Sheet'!K59,0) -> 3928.93
B51: Other Liabilities | C51: =IFERROR('Data Sheet'!B60,0) -> 4240.96 | D51: =IFERROR('Data Sheet'!C60,0) -> 4819.82 | E51: =IFERROR('Data Sheet'!D60,0) -> 5458.69 | F51: =IFERROR('Data Sheet'!E60,0) -> 4889.31 | G51: =IFERROR('Data Sheet'!F60,0) -> 6455.93 | H51: =IFERROR('Data Sheet'!G60,0) -> 7559.99 | I51: =IFERROR('Data Sheet'!H60,0) -> 7854.48 | J51: =IFERROR('Data Sheet'!I60,0) -> 8698.09 | ... L51: =IFERROR('Data Sheet'!K60,0) -> 9218.23
B52: Total Liabilities | C52: =IFERROR('Data Sheet'!B61,0) -> 12405.19 | D52: =IFERROR('Data Sheet'!C61,0) -> 13763.48 | E52: =IFERROR('Data Sheet'!D61,0) -> 16248.84 | F52: =IFERROR('Data Sheet'!E61,0) -> 16137.97 | G52: =IFERROR('Data Sheet'!F61,0) -> 20355.34 | H52: =IFERROR('Data Sheet'!G61,0) -> 22958.43 | I52: =IFERROR('Data Sheet'!H61,0) -> 25779.33 | J52: =IFERROR('Data Sheet'!I61,0) -> 29900.77 | ... L52: =IFERROR('Data Sheet'!K61,0) -> 34518.75
B54: Fixed Assets Net Block | C54: =IFERROR('Data Sheet'!B62,0) -> 3303.74 | D54: =IFERROR('Data Sheet'!C62,0) -> 3732.24 | E54: =IFERROR('Data Sheet'!D62,0) -> 6496.56 | F54: =IFERROR('Data Sheet'!E62,0) -> 6272.31 | G54: =IFERROR('Data Sheet'!F62,0) -> 5858.52 | H54: =IFERROR('Data Sheet'!G62,0) -> 5519.06 | I54: =IFERROR('Data Sheet'!H62,0) -> 5770.46 | J54: =IFERROR('Data Sheet'!I62,0) -> 7146.62 | ... L54: =IFERROR('Data Sheet'!K62,0) -> 9640.28
B55: Capital Work in Progress | C55: =IFERROR('Data Sheet'!B63,0) -> 257.54 | D55: =IFERROR('Data Sheet'!C63,0) -> 1405.11 | E55: =IFERROR('Data Sheet'!D63,0) -> 209.67 | F55: =IFERROR('Data Sheet'!E63,0) -> 140.24 | G55: =IFERROR('Data Sheet'!F63,0) -> 182.98 | H55: =IFERROR('Data Sheet'!G63,0) -> 426.43 | I55: =IFERROR('Data Sheet'!H63,0) -> 1019.59 | J55: =IFERROR('Data Sheet'!I63,0) -> 2698.37 | ... L55: =IFERROR('Data Sheet'!K63,0) -> 1848.67
B56: Investments | C56: =IFERROR('Data Sheet'!B64,0) -> 2651.99 | D56: =IFERROR('Data Sheet'!C64,0) -> 2140.7 | E56: =IFERROR('Data Sheet'!D64,0) -> 2568.58 | F56: =IFERROR('Data Sheet'!E64,0) -> 2018.85 | G56: =IFERROR('Data Sheet'!F64,0) -> 4736.8 | H56: =IFERROR('Data Sheet'!G64,0) -> 3247.53 | I56: =IFERROR('Data Sheet'!H64,0) -> 4261.71 | J56: =IFERROR('Data Sheet'!I64,0) -> 4587.92 | ... L56: =IFERROR('Data Sheet'!K64,0) -> 7061.74
B57: Other Assets | C57: =IFERROR('Data Sheet'!B65-SUM('Data Sheet'!B67:B69),0) -> 1317.17 | D57: =IFERROR('Data Sheet'!C65-SUM('Data Sheet'!C67:C69),0) -> 1691.84 | E57: =IFERROR('Data Sheet'!D65-SUM('Data Sheet'!D67:D69),0) -> 1471.96 | F57: =IFERROR('Data Sheet'!E65-SUM('Data Sheet'!E67:E69),0) -> 1738.71 | G57: =IFERROR('Data Sheet'!F65-SUM('Data Sheet'!F67:F69),0) -> 2565.52 | H57: =IFERROR('Data Sheet'!G65-SUM('Data Sheet'!G67:G69),0) -> 2876.66 | I57: =IFERROR('Data Sheet'!H65-SUM('Data Sheet'!H67:H69),0) -> 3036.17 | J57: =IFERROR('Data Sheet'!I65-SUM('Data Sheet'!I67:I69),0) -> 3571.39 | ... L57: =IFERROR('Data Sheet'!K65-SUM('Data Sheet'!K67:K69),0) -> 4688.89
B58: Total Non Current Assets | C58: =IFERROR(SUM(C54:C57),0) -> 7530.44 | D58: =IFERROR(SUM(D54:D57),0) -> 8969.89 | E58: =IFERROR(SUM(E54:E57),0) -> 10746.77 | F58: =IFERROR(SUM(F54:F57),0) -> 10170.11 | G58: =IFERROR(SUM(G54:G57),0) -> 13343.82 | H58: =IFERROR(SUM(H54:H57),0) -> 12069.68 | I58: =IFERROR(SUM(I54:I57),0) -> 14087.93 | J58: =IFERROR(SUM(J54:J57),0) -> 18004.3 | ... L58: =IFERROR(SUM(L54:L57),0) -> 23239.58
B60: Receivables | C60: =IFERROR('Data Sheet'!B67,0) -> 1446.6 | D60: =IFERROR('Data Sheet'!C67,0) -> 1730.63 | E60: =IFERROR('Data Sheet'!D67,0) -> 1907.33 | F60: =IFERROR('Data Sheet'!E67,0) -> 1795.22 | G60: =IFERROR('Data Sheet'!F67,0) -> 2602.17 | H60: =IFERROR('Data Sheet'!G67,0) -> 3871.44 | I60: =IFERROR('Data Sheet'!H67,0) -> 4636.94 | J60: =IFERROR('Data Sheet'!I67,0) -> 4889.05 | ... L60: =IFERROR('Data Sheet'!K67,0) -> 4461.8
B61: Inventory | C61: =IFERROR('Data Sheet'!B68,0) -> 2626.94 | D61: =IFERROR('Data Sheet'!C68,0) -> 2658.31 | E61: =IFERROR('Data Sheet'!D68,0) -> 3149.86 | F61: =IFERROR('Data Sheet'!E68,0) -> 3389.81 | G61: =IFERROR('Data Sheet'!F68,0) -> 3798.6 | H61: =IFERROR('Data Sheet'!G68,0) -> 6152.98 | I61: =IFERROR('Data Sheet'!H68,0) -> 6210.64 | J61: =IFERROR('Data Sheet'!I68,0) -> 5923.41 | ... L61: =IFERROR('Data Sheet'!K68,0) -> 5743.69
B62: Cash & Bank | C62: =IFERROR('Data Sheet'!B69,0) -> 801.21 | D62: =IFERROR('Data Sheet'!C69,0) -> 404.65 | E62: =IFERROR('Data Sheet'!D69,0) -> 444.88 | F62: =IFERROR('Data Sheet'!E69,0) -> 782.83 | G62: =IFERROR('Data Sheet'!F69,0) -> 610.75 | H62: =IFERROR('Data Sheet'!G69,0) -> 864.33 | I62: =IFERROR('Data Sheet'!H69,0) -> 843.82 | J62: =IFERROR('Data Sheet'!I69,0) -> 1084.01 | ... L62: =IFERROR('Data Sheet'!K69,0) -> 1073.68
B63: Total Current Assets | C63: =IFERROR(SUM(C60:C62),0) -> 4874.75 | D63: =IFERROR(SUM(D60:D62),0) -> 4793.59 | E63: =IFERROR(SUM(E60:E62),0) -> 5502.07 | F63: =IFERROR(SUM(F60:F62),0) -> 5967.86 | G63: =IFERROR(SUM(G60:G62),0) -> 7011.52 | H63: =IFERROR(SUM(H60:H62),0) -> 10888.75 | I63: =IFERROR(SUM(I60:I62),0) -> 11691.4 | J63: =IFERROR(SUM(J60:J62),0) -> 11896.47 | ... L63: =IFERROR(SUM(L60:L62),0) -> 11279.17
B65: Total Assets | C65: =IFERROR(SUM(C63,C58),0) -> 12405.19 | D65: =IFERROR(SUM(D63,D58),0) -> 13763.48 | E65: =IFERROR(SUM(E63,E58),0) -> 16248.84 | F65: =IFERROR(SUM(F63,F58),0) -> 16137.97 | G65: =IFERROR(SUM(G63,G58),0) -> 20355.34 | H65: =IFERROR(SUM(H63,H58),0) -> 22958.43 | I65: =IFERROR(SUM(I63,I58),0) -> 25779.33 | J65: =IFERROR(SUM(J63,J58),0) -> 29900.77 | ... L65: =IFERROR(SUM(L63,L58),0) -> 34518.75
A67: # | B67: Cash Flow Statements
B69: Cash from operating activities | C69: =IFERROR('Data Sheet'!B82,0) -> 1527.33 | D69: =IFERROR('Data Sheet'!C82,0) -> 2113.44 | E69: =IFERROR('Data Sheet'!D82,0) -> 2469.54 | F69: =IFERROR('Data Sheet'!E82,0) -> 3038.15 | G69: =IFERROR('Data Sheet'!F82,0) -> 3683.35 | H69: =IFERROR('Data Sheet'!G82,0) -> 986.49 | I69: =IFERROR('Data Sheet'!H82,0) -> 4193.43 | J69: =IFERROR('Data Sheet'!I82,0) -> 6103.6 | ... L69: =IFERROR('Data Sheet'!K82,0) -> 7088.18
B71: Cash from Investing Activity | C71: =IFERROR('Data Sheet'!B83,0) -> -681.11 | D71: =IFERROR('Data Sheet'!C83,0) -> -1556.14 | E71: =IFERROR('Data Sheet'!D83,0) -> -917.79 | F71: =IFERROR('Data Sheet'!E83,0) -> -517.91 | G71: =IFERROR('Data Sheet'!F83,0) -> -540.54 | H71: =IFERROR('Data Sheet'!G83,0) -> -316.75 | I71: =IFERROR('Data Sheet'!H83,0) -> -1282.34 | J71: =IFERROR('Data Sheet'!I83,0) -> -2548.48 | ... L71: =IFERROR('Data Sheet'!K83,0) -> -1328.23
B73: Cash from Financing Activity | C73: =IFERROR('Data Sheet'!B84,0) -> -756.43 | D73: =IFERROR('Data Sheet'!C84,0) -> -1379.14 | E73: =IFERROR('Data Sheet'!D84,0) -> -1117.46 | F73: =IFERROR('Data Sheet'!E84,0) -> -2871.46 | G73: =IFERROR('Data Sheet'!F84,0) -> -650.4 | H73: =IFERROR('Data Sheet'!G84,0) -> -1807.61 | I73: =IFERROR('Data Sheet'!H84,0) -> -2140.05 | J73: =IFERROR('Data Sheet'!I84,0) -> -2982.5 | ... L73: =IFERROR('Data Sheet'!K84,0) -> -2376.51
B75: Net Cash flow | C75: ='Data Sheet'!B85 -> 89.79 | D75: ='Data Sheet'!C85 -> -821.84 | E75: ='Data Sheet'!D85 -> 434.29 | F75: ='Data Sheet'!E85 -> -351.22 | G75: ='Data Sheet'!F85 -> 2492.41 | H75: ='Data Sheet'!G85 -> -1137.87 | I75: ='Data Sheet'!H85 -> 771.04 | J75: ='Data Sheet'!I85 -> 572.62 | ... L75: ='Data Sheet'!K85 -> 3383.44

Sheet Analysis-Historical FS
B2: Asian Paints Ltd. — Historical Financial Statement Analysis
B4: Purpose: To analyse historical revenue, profitability, balance-sheet and cash-flow trends and identify the key factors affecting the company's financial performance.
B6: Table 1: Executive summary
B8: Area | C8: FY25 | D8: FY26 | E8: Change | F8: What changed? | G8: Initial assessment
B9: Revenue from Operations | C9: ₹33,905.6 Cr | D9: ₹35,583.5 Cr | E9: 0.049 | F9: Revenue recovered after FY25 decline | G9: Moderate recovery
B10: Material Cost / Net Sales | C10: 0.577 | D10: 0.563 | E10: -1.4 pp | F10: Material-cost intensity reduced | G10: Positive
B11: Gross Margin | C11: 0.423 | D11: 0.437 | E11: +1.4 pp | F11: Gross profitability improved | G11: Positive
B12: EBITDA | C12: ₹6,326.9 Cr | D12: ₹7,113.1 Cr | E12: 0.124 | F12: EBITDA grew faster than revenue | G12: Strong positive
B13: Decorative & Home Décor Revenue | C13: ₹29,545.3 Cr | D13: ₹30,830.4 Cr | E13: 0.043 | F13: Core business recovered | G13: Moderate
B14: International Revenue | C14: ₹3,066.4 Cr | D14: ₹3,353.6 Cr | E14: 0.094 | F14: Faster growth than group | G14: Positive
B15: Industrial Revenue | C15: ₹1,185.7 Cr | D15: ₹1,332.4 Cr | E15: 0.124 | F15: Stronger growth, smaller base | G15: Positive
B18: Table 2: Revenue Analysis
B20: Metric | C20: FY25 | D20: FY26 | E20: Change | F20: Evidence / Reason | G20: Interpretation
B21: Consolidated Revenue | C21: ₹33,905.6 Cr | D21: ₹35,583.5 Cr | E21: 0.049 | F21: Recovery after FY25 decline | G21: Revenue growth recovered
B22: Decorative & Home Décor | C22: ₹29,545.3 Cr | D22: ₹30,830.4 Cr | E22: 0.043 | F22: Largest contributor; 86.8% of revenue | G22: Core business remained the main growth driver
B23: International | C23: ₹3,066.4 Cr | D23: ₹3,353.6 Cr | E23: 0.094 | F23: Growth led by South Asia | G23: Diversification supported growth
B24: Industrial | C24: ₹1,185.7 Cr | D24: ₹1,332.4 Cr | E24: 0.124 | F24: Faster-growing segment | G24: Positive but smaller contribution
B25: White Teak | C25: — | D25: ₹99 Cr | E25: -0.071 | F25: Subdued decorative-lighting demand and residual BIS-related disruption | G25: Weakness in this business
B26: Weatherseal | C26: — | D26: ₹75 Cr | E26: 0.421 | F26: Broad-based growth; stronger acceptance of Struva | G26: Strong growth within home improvement
B29: Revenue conclusion:
B31: Revenue recovered by 4.9% in FY26 after declining by 4.5% in FY25. The core Decorative & Home Décor segment grew at approximately 4.3%, while International and Industrial businesses grew faster.
B32: Therefore, the recovery was broad-based, although the core business remained the primary contributor because of its much larger revenue base.
B34: TABLE 3 — Cost & Profitability Bridge
B36: Metric | C36: FY25 | D36: FY26 | E36: Change | F36: What happened? | G36: Evidence / Reason | H36: Implication
B37: Revenue | C37: ₹33,905.6 Cr | D37: ₹35,583.5 Cr | E37: 0.049 | F37: Moderate growth | G37: Core + International + Industrial growth | H37: Top-line recovery
B38: Material Cost | C38: ₹19,515.8 Cr | D38: ₹20,001.8 Cr | E38: 0.025 | F38: Absolute cost increased | G38: Cost grew slower than revenue | H38: Better cost efficiency
B39: Material Cost / Sales | C39: 0.577 | D39: 0.563 | E39: -1.4 pp | F39: Cost intensity declined | G39: Benign raw-material environment | H39: Positive
B40: Gross Profit | C40: ₹14,281.6 Cr | D40: ₹15,514.6 Cr | E40: 0.086 | F40: Grew faster than revenue | G40: Lower material-cost intensity | H40: Better product-level profitability
B41: Gross Margin | C41: 0.423 | D41: 0.437 | E41: +1.4 pp | F41: Margin expanded | G41: Raw-material + efficiency factors | H41: Positive
B42: EBITDA | C42: ₹6,326.9 Cr | D42: ₹7,113.1 Cr | E42: 0.124 | F42: Grew much faster than revenue | G42: Cost discipline + efficiency | H42: Strong operating improvement
B43: EBITDA Margin | C43: ~18.7% | D43: ~20.0%* | E43: ↑ | F43: Operating profitability improved | G43: Management commentary | H43: Positive
B45: The most significant improvement in FY26 was profitability rather than sales growth. Although absolute material cost increased, it grew more slowly than revenue, reducing material cost as a percentage of sales from 57.7% to 56.3%.
B46: This supported gross-margin expansion and contributed to EBITDA growing substantially faster than revenue.
B48: TABLE 4 — Business Drivers & Risks
B50: Factor | C50: What the Annual Report says | D50: Type | E50: Financial relevance | F50: How I use it
B51: Innovation / Premiumisation | C51: Portfolio shaped through innovation-led premiumisation and differentiated propositions | D51: Strategic driver | E51: Can support product mix and competitiveness | F51: Supporting evidence
B52: New Products | C52: New products introduced across wood finishes, water-based products and value segments | D52: Strategic driver | E52: Portfolio expansion | F52: Supporting evidence
B53: Dealer / Network Initiatives | C53: Dealer engagement, store upgrades, Colour Ideas/Cubes, Beautiful Homes services | D53: Strategic driver | E53: Consumer reach/network effectiveness | F53: Supporting evidence
B54: B2B / Infrastructure | C54: Infrastructure and construction activity provide a structural opportunity | D54: Macro/industry driver | E54: Supports B2B demand potential | F54: Forward-looking support
B55: Raw Materials | C55: Raw-material costs largely stable/benign for most of FY26 | D55: Cost driver | E55: Supports gross margins | F55: Direct explanation of margin improvement
B56: Supply Chain | C56: Geopolitical disruptions created renewed volatility toward year-end | D56: Risk | E56: Could affect future costs/availability | F56: Risk
B57: International Markets | C57: Different countries faced different demand/macro conditions | D57: Risk + opportunity | E57: Affects consolidated revenue | F57: Diversification but volatility
B58: Competition | C58: Competitive intensity remains relevant | D58: Risk | E58: May affect pricing and market share | F58: Future risk
B60: Management continued innovation and portfolio expansion as part of its strategy; however, the report does not quantify the individual revenue contribution of these initiatives."
B62: TABLE 5 — Financial Health Indicators
B64: Area | C64: Historical observation | D64: Why it matters | E64: What I need to investigate
B65: Revenue | C65: FY26 recovery after FY25 decline | D65: Determines future growth base | E65: Sustainability of demand recovery
B66: Margins | C66: Gross margin improved | D66: Determines profitability | E66: Sustainability of raw-material benefit
B67: Debt | C67: Borrowings increased materially in FY26 | D67: Could affect financial risk | E67: Why debt increased and how funds were used
B68: Cash Generation | C68: CFO strengthened in FY26 | D68: Tests quality of earnings | E68: Working-capital drivers
B69: Capex | C69: Investment continues | D69: Can support future growth | E69: Capacity expansion and expected returns
B70: International | C70: Faster growth than consolidated revenue | D70: Diversification | E70: Sustainability across geographies
B73: Conclusion
B75: Asian Paints' FY26 performance represents a moderate recovery in revenue accompanied by a stronger improvement in profitability. Consolidated revenue increased by 4.9% after declining by 4.5% in FY25, with the core Decorative & Home Décor business growing by approximately 4.3% and International and Industrial businesses growing faster.
B77: The stronger aspect of FY26 performance was operating profitability. Material cost as a percentage of sales declined from 57.7% to 56.3%, while gross margin increased from 42.3% to 43.7%. Management attributes the improvement to cost discipline, efficiency initiatives and a largely benign raw-material environment during most of the year.
B79: Overall, the historical financials indicate improving cost efficiency and profitability, but only moderate top-line growth. Therefore, the key question for the forecast and valuation is whether the improvement in margins is sustainable and whether revenue growth can accelerate without a reversal in cost advantages.
B83: Value addition:
B84: The analysis goes beyond reporting historical financial figures by identifying the key drivers of revenue and profitability changes, distinguishing temporary factors from potential structural drivers, and identifying the questions that need to be tested in the forecast and valuation.
B87: Disclaimer: This analysis has been prepared for educational purposes only and is based on publicly available financial information and the assumptions stated in the model. It should not be construed as investment advice or a recommendation to buy or sell securities.

Sheet Ratio Analysis
B2: ="Ratio Analysis -"&'Data Sheet'!B1 -> Ratio Analysis -ASIAN PAINTS LTD
B3: Years | C3: ='Data Sheet'!B16 -> 42825 | D3: ='Data Sheet'!C16 -> 43190 | E3: ='Data Sheet'!D16 -> 43555 | F3: ='Data Sheet'!E16 -> 43921 | G3: ='Data Sheet'!F16 -> 44286 | H3: ='Data Sheet'!G16 -> 44651 | I3: ='Data Sheet'!H16 -> 45016 | J3: ='Data Sheet'!I16 -> 45382 | ... L3: ='Data Sheet'!K16 -> 46112 | M3: Trend | N3: Mean | O3: Median
B5: Sales Growth | D5: =IFERROR(HistoricalFS!D7,0) -> 0.11702039 | E5: =IFERROR(HistoricalFS!E7,0) -> 0.14357472 | F5: =IFERROR(HistoricalFS!F7,0) -> 0.050473671 | G5: =IFERROR(HistoricalFS!G7,0) -> 0.074292288 | H5: =IFERROR(HistoricalFS!H7,0) -> 0.34028285 | I5: =IFERROR(HistoricalFS!I7,0) -> 0.18512278 | J5: =IFERROR(HistoricalFS!J7,0) -> 0.029173127 | K5: =IFERROR(HistoricalFS!K7,0) -> -0.044770308 | L5: =IFERROR(HistoricalFS!L7,0) -> 0.049487961 | N5: =IFERROR(AVERAGE(D5:L5),0) -> 0.10496194 | O5: =IFERROR(MEDIAN(C5:L5),0) -> 0.074292288
B6: EBITDA Growth | D6: =IFERROR((HistoricalFS!D18/HistoricalFS!C18)-1,0) -> 0.072452989 | E6: =IFERROR((HistoricalFS!E18/HistoricalFS!D18)-1,0) -> 0.15759264 | F6: =IFERROR((HistoricalFS!F18/HistoricalFS!E18)-1,0) -> 0.10492189 | G6: =IFERROR((HistoricalFS!G18/HistoricalFS!F18)-1,0) -> 0.15726798 | H6: =IFERROR((HistoricalFS!H18/HistoricalFS!G18)-1,0) -> 0.030455037 | I6: =IFERROR((HistoricalFS!I18/HistoricalFS!H18)-1,0) -> 0.25734668 | J6: =IFERROR((HistoricalFS!J18/HistoricalFS!I18)-1,0) -> 0.1957089 | K6: =IFERROR((HistoricalFS!K18/HistoricalFS!J18)-1,0) -> -0.1318471 | L6: =IFERROR((HistoricalFS!L18/HistoricalFS!K18)-1,0) -> 0.10421169 | N6: =IFERROR(AVERAGE(D6:L6),0) -> 0.10534563 | O6: =IFERROR(MEDIAN(C6:L6),0) -> 0.10492189
B7: EBT Growth | D7: =IFERROR((HistoricalFS!D27/HistoricalFS!C27)-1,0) -> 0.071672224 | E7: =IFERROR((HistoricalFS!E27/HistoricalFS!D27)-1,0) -> 0.089465744 | F7: =IFERROR((HistoricalFS!F27/HistoricalFS!E27)-1,0) -> 0.087763332 | G7: =IFERROR((HistoricalFS!G27/HistoricalFS!F27)-1,0) -> 0.18710983 | H7: =IFERROR((HistoricalFS!H27/HistoricalFS!G27)-1,0) -> 0.030096136 | I7: =IFERROR((HistoricalFS!I27/HistoricalFS!H27)-1,0) -> 0.28265966 | J7: =IFERROR((HistoricalFS!J27/HistoricalFS!I27)-1,0) -> 0.21497084 | K7: =IFERROR((HistoricalFS!K27/HistoricalFS!J27)-1,0) -> -0.16961699 | L7: =IFERROR((HistoricalFS!L27/HistoricalFS!K27)-1,0) -> 0.098737129 | N7: =IFERROR(AVERAGE(D7:L7),0) -> 0.099206433 | O7: =IFERROR(MEDIAN(C7:L7),0) -> 0.089465744
B8: Net Profit Growth | D8: =IFERROR((HistoricalFS!D33/HistoricalFS!C33)-1,0) -> 0.060612749 | E8: =IFERROR((HistoricalFS!E33/HistoricalFS!D33)-1,0) -> 0.10196323 | F8: =IFERROR((HistoricalFS!F33/HistoricalFS!E33)-1,0) -> 0.19465149 | G8: =IFERROR((HistoricalFS!G33/HistoricalFS!F33)-1,0) -> 0.16529394 | H8: =IFERROR((HistoricalFS!H33/HistoricalFS!G33)-1,0) -> 0.036364582 | I8: =IFERROR((HistoricalFS!I33/HistoricalFS!H33)-1,0) -> 0.26545858 | J8: =IFERROR((HistoricalFS!J33/HistoricalFS!I33)-1,0) -> 0.21919114 | K8: =IFERROR((HistoricalFS!K33/HistoricalFS!J33)-1,0) -> -0.15645288 | L8: =IFERROR((HistoricalFS!L33/HistoricalFS!K33)-1,0) -> 0.085692684 | N8: =IFERROR(AVERAGE(D8:L8),0) -> 0.10808617 | O8: =IFERROR(MEDIAN(C8:L8),0) -> 0.10196323
B9: Dividend Growth | D9: =IFERROR(HistoricalFS!D41/HistoricalFS!C41-1,0) -> -0.20361817 | E9: =IFERROR(HistoricalFS!E41/HistoricalFS!D41-1,0) -> 0.095229224 | F9: =IFERROR(HistoricalFS!F41/HistoricalFS!E41-1,0) -> -0.043355195 | G9: =IFERROR(HistoricalFS!G41/HistoricalFS!F41-1,0) -> 0.27650047 | H9: =IFERROR(HistoricalFS!H41/HistoricalFS!G41-1,0) -> 0.035187396 | I9: =IFERROR(HistoricalFS!I41/HistoricalFS!H41-1,0) -> 0.058450465 | J9: =IFERROR(HistoricalFS!J41/HistoricalFS!I41-1,0) -> 0.064842205 | K9: =IFERROR(HistoricalFS!K41/HistoricalFS!J41-1,0) -> -0.1171269 | L9: =IFERROR(HistoricalFS!L41/HistoricalFS!K41-1,0) -> 0.021347126 | N9: =IFERROR(AVERAGE(D9:L9),0) -> 0.020828515 | O9: =IFERROR(MEDIAN(C9:L9),0) -> 0.035187396
B11: Gross Margin | C11: =IFERROR(HistoricalFS!C13,0) -> 0.4228671 | D11: =IFERROR(HistoricalFS!D13,0) -> 0.40133436 | E11: =IFERROR(HistoricalFS!E13,0) -> 0.39381283 | F11: =IFERROR(HistoricalFS!F13,0) -> 0.41682231 | G11: =IFERROR(HistoricalFS!G13,0) -> 0.42487999 | H11: =IFERROR(HistoricalFS!H13,0) -> 0.35411913 | I11: =IFERROR(HistoricalFS!I13,0) -> 0.36992814 | J11: =IFERROR(HistoricalFS!J13,0) -> 0.41751719 | ... L11: =IFERROR(HistoricalFS!L13,0) -> 0.41883523 | N11: =IFERROR(AVERAGE(C11:L11),0) -> 0.40262475 | O11: =IFERROR(MEDIAN(C11:L11),0) -> 0.41147676
B12: EBITDA Margin | C12: =IFERROR(HistoricalFS!C19,0) -> 0.26780326 | D12: =IFERROR(HistoricalFS!D19,0) -> 0.25711832 | E12: =IFERROR(HistoricalFS!E19,0) -> 0.26027007 | F12: =IFERROR(HistoricalFS!F19,0) -> 0.27376041 | G12: =IFERROR(HistoricalFS!G19,0) -> 0.29490498 | H12: =IFERROR(HistoricalFS!H19,0) -> 0.22673298 | I12: =IFERROR(HistoricalFS!I19,0) -> 0.24055057 | J12: =IFERROR(HistoricalFS!J19,0) -> 0.27947529 | ... L12: =IFERROR(HistoricalFS!L19,0) -> 0.26724323 | N12: =IFERROR(AVERAGE(C12:L12),0) -> 0.2621858 | O12: =IFERROR(MEDIAN(C12:L12),0) -> 0.26375665
B13: EBIT Margin | C13: =IFERROR((HistoricalFS!C18-HistoricalFS!C24)/HistoricalFS!C6,0) -> 0.24557578 | D13: =IFERROR((HistoricalFS!D18-HistoricalFS!D24)/HistoricalFS!D6,0) -> 0.23569308 | E13: =IFERROR((HistoricalFS!E18-HistoricalFS!E24)/HistoricalFS!E6,0) -> 0.22793453 | F13: =IFERROR((HistoricalFS!F18-HistoricalFS!F24)/HistoricalFS!F6,0) -> 0.2351433 | G13: =IFERROR((HistoricalFS!G18-HistoricalFS!G24)/HistoricalFS!G6,0) -> 0.25846241 | H13: =IFERROR((HistoricalFS!H18-HistoricalFS!H24)/HistoricalFS!H6,0) -> 0.19868061 | I13: =IFERROR((HistoricalFS!I18-HistoricalFS!I24)/HistoricalFS!I6,0) -> 0.2156722 | J13: =IFERROR((HistoricalFS!J18-HistoricalFS!J24)/HistoricalFS!J6,0) -> 0.25544355 | ... L13: =IFERROR((HistoricalFS!L18-HistoricalFS!L24)/HistoricalFS!L6,0) -> 0.232709 | N13: =IFERROR(AVERAGE(C13:L13),0) -> 0.23290429 | O13: =IFERROR(MEDIAN(C13:L13),0) -> 0.23392615
B14: EBT Margin | C14: =IFERROR(HistoricalFS!C28,0) -> 0.24309736 | D14: =IFERROR(HistoricalFS!D28,0) -> 0.23322823 | E14: =IFERROR(HistoricalFS!E28,0) -> 0.22219289 | F14: =IFERROR(HistoricalFS!F28,0) -> 0.23008028 | G14: =IFERROR(HistoricalFS!G28,0) -> 0.25424232 | H14: =IFERROR(HistoricalFS!H28,0) -> 0.19540206 | I14: =IFERROR(HistoricalFS!I28,0) -> 0.21148386 | J14: =IFERROR(HistoricalFS!J28,0) -> 0.24966326 | ... L14: =IFERROR(HistoricalFS!L28,0) -> 0.22721742 | N14: =IFERROR(AVERAGE(C14:L14),0) -> 0.22836404 | O14: =IFERROR(MEDIAN(C14:L14),0) -> 0.22864885
B15: Net Profit Margin | C15: =IFERROR(HistoricalFS!C34,0) -> 0.18047018 | D15: =IFERROR(HistoricalFS!D34,0) -> 0.17135674 | E15: =IFERROR(HistoricalFS!E34,0) -> 0.16512155 | F15: =IFERROR(HistoricalFS!F34,0) -> 0.18778453 | G15: =IFERROR(HistoricalFS!G34,0) -> 0.20369146 | H15: =IFERROR(HistoricalFS!H34,0) -> 0.15750304 | I15: =IFERROR(HistoricalFS!I34,0) -> 0.16817968 | J15: =IFERROR(HistoricalFS!J34,0) -> 0.19923098 | ... L15: =IFERROR(HistoricalFS!L34,0) -> 0.18200691 | N15: =IFERROR(AVERAGE(C15:L15),0) -> 0.17912826 | O15: =IFERROR(MEDIAN(C15:L15),0) -> 0.17820384
B17: SalesExpenses%Sales | C17: =IFERROR(HistoricalFS!C16,0) -> 0.15506384 | D17: =IFERROR(HistoricalFS!D16,0) -> 0.14421604 | E17: =IFERROR(HistoricalFS!E16,0) -> 0.13354276 | F17: =IFERROR(HistoricalFS!F16,0) -> 0.14306191 | G17: =IFERROR(HistoricalFS!G16,0) -> 0.12997501 | H17: =IFERROR(HistoricalFS!H16,0) -> 0.12738615 | I17: =IFERROR(HistoricalFS!I16,0) -> 0.12937757 | J17: =IFERROR(HistoricalFS!J16,0) -> 0.1380419 | ... L17: =IFERROR(HistoricalFS!L16,0) -> 0.151592 | N17: =IFERROR(AVERAGE(C17:L17),0) -> 0.14043895 | O17: =IFERROR(MEDIAN(C17:L17),0) -> 0.1405519
B18: Depreciation%Sales | C18: =IFERROR(HistoricalFS!C25,0) -> 0.022227475 | D18: =IFERROR(HistoricalFS!D25,0) -> 0.021425239 | E18: =IFERROR(HistoricalFS!E25,0) -> 0.03233554 | F18: =IFERROR(HistoricalFS!F25,0) -> 0.038617107 | G18: =IFERROR(HistoricalFS!G25,0) -> 0.036442576 | H18: =IFERROR(HistoricalFS!H25,0) -> 0.028052374 | I18: =IFERROR(HistoricalFS!I25,0) -> 0.024878373 | J18: =IFERROR(HistoricalFS!J25,0) -> 0.024031737 | ... L18: =IFERROR(HistoricalFS!L25,0) -> 0.034534226 | N18: =IFERROR(AVERAGE(C18:L18),0) -> 0.029281514 | O18: =IFERROR(MEDIAN(C18:L18),0) -> 0.029161436
B19: OperatingIncome%Sales | C19: =C13 -> 0.24557578 | D19: =D13 -> 0.23569308 | E19: =E13 -> 0.22793453 | F19: =F13 -> 0.2351433 | G19: =G13 -> 0.25846241 | H19: =H13 -> 0.19868061 | I19: =I13 -> 0.2156722 | J19: =J13 -> 0.25544355 | ... L19: =L13 -> 0.232709 | N19: =IFERROR(AVERAGE(C19:L19),0) -> 0.23290429 | O19: =IFERROR(MEDIAN(C19:L19),0) -> 0.23392615
B21: Return on Capital Employed | C21: =IFERROR((HistoricalFS!C18-HistoricalFS!C24)/SUM(HistoricalFS!C48:C50),0) -> 0.45305681 | D21: =IFERROR((HistoricalFS!D18-HistoricalFS!D24)/SUM(HistoricalFS!D48:D50),0) -> 0.44337889 | E21: =IFERROR((HistoricalFS!E18-HistoricalFS!E24)/SUM(HistoricalFS!E48:E50),0) -> 0.40643457 | F21: =IFERROR((HistoricalFS!F18-HistoricalFS!F24)/SUM(HistoricalFS!F48:F50),0) -> 0.42249832 | G21: =IFERROR((HistoricalFS!G18-HistoricalFS!G24)/SUM(HistoricalFS!G48:G50),0) -> 0.40375383 | H21: =IFERROR((HistoricalFS!H18-HistoricalFS!H24)/SUM(HistoricalFS!H48:H50),0) -> 0.37548349 | I21: =IFERROR((HistoricalFS!I18-HistoricalFS!I24)/SUM(HistoricalFS!I48:I50),0) -> 0.41496749 | J21: =IFERROR((HistoricalFS!J18-HistoricalFS!J24)/SUM(HistoricalFS!J48:J50),0) -> 0.4276299 | ... L21: =IFERROR((HistoricalFS!L18-HistoricalFS!L24)/SUM(HistoricalFS!L48:L50),0) -> 0.32729011 | N21: =IFERROR(AVERAGE(C21:L21),0) -> 0.40242221 | O21: =IFERROR(MEDIAN(C21:L21),0) -> 0.41070103
B22: Retained Earnings % | C22: =IFERROR(HistoricalFS!C44,0) -> 0 | D22: =IFERROR(HistoricalFS!D44,0) -> 0.07624799 | E22: =IFERROR(HistoricalFS!E44,0) -> 0.081892964 | F22: =IFERROR(HistoricalFS!F44,0) -> 0.26480456 | G22: =IFERROR(HistoricalFS!G44,0) -> 0.19464326 | H22: =IFERROR(HistoricalFS!H44,0) -> 0.19555805 | I22: =IFERROR(HistoricalFS!I44,0) -> 0.32715146 | J22: =IFERROR(HistoricalFS!J44,0) -> 0.41233372 | ... L22: =IFERROR(HistoricalFS!L44,0) -> 0.42138969 | N22: =IFERROR(AVERAGE(C22:L22),0) -> 0.23589585 | O22: =IFERROR(MEDIAN(C22:L22),0) -> 0.23018131
B23: Return on Equity% | C23: =IFERROR(HistoricalFS!C33/SUM(HistoricalFS!C48:C49),0) -> 0.35748018 | D23: =IFERROR(HistoricalFS!D33/SUM(HistoricalFS!D48:D49),0) -> 0.34279681 | E23: =IFERROR(HistoricalFS!E33/SUM(HistoricalFS!E48:E49),0) -> 0.33545676 | F23: =IFERROR(HistoricalFS!F33/SUM(HistoricalFS!F48:F49),0) -> 0.37465943 | G23: =IFERROR(HistoricalFS!G33/SUM(HistoricalFS!G48:G49),0) -> 0.34535451 | H23: =IFERROR(HistoricalFS!H33/SUM(HistoricalFS!H48:H49),0) -> 0.33186258 | I23: =IFERROR(HistoricalFS!I33/SUM(HistoricalFS!I48:I49),0) -> 0.36269363 | J23: =IFERROR(HistoricalFS!J33/SUM(HistoricalFS!J48:J49),0) -> 0.37759167 | ... L23: =IFERROR(HistoricalFS!L33/SUM(HistoricalFS!L48:L49),0) -> 0.30304016 | N23: =IFERROR(AVERAGE(C23:L23),0) -> 0.34384269 | O23: =IFERROR(MEDIAN(C23:L23),0) -> 0.34407566
B24: Self sustained growth rate | C24: =IFERROR(C22*C23,0) -> 0 | D24: =IFERROR(D22*D23,0) -> 0.026137568 | E24: =IFERROR(E22*E23,0) -> 0.027471548 | F24: =IFERROR(F22*F23,0) -> 0.099211527 | G24: =IFERROR(G22*G23,0) -> 0.067220928 | H24: =IFERROR(H22*H23,0) -> 0.0648984 | I24: =IFERROR(I22*I23,0) -> 0.11865575 | J24: =IFERROR(J22*J23,0) -> 0.15569378 | ... L24: =IFERROR(L22*L23,0) -> 0.127698 | N24: =IFERROR(AVERAGE(C24:L24),0) -> 0.080535217 | O24: =IFERROR(MEDIAN(C24:L24),0) -> 0.083216227
B25: Interest Coverage Ratio | C25: =IFERROR((HistoricalFS!C18-HistoricalFS!C24)/HistoricalFS!C21,0) -> 99.085454 | D25: =IFERROR((HistoricalFS!D18-HistoricalFS!D24)/HistoricalFS!D21,0) -> 95.621654 | E25: =IFERROR((HistoricalFS!E18-HistoricalFS!E24)/HistoricalFS!E21,0) -> 39.69847 | F25: =IFERROR((HistoricalFS!F18-HistoricalFS!F24)/HistoricalFS!F21,0) -> 46.443272 | G25: =IFERROR((HistoricalFS!G18-HistoricalFS!G24)/HistoricalFS!G21,0) -> 61.245662 | H25: =IFERROR((HistoricalFS!H18-HistoricalFS!H24)/HistoricalFS!H21,0) -> 60.600147 | I25: =IFERROR((HistoricalFS!I18-HistoricalFS!I24)/HistoricalFS!I21,0) -> 51.493458 | J25: =IFERROR((HistoricalFS!J18-HistoricalFS!J24)/HistoricalFS!J21,0) -> 44.192133 | ... L25: =IFERROR((HistoricalFS!L18-HistoricalFS!L24)/HistoricalFS!L21,0) -> 42.375569 | N25: =IFERROR(AVERAGE(C25:L25),0) -> 57.416984 | O25: =IFERROR(MEDIAN(C25:L25),0) -> 48.968365
B27: Debtor Turnover Ratio | C27: =IFERROR(HistoricalFS!C6/HistoricalFS!C60,0) -> 10.411994 | D27: =IFERROR(HistoricalFS!D6/HistoricalFS!D60,0) -> 9.7216332 | E27: =IFERROR(HistoricalFS!E6/HistoricalFS!E60,0) -> 10.087468 | F27: =IFERROR(HistoricalFS!F6/HistoricalFS!F60,0) -> 11.258369 | G27: =IFERROR(HistoricalFS!G6/HistoricalFS!G60,0) -> 8.344109 | H27: =IFERROR(HistoricalFS!H6/HistoricalFS!H60,0) -> 7.5169136 | I27: =IFERROR(HistoricalFS!I6/HistoricalFS!I60,0) -> 7.4377909 | J27: =IFERROR(HistoricalFS!J6/HistoricalFS!J60,0) -> 7.2600464 | ... L27: =IFERROR(HistoricalFS!L6/HistoricalFS!L60,0) -> 7.9751535 | N27: =IFERROR(AVERAGE(C27:L27),0) -> 8.7873554 | O27: =IFERROR(MEDIAN(C27:L27),0) -> 8.1596312
B28: Creditor Turnover Ratio | C28: =IFERROR(HistoricalFS!C6/HistoricalFS!C51,0) -> 3.551552 | D28: =IFERROR(HistoricalFS!D6/HistoricalFS!D51,0) -> 3.4907009 | E28: =IFERROR(HistoricalFS!E6/HistoricalFS!E51,0) -> 3.524679 | F28: =IFERROR(HistoricalFS!F6/HistoricalFS!F51,0) -> 4.1337633 | G28: =IFERROR(HistoricalFS!G6/HistoricalFS!G51,0) -> 3.3632319 | H28: =IFERROR(HistoricalFS!H6/HistoricalFS!H51,0) -> 3.8493808 | I28: =IFERROR(HistoricalFS!I6/HistoricalFS!I51,0) -> 4.390945 | J28: =IFERROR(HistoricalFS!J6/HistoricalFS!J51,0) -> 4.0807499 | ... L28: =IFERROR(HistoricalFS!L6/HistoricalFS!L51,0) -> 3.8601272 | N28: =IFERROR(AVERAGE(C28:L28),0) -> 3.8158002 | O28: =IFERROR(MEDIAN(C28:L28),0) -> 3.854754
B29: Inventory Turnover | C29: =IFERROR(HistoricalFS!C9/HistoricalFS!C61,0) -> 3.3090859 | D29: =IFERROR(HistoricalFS!D9/HistoricalFS!D61,0) -> 3.7889787 | E29: =IFERROR(HistoricalFS!E9/HistoricalFS!E61,0) -> 3.7027423 | F29: =IFERROR(HistoricalFS!F9/HistoricalFS!F61,0) -> 3.4771123 | G29: =IFERROR(HistoricalFS!G9/HistoricalFS!G61,0) -> 3.2873848 | H29: =IFERROR(HistoricalFS!H9/HistoricalFS!H61,0) -> 3.0547735 | I29: =IFERROR(HistoricalFS!I9/HistoricalFS!I61,0) -> 3.498881 | J29: =IFERROR(HistoricalFS!J9/HistoricalFS!J61,0) -> 3.4904 | ... L29: =IFERROR(HistoricalFS!L9/HistoricalFS!L61,0) -> 3.6004555 | N29: =IFERROR(AVERAGE(C29:L29),0) -> 3.4206492 | O29: =IFERROR(MEDIAN(C29:L29),0) -> 3.4837561
B30: Fixed Asset Turnover | C30: =IFERROR(HistoricalFS!C6/HistoricalFS!C54,0) -> 4.5590724 | D30: =IFERROR(HistoricalFS!D6/HistoricalFS!D54,0) -> 4.5078961 | E30: =IFERROR(HistoricalFS!E6/HistoricalFS!E54,0) -> 2.9615874 | F30: =IFERROR(HistoricalFS!F6/HistoricalFS!F54,0) -> 3.2222977 | G30: =IFERROR(HistoricalFS!G6/HistoricalFS!G54,0) -> 3.7061903 | H30: =IFERROR(HistoricalFS!H6/HistoricalFS!H54,0) -> 5.2728689 | I30: =IFERROR(HistoricalFS!I6/HistoricalFS!I54,0) -> 5.9767488 | J30: =IFERROR(HistoricalFS!J6/HistoricalFS!J54,0) -> 4.9666458 | ... L30: =IFERROR(HistoricalFS!L6/HistoricalFS!L54,0) -> 3.6911314 | N30: =IFERROR(AVERAGE(C30:L30),0) -> 4.2541798 | O30: =IFERROR(MEDIAN(C30:L30),0) -> 4.1070432
B31: Capital Turnover Ratio | C31: =IFERROR(HistoricalFS!C6/SUM(HistoricalFS!C49:C50),0) -> 1.8668085 | D31: =IFERROR(HistoricalFS!D6/SUM(HistoricalFS!D49:D50),0) -> 1.9015647 | E31: =IFERROR(HistoricalFS!E6/SUM(HistoricalFS!E49:E50),0) -> 1.7991132 | F31: =IFERROR(HistoricalFS!F6/SUM(HistoricalFS!F49:F50),0) -> 1.8122228 | G31: =IFERROR(HistoricalFS!G6/SUM(HistoricalFS!G49:G50),0) -> 1.5729928 | H31: =IFERROR(HistoricalFS!H6/SUM(HistoricalFS!H49:H50),0) -> 1.9017312 | I31: =IFERROR(HistoricalFS!I6/SUM(HistoricalFS!I49:I50),0) -> 1.9344173 | J31: =IFERROR(HistoricalFS!J6/SUM(HistoricalFS!J49:J50),0) -> 1.6816759 | ... L31: =IFERROR(HistoricalFS!L6/SUM(HistoricalFS!L49:L50),0) -> 1.4117875 | N31: =IFERROR(AVERAGE(C31:L31),0) -> 1.7452442 | O31: =IFERROR(MEDIAN(C31:L31),0) -> 1.805668
B33: Debtor Days | C33: =IFERROR(365/C27,0) -> 35.055726 | D33: =IFERROR(365/D27,0) -> 37.545132 | E33: =IFERROR(365/E27,0) -> 36.183511 | F33: =IFERROR(365/F27,0) -> 32.420325 | G33: =IFERROR(365/G27,0) -> 43.743436 | H33: =IFERROR(365/H27,0) -> 48.557163 | I33: =IFERROR(365/I27,0) -> 49.073711 | J33: =IFERROR(365/J27,0) -> 50.275161 | ... L33: =IFERROR(365/L27,0) -> 45.767144 | N33: =IFERROR(AVERAGE(C33:L33),0) -> 42.505852 | O33: =IFERROR(MEDIAN(C33:L33),0) -> 44.75529
B34: Payable Days | C34: =IFERROR(365/C28,0) -> 102.77197 | D34: =IFERROR(365/D28,0) -> 104.56353 | E34: =IFERROR(365/E28,0) -> 103.55553 | F34: =IFERROR(365/F28,0) -> 88.297268 | G34: =IFERROR(365/G28,0) -> 108.52656 | H34: =IFERROR(365/H28,0) -> 94.820446 | I34: =IFERROR(365/I28,0) -> 83.125613 | J34: =IFERROR(365/J28,0) -> 89.444344 | ... L34: =IFERROR(365/L28,0) -> 94.55647 | N34: =IFERROR(AVERAGE(C34:L34),0) -> 96.294361 | O34: =IFERROR(MEDIAN(C34:L34),0) -> 94.688458
B35: Inventory Days | C35: =IFERROR(365/C29,0) -> 110.30237 | D35: =IFERROR(365/D29,0) -> 96.332027 | E35: =IFERROR(365/E29,0) -> 98.575587 | F35: =IFERROR(365/F29,0) -> 104.97216 | G35: =IFERROR(365/G29,0) -> 111.03051 | H35: =IFERROR(365/H29,0) -> 119.48513 | I35: =IFERROR(365/I29,0) -> 104.31907 | J35: =IFERROR(365/J29,0) -> 104.57254 | ... L35: =IFERROR(365/L29,0) -> 101.37606 | N35: =IFERROR(AVERAGE(C35:L35),0) -> 107.2767 | O35: =IFERROR(MEDIAN(C35:L35),0) -> 104.77235
B36: Cash Conversion cycle(in days) | C36: =SUM(C33,C35)-C34 -> 42.586122 | D36: =SUM(D33,D35)-D34 -> 29.313631 | E36: =SUM(E33,E35)-E34 -> 31.203568 | F36: =SUM(F33,F35)-F34 -> 49.095221 | G36: =SUM(G33,G35)-G34 -> 46.24738 | H36: =SUM(H33,H35)-H34 -> 73.221846 | I36: =SUM(I33,I35)-I34 -> 70.267166 | J36: =SUM(J33,J35)-J34 -> 65.403359 | ... L36: =SUM(L33,L35)-L34 -> 52.586737 | N36: =IFERROR(AVERAGE(C36:L36),0) -> 53.48819 | O36: =IFERROR(MEDIAN(C36:L36),0) -> 50.840979
B38: CFO/Sales | C38: =IFERROR(HistoricalFS!C69/HistoricalFS!C6,0) -> 0.10140294 | D38: =IFERROR(HistoricalFS!D69/HistoricalFS!D6,0) -> 0.12561644 | E38: =IFERROR(HistoricalFS!E69/HistoricalFS!E6,0) -> 0.1283536 | F38: =IFERROR(HistoricalFS!F69/HistoricalFS!F6,0) -> 0.15031975 | G38: =IFERROR(HistoricalFS!G69/HistoricalFS!G6,0) -> 0.16963965 | H38: =IFERROR(HistoricalFS!H69/HistoricalFS!H6,0) -> 0.033898509 | I38: =IFERROR(HistoricalFS!I69/HistoricalFS!I6,0) -> 0.12158891 | J38: =IFERROR(HistoricalFS!J69/HistoricalFS!J6,0) -> 0.17195792 | ... L38: =IFERROR(HistoricalFS!L69/HistoricalFS!L6,0) -> 0.19919828 | N38: =IFERROR(AVERAGE(C38:L38),0) -> 0.13324547 | O38: =IFERROR(MEDIAN(C38:L38),0) -> 0.12941613
B39: CFO/Total Assets | C39: =IFERROR(HistoricalFS!C69/HistoricalFS!C65,0) -> 0.12312024 | D39: =IFERROR(HistoricalFS!D69/HistoricalFS!D65,0) -> 0.15355419 | E39: =IFERROR(HistoricalFS!E69/HistoricalFS!E65,0) -> 0.15198254 | F39: =IFERROR(HistoricalFS!F69/HistoricalFS!F65,0) -> 0.18826098 | G39: =IFERROR(HistoricalFS!G69/HistoricalFS!G65,0) -> 0.18095252 | H39: =IFERROR(HistoricalFS!H69/HistoricalFS!H65,0) -> 0.042968531 | I39: =IFERROR(HistoricalFS!I69/HistoricalFS!I65,0) -> 0.16266637 | J39: =IFERROR(HistoricalFS!J69/HistoricalFS!J65,0) -> 0.20412852 | ... L39: =IFERROR(HistoricalFS!L69/HistoricalFS!L65,0) -> 0.20534289 | N39: =IFERROR(AVERAGE(C39:L39),0) -> 0.15587163 | O39: =IFERROR(MEDIAN(C39:L39),0) -> 0.15811028
B40: CFO/Total Debt | C40: =IFERROR(HistoricalFS!C69/HistoricalFS!C50,0) -> 2.7257201 | D40: =IFERROR(HistoricalFS!D69/HistoricalFS!D50,0) -> 3.9619819 | E40: =IFERROR(HistoricalFS!E69/HistoricalFS!E50,0) -> 1.8714307 | F40: =IFERROR(HistoricalFS!F69/HistoricalFS!F50,0) -> 2.7162718 | G40: =IFERROR(HistoricalFS!G69/HistoricalFS!G50,0) -> 3.3695752 | H40: =IFERROR(HistoricalFS!H69/HistoricalFS!H50,0) -> 0.62165381 | I40: =IFERROR(HistoricalFS!I69/HistoricalFS!I50,0) -> 2.1698161 | J40: =IFERROR(HistoricalFS!J69/HistoricalFS!J50,0) -> 2.4667189 | ... L40: =IFERROR(HistoricalFS!L69/HistoricalFS!L50,0) -> 1.8040993 | N40: =IFERROR(AVERAGE(C40:L40),0) -> 2.3638884 | O40: =IFERROR(MEDIAN(C40:L40),0) -> 2.3182675

Sheet Analysis of ratios
B2: Ratio | C2: Formula | D2: Significance | E2: Number | F2: Reason
B3: Sales Growth | C3: (Current Sales − Previous Sales) / Previous Sales × 100 | D3: Measures the rate of change in revenue; indicates top-line expansion or contraction | E3: FY22 34.03% → FY23 18.51% → FY24 2.92% → FY25 -4.48% → FY26 4.95% | F3: Sales growth recovered in FY26, supported by a recovery in underlying coatings volumes, with India Decorative volume growth of 8.7%, double-digit growth in Industrial and Automotive Protective Coatings, and 9.4% growth in the International business. However, home décor faced near-term retail headwinds and competitive intensity remained a constraint.
B4: EBITDA Growth | C4: (Current EBITDA − Previous EBITDA) / Previous EBITDA × 100 | D4: Measures growth in operating earnings before D&A, interest and tax. | E4: FY22 3.05%, FY23 25.73%, FY24 19.57%, FY25 -13.18%, FY26 10.42% | F4: EBITDA growth was supported by improved operating profitability as material costs moderated, gross margins improved and the Company continued cost optimisation and operating-efficiency initiatives.
B5: EBT Growth | C5: (Current EBT − Previous EBT) / Previous EBT × 100 | D5: Measures growth in profit before tax after operating, depreciation and financing-related effects. | E5: FY22 3.01%, FY23 28.27%, FY24 21.50%, FY25 -16.96%, FY26 9.87% | F5: EBT growth was supported by lower finance costs, primarily due to reduced interest on bank borrowings, bill discounting and other interest expenses. However, the benefit was partly offset by higher depreciation expense.
B6: Net Profit Growth | C6: (Current PAT − Previous PAT) / Previous PAT × 100 | D6: Measures growth in the company's final profit after expenses and tax. | E6: FY22 3.64%, FY23 26.55%, FY24 21.92%, FY25 -15.65%, FY26 8.57% | F6: Improved profitability and stronger margin performance supported growth in net profit.
B7: Dividend Growth | C7: (Current Dividend − Previous Dividend) / Previous Dividend × 100 | D7: Shows how quickly shareholder distributions are changing. | E7: FY22 3.52%, FY23 5.85%, FY24 6.48%, FY25 -11.71%, FY26 2.13% | F7: Dividend increased in line with the company's progressive dividend policy. The payout ratio was maintained at 60%, consistent with the previous three years, reflecting the company's policy of sharing the benefits of growth with shareholders
B9: Gross Margin | C9: Gross Profit / Revenue × 100 | D9: Measures the proportion of revenue left after COGS. Helps assess product-level profitability, pricing and input-cost efficiency. | E9: FY22 35.41% → FY23 36.99% → FY24 41.75% → FY25 40.61% → FY26 41.88% | F9: Improvement was supported by raw-material efficiencies and favourable input-cost conditions, along with a better product mix/premiumisation
B10: EBITDA Margin | C10: EBITDA / Revenue × 100 | D10: Measures operating profitability before D&A, interest and tax. Useful for comparing operating performance relative to revenue. | E10: FY22 22.67% → FY23 24.06% → FY24 27.95% → FY25 25.40% → FY26 26.72% | F10: EBITDA margin improved as the benefit from better gross margins flowed through to operating profitability, supported by operating efficiencies and cost-management initiatives.
B11: EBIT Margin | C11: EBIT / Revenue × 100 | D11: Measures operating profitability after depreciation and amortisation. Shows the effect of using the company's asset base on operating earnings. | E11: FY22 19.87% → FY23 21.57% → FY24 25.54% → FY25 22.37% → FY26 23.27% | F11: Improved operating profitability more than offset the higher depreciation burden from continued investment in capacity and assets.
B12: EBT Margin | C12: EBT / Revenue × 100 | D12: Measures the percentage of revenue remaining as profit before tax, after operating and financing-related effects. | E12: FY22 19.54% → FY23 21.15% → FY24 24.97% → FY25 21.70% → FY26 22.72% | F12: Higher operating profitability, together with lower finance costs, reduced the financing burden and improved pre-tax profitability.
B13: Net Profit Margin | C13: PAT / Revenue × 100 | D13: Measures the percentage of revenue ultimately retained as net profit after expenses and tax. Indicates bottom-line profitability. | E13: FY22 15.75% → FY23 16.82% → FY24 19.92% → FY25 17.59% → FY26 18.20% | F13: Improved overall profitability led to better net profit conversion.
B15: SalesExpenses%Sales | C15: Selling & Administrative Expenses / Sales × 100 | D15: Shows how much of revenue is consumed by selling and administrative expenses. Helps assess the company's operating cost intensity. | E15: FY22 12.74% → FY23 12.94% → FY24 13.80% → FY25 15.21% → FY26 15.16% | F15: The slight decline suggests that operating expense growth was broadly controlled despite the company's continued investments in brand building, distribution and services.
... B38: CFO/Total Debt | C38: Cash Flow from Operations / Total Debt × 100 | D38: Indicates the company's ability to generate operating cash relative to its debt obligations. A higher ratio generally indicates stronger cash-flow-based debt servicing capacity. | E38: FY22 62.17% → FY23 216.98% → FY24 246.67% → FY25 193.16% → FY26 180.41% | F38: Operating cash flow remained very strong relative to debt, although cash coverage per rupee of debt declined somewhat during the year.

Sheet Forecasting
B2: ='Data Sheet'!B1&" -"&'Data Sheet'!A17&" forecasting" -> ASIAN PAINTS LTD -Sales forecasting | G2: ='Data Sheet'!B1&" -"&HistoricalFS!B18&" forecasting" -> ASIAN PAINTS LTD -EBITDA forecasting | L2: ='Data Sheet'!B1&" -"&HistoricalFS!B38&" forecasting" -> ASIAN PAINTS LTD -Earnings per Share forecasting
B3: Year Weight | C3: Year | D3: Sales | E3: Sales Growth | G3: Year Weight | H3: Year | I3: EBITDA | J3: EBITDA Growth | L3: Year Weight | M3: Year | N3: EPS | O3: EPS Growth
B4: 1 | C4: ='Data Sheet'!$B$16 -> 42825 | D4: {=TRANSPOSE('Data Sheet'!B17:K17)} -> 15061.99 | G4: 1 | H4: =C4 -> 42825 | I4: {=TRANSPOSE(HistoricalFS!C18:L18)} -> 4033.65 | L4: 1 | M4: =H4 -> 42825 | N4: {=TRANSPOSE(HistoricalFS!C38:L38)} -> 28.338616
B5: =B4+1 -> 2 | C5: =C4+365 -> 43190 | D5: 16824.55 | E5: =D5/D4-1 -> 0.11702039 | G5: =G4+1 -> 2 | H5: =H4+365 -> 43190 | I5: 4325.9 | J5: =I5/I4-1 -> 0.072452989 | L5: =L4+1 -> 2 | M5: =M4+365 -> 43190 | N5: 30.056297 | O5: =N5/N4-1 -> 0.060612749
B6: =B5+1 -> 3 | C6: =C5+365 -> 43555 | D6: 19240.13 | E6: =D6/D5-1 -> 0.14357472 | G6: =G5+1 -> 3 | H6: =H5+365 -> 43555 | I6: 5007.63 | J6: =I6/I5-1 -> 0.15759264 | L6: =L5+1 -> 3 | M6: =M5+365 -> 43555 | N6: 33.120934 | O6: =N6/N5-1 -> 0.10196323
B7: =B6+1 -> 4 | C7: =C6+365 -> 43920 | D7: 20211.25 | E7: =D7/D6-1 -> 0.050473671 | G7: =G6+1 -> 4 | H7: =H6+365 -> 43920 | I7: 5533.04 | J7: =I7/I6-1 -> 0.10492189 | L7: =L6+1 -> 4 | M7: =M6+365 -> 43920 | N7: 39.567973 | O7: =N7/N6-1 -> 0.19465149
B8: =B7+1 -> 5 | C8: =C7+365 -> 44285 | D8: 21712.79 | E8: =D8/D7-1 -> 0.074292288 | G8: =G7+1 -> 5 | H8: =H7+365 -> 44285 | I8: 6403.21 | J8: =I8/I7-1 -> 0.15726798 | L8: =L7+1 -> 5 | M8: =M7+365 -> 44285 | N8: 46.108319 | O8: =N8/N7-1 -> 0.16529394
B9: =B8+1 -> 6 | C9: =C8+365 -> 44650 | D9: 29101.28 | E9: =D9/D8-1 -> 0.34028285 | G9: =G8+1 -> 6 | H9: =H8+365 -> 44650 | I9: 6598.22 | J9: =I9/I8-1 -> 0.030455037 | L9: =L8+1 -> 6 | M9: =M8+365 -> 44650 | N9: 47.785029 | O9: =N9/N8-1 -> 0.036364582
B10: =B9+1 -> 7 | C10: =C9+365 -> 45015 | D10: 34488.59 | E10: =D10/D9-1 -> 0.18512278 | G10: =G9+1 -> 7 | H10: =H9+365 -> 45015 | I10: 8296.25 | J10: =I10/I9-1 -> 0.25734668 | L10: =L9+1 -> 7 | M10: =M9+365 -> 45015 | N10: 60.469975 | O10: =N10/N9-1 -> 0.26545858
B11: =B10+1 -> 8 | C11: =C10+365 -> 45380 | D11: 35494.73 | E11: =D11/D10-1 -> 0.029173127 | G11: =G10+1 -> 8 | H11: =H10+365 -> 45380 | I11: 9919.9 | J11: =I11/I10-1 -> 0.1957089 | L11: =L10+1 -> 8 | M11: =M10+365 -> 45380 | N11: 73.724458 | O11: =N11/N10-1 -> 0.21919114
B12: =B11+1 -> 9 | C12: =C11+365 -> 45745 | D12: 33905.62 | E12: =D12/D11-1 -> -0.044770308 | G12: =G11+1 -> 9 | H12: =H11+365 -> 45745 | I12: 8611.99 | J12: =I12/I11-1 -> -0.1318471 | L12: =L11+1 -> 9 | M12: =M11+365 -> 45745 | N12: 62.190054 | O12: =N12/N11-1 -> -0.15645288
B13: =B12+1 -> 10 | C13: =C12+365 -> 46110 | D13: 35583.54 | E13: =D13/D12-1 -> 0.049487961 | G13: =G12+1 -> 10 | H13: =H12+365 -> 46110 | I13: 9509.46 | J13: =I13/I12-1 -> 0.10421169 | L13: =L12+1 -> 10 | M13: =M12+365 -> 46110 | N13: 67.519287 | O13: =N13/N12-1 -> 0.085692684
B14: =B13+1 -> 11 | C14: =C13+365 -> 46475 | D14: =FORECAST(B14,$D$4:$D$13,$B$4:$B$13) -> 40687.612 | E14: =D14/D13-1 -> 0.14343913 | G14: =G13+1 -> 11 | H14: =H13+365 -> 46475 | I14: =FORECAST(G14,$I$4:$I$13,$G$4:$G$13) -> 10568.289 | J14: =I14/I13-1 -> 0.11134477 | L14: =L13+1 -> 11 | M14: =M13+365 -> 46475 | N14: =FORECAST(L14,$N$4:$N$13,$L$4:$L$13) -> 77.053517 | O14: =N14/N13-1 -> 0.1412075
B15: =B14+1 -> 12 | C15: =C14+365 -> 46840 | D15: =FORECAST(B15,$D$4:$D$13,$B$4:$B$13) -> 43328.551 | E15: =D15/D14-1 -> 0.064907695 | G15: =G14+1 -> 12 | H15: =H14+365 -> 46840 | I15: =FORECAST(G15,$I$4:$I$13,$G$4:$G$13) -> 11249.082 | J15: =I15/I14-1 -> 0.064418509 | L15: =L14+1 -> 12 | M15: =M14+365 -> 46840 | N15: =FORECAST(L15,$N$4:$N$13,$L$4:$L$13) -> 82.174503 | O15: =N15/N14-1 -> 0.066460119
B16: =B15+1 -> 13 | C16: =C15+365 -> 47205 | D16: =FORECAST(B16,$D$4:$D$13,$B$4:$B$13) -> 45969.49 | E16: =D16/D15-1 -> 0.060951475 | G16: =G15+1 -> 13 | H16: =H15+365 -> 47205 | I16: =FORECAST(G16,$I$4:$I$13,$G$4:$G$13) -> 11929.875 | J16: =I16/I15-1 -> 0.060519906 | L16: =L15+1 -> 13 | M16: =M15+365 -> 47205 | N16: =FORECAST(L16,$N$4:$N$13,$L$4:$L$13) -> 87.295489 | O16: =N16/N15-1 -> 0.062318429
B17: =B16+1 -> 14 | C17: =C16+365 -> 47570 | D17: =FORECAST(B17,$D$4:$D$13,$B$4:$B$13) -> 48610.429 | E17: =D17/D16-1 -> 0.057449823 | G17: =G16+1 -> 14 | H17: =H16+365 -> 47570 | I17: =FORECAST(G17,$I$4:$I$13,$G$4:$G$13) -> 12610.669 | J17: =I17/I16-1 -> 0.057066262 | L17: =L16+1 -> 14 | M17: =M16+365 -> 47570 | N17: =FORECAST(L17,$N$4:$N$13,$L$4:$L$13) -> 92.416475 | O17: =N17/N16-1 -> 0.058662664
B18: =B17+1 -> 15 | C18: =C17+365 -> 47935 | D18: =FORECAST(B18,$D$4:$D$13,$B$4:$B$13) -> 51251.368 | E18: =D18/D17-1 -> 0.054328652 | G18: =G17+1 -> 15 | H18: =H17+365 -> 47935 | I18: =FORECAST(G18,$I$4:$I$13,$G$4:$G$13) -> 13291.462 | J18: =I18/I17-1 -> 0.05398551 | L18: =L17+1 -> 15 | M18: =M17+365 -> 47935 | N18: =FORECAST(L18,$N$4:$N$13,$L$4:$L$13) -> 97.537461 | O18: =N18/N17-1 -> 0.055412046
B19: =B18+1 -> 16 | C19: =C18+365 -> 48300 | D19: =FORECAST(B19,$D$4:$D$13,$B$4:$B$13) -> 53892.307 | E19: =D19/D18-1 -> 0.051529143 | G19: =G18+1 -> 16 | H19: =H18+365 -> 48300 | I19: =FORECAST(G19,$I$4:$I$13,$G$4:$G$13) -> 13972.256 | J19: =I19/I18-1 -> 0.051220353 | L19: =L18+1 -> 16 | M19: =M18+365 -> 48300 | N19: =FORECAST(L19,$N$4:$N$13,$L$4:$L$13) -> 102.65845 | O19: =N19/N18-1 -> 0.05250276
B22: Forecast Methodology
B23: Item | C23: Details
B24: Method | C24: Simple Linear Regression
B25: Independent Variable(X) | C25: Year Weight(1,2,3….)
B26: Dependent Variable(Y) | C26: Sales/EBITDA/EPS
B27: Historical Period | C27: FY17-FY26
B28: Forecast Period | C28: FY27-FY32
B29: Purpose | C29: Establish a historical trend- based baseline
B31: The regression extrapolates the historical relationship between time and the financial variable; the forecast is therefore a statistical baseline, not a business-driven assumption.
B34: InSample forecasting- Sales | G34: Back-testing- EBITDA | L34: Back-testing- EPS
B35: Year | C35: Regression Forecast | D35: Forecast Error(Actual-Forecast) | E35: Absolute % Error | G35: Year | H35: Regression Forecast | I35: Forecast Error(Actual-Forecast) | J35: Absolute % Error | L35: Year | M35: Regression Forecast | N35: Forecast Error(Actual-Forecast) | O35: Absolute % Error
B36: 2022 | C36: =FORECAST(B9,D4:D8,B4:B8) -> 23616.632 | D36: =D9-C36 -> 5484.648 | E36: =ABS(D36/D9) -> 0.18846759 | G36: 2022 | H36: =FORECAST(G9,I4:I8,G4:G8) -> 6844.564 | I36: =I9-H36 -> -246.344 | J36: =ABS(I36/I9) -> 0.037334918 | L36: 2022 | M36: =FORECAST(L9,N4:N8,L4:L8) -> 48.953753 | N36: =N9-M36 -> -1.1687239 | O36: =ABS(N36/N9) -> 0.024457952
B37: =B36+1 -> 2023 | C37: =FORECAST(B10,D5:D9,B5:B9) -> 29525.836 | D37: =D10-C37 -> 4962.754 | E37: =ABS(D37/D10) -> 0.14389553 | G37: =G36+1 -> 2023 | H37: =FORECAST(G10,I5:I9,G5:G9) -> 7355.666 | I37: =I10-H37 -> 940.584 | J37: =ABS(I37/I10) -> 0.1133746 | L37: =L36+1 -> 2023 | M37: =FORECAST(L10,N5:N9,L5:L9) -> 53.861166 | N37: =N10-M37 -> 6.6088094 | O37: =ABS(N37/N10) -> 0.10929076
B38: =B37+1 -> 2024 | C38: =FORECAST(B11,D6:D10,B6:B10) -> 36766.893 | D38: =D11-C38 -> -1272.163 | E38: =ABS(D38/D11) -> 0.035840898 | G38: =G37+1 -> 2024 | H38: =FORECAST(G11,I6:I10,G6:G10) -> 8660.396 | I38: =I11-H38 -> 1259.504 | J38: =ABS(I38/I11) -> 0.12696741 | L38: =L37+1 -> 2024 | M38: =FORECAST(L11,N6:N10,L6:L10) -> 64.284987 | N38: =N11-M38 -> 9.4394704 | O38: =ABS(N38/N11) -> 0.12803716
B39: =B38+1 -> 2025 | C39: =FORECAST(B12,D7:D11,B7:B11) -> 41204.556 | D39: =D12-C39 -> -7298.936 | E39: =ABS(D39/D12) -> 0.21527216 | G39: =G38+1 -> 2025 | H39: =FORECAST(G12,I7:I11,G7:G11) -> 10550.152 | I39: =I12-H39 -> -1938.162 | J39: =ABS(I39/I12) -> 0.22505391 | L39: =L38+1 -> 2025 | M39: =FORECAST(L12,N7:N11,L7:L11) -> 78.333538 | N39: =N12-M39 -> -16.143484 | O39: =ABS(N39/N12) -> 0.25958305
B40: =B39+1 -> 2026 | C40: =FORECAST(B13,D8:D12,B8:B12) -> 40174.335 | D40: =D13-C40 -> -4590.795 | E40: =ABS(D40/D13) -> 0.12901457 | G40: =G39+1 -> 2026 | H40: =FORECAST(G13,I8:I12,G8:G12) -> 10287.686 | I40: =I13-H40 -> -778.226 | J40: =ABS(I40/I13) -> 0.081837034 | L40: =L39+1 -> 2026 | M40: =FORECAST(L13,N8:N12,L8:L12) -> 75.486437 | N40: =N13-M40 -> -7.9671497 | O40: =ABS(N40/N13) -> 0.11799813
D41: MAPE | E41: =AVERAGE(E36:E40) -> 0.14249815 | I41: MAPE | J41: =AVERAGE(J36:J40) -> 0.11691357 | N41: MAPE | O41: =AVERAGE(O36:O40) -> 0.12787341
B43: Back-testing over FY22–FY26 shows average absolute forecasting errors of 14.25% for Sales, 11.69% for EBITDA and 12.79% for EPS. The errors indicate that a simple time trend can miss significant changes in business performance.
B46: Model Output and Interpretation
B47: The regression forecasts should be treated as statistical baselines rather than standalone investment forecasts. They should be compared with management guidance, industry outlook and company-specific business drivers before being relied upon.
B48: FY27 Sales forecast of ₹40,687.6 crore implies 14.34% growth based on the historical trend. This is a model-derived outcome, not a business assumption.
B49: FY27 EBITDA forecast of ₹10,568.3 crore implies 11.13% growth based on the historical trend. Given the EBITDA model's 11.69% historical MAPE, this estimate should be validated against expected margins, input costs and operating conditions.
B50: FY27 EPS forecast of ₹77.1 implies 14.12% growth based on the historical trend. Given the EPS model's 12.79% historical MAPE, this estimate should be validated against expected profitability, finance costs, taxation and share-count assumptions.
B52: Limitation | C52: Impact
B53: Historical trend only | C53: Does not incorporate business fundamentals.
B54: No volume/price split | C54: Cannot distinguish volume growth from pricing or mix.
B55: No competition factor | C55: Ignores market-share, pricing and discount pressure.
B56: No macro variables | C56: Ignores GDP, inflation, housing, interest rates, etc.
B57: No commodity assumptions | C57: Does not incorporate raw-material price movements.
B58: No strategic initiatives | C58: Does not capture capacity expansion, premiumisation, B2B growth, etc.
B59: Structural changes | C59: Assumes the historical relationship continues into the future.
B60: Long-horizon uncertainty | C60: FY30–FY32 forecasts are increasingly uncertain.
B64: Investor Interpretation
B65: The regression forecast should be treated as a baseline rather than a standalone investment forecast. Investors should compare it with management guidance, industry growth, volume and pricing outlook, competitive conditions, capacity expansion and macroeconomic factors before relying on it.
B67: The FY27 regression implies 14.34% growth; given the model's 14.25% historical MAPE, this estimate should be validated against business fundamentals before being considered achievable.
B68: FY27 EBITDA regression implies 11.13% growth; given the EBITDA model's 11.69% historical MAPE, this estimate should be treated as a trend-based benchmark and validated against expected margins, costs and operating conditions.
B69: FY27 EPS regression implies 14.12% growth; given the EPS model's 12.79% historical MAPE, this estimate should be treated as a statistical benchmark and validated against expected profitability, finance costs, taxation and share-count assumptions.

Sheet Beta-Regression
B2: Regression Beta- 2 years weekly
B4: Asian Paints Weekly Returns | F4: Nifty Returns | I4: Beta Drifting | L4: Asian Paints | V4: Berger Paints | Z4: Kansai Nerolac | AC4: JSW Dulux | AF4: Indigo Paints
B6: Date | C6: Adj. Closing Price | D6: Return | F6: Adj. Closing Price | G6: Return | I6: Levered Raw Beta | J6: =M7 -> 0.96207015 | V6: Adj. Closing Price | W6: Return | Z6: Adj. Closing Price | AA6: Return | AC6: Adj. Closing Price | AD6: Return | AF6: Adj. Closing Price | AG6: Return
B7: 45509 | C7: 2977.1318 | F7: 24367.5 | I7: Raw Beta Weight | J7: 0.67 | L7: Beta | M7: =M26 -> 0.96207015 | V7: 524.14838 | Z7: 285.70441 | AC7: 3068.8447 | AF7: 1418.0793
B8: 45516 | C8: 2984.5239 | D8: =C8/C7-1 -> 0.0024829568 | F8: 24541.15 | G8: =F8/F7-1 -> 0.0071263113 | V8: 542.14081 | W8: =V8/V7-1 -> 0.034326982 | Z8: 282.20242 | AA8: =Z8/Z7-1 -> -0.012257367 | AC8: 2926.2136 | AD8: =AC8/AC7-1 -> -0.046477133 | AF8: 1430.9397 | AG8: =AF8/AF7-1 -> 0.0090688519
B9: 45523 | C9: 3088.8008 | D9: =C9/C8-1 -> 0.034939192 | F9: 24823.15 | G9: =F9/F8-1 -> 0.011490904 | I9: Market Beta | J9: 1 | L9: SUMMARY OUTPUT | V9: 557.71796 | W9: =V9/V8-1 -> 0.028732662 | Z9: 286.28806 | AA9: =Z9/Z8-1 -> 0.014477666 | AC9: 3001.8191 | AD9: =AC9/AC8-1 -> 0.025837303 | AF9: 1444.9465 | AG9: =AF9/AF8-1 -> 0.0097885578
B10: 45530 | C10: 3061.5327 | D10: =C10/C9-1 -> -0.0088280431 | F10: 25235.9 | G10: =F10/F9-1 -> 0.016627624 | I10: Market Beta Weight | J10: 0.33 | V10: 562.99243 | W10: =V10/V9-1 -> 0.0094572445 | Z10: 288.42816 | AA10: =Z10/Z9-1 -> 0.0074753597 | AC10: 3179.4082 | AD10: =AC10/AC9-1 -> 0.059160498 | AF10: 1446.0432 | AG10: =AF10/AF9-1 -> 0.00075897596
B11: 45537 | C11: 3205.366 | D11: =C11/C10-1 -> 0.046980799 | F11: 24852.15 | G11: =F11/F10-1 -> -0.015206511 | L11: Regression Statistics | V11: 587.88611 | W11: =V11/V10-1 -> 0.044216717 | Z11: 297.71817 | AA11: =Z11/Z10-1 -> 0.03220909 | AC11: 3459.4412 | AD11: =AC11/AC10-1 -> 0.08807707 | AF11: 1474.8044 | AG11: =AF11/AF10-1 -> 0.019889606
B12: 45544 | C12: 3287.9553 | D12: =C12/C11-1 -> 0.025765968 | F12: 25356.5 | G12: =F12/F11-1 -> 0.020294003 | I12: Adjusted Beta | J12: =(J6*J7)+(J9*J10) -> 0.974587 | L12: Multiple R | M12: 0.52323038 | V12: 613.86438 | W12: =V12/V11-1 -> 0.044189293 | Z12: 302.92252 | AA12: =Z12/Z11-1 -> 0.01748078 | AC12: 3386.2217 | AD12: =AC12/AC11-1 -> -0.021165119 | AF12: 1497.5345 | AG12: =AF12/AF11-1 -> 0.015412282
B13: 45551 | C13: 3237.9219 | D13: =C13/C12-1 -> -0.015217192 | F13: 25790.949 | G13: =F13/F12-1 -> 0.017133643 | L13: R Square | M13: 0.27377003 | V13: 614.06146 | W13: =V13/V12-1 -> 0.00032105222 | Z13: 293.92435 | AA13: =Z13/Z12-1 -> -0.029704523 | AC13: 3401.3608 | AD13: =AC13/AC12-1 -> 0.0044708119 | AF13: 1476.7485 | AG13: =AF13/AF12-1 -> -0.013880154
B14: 45558 | C14: 3241.6428 | D14: =C14/C13-1 -> 0.0011491776 | F14: 26178.949 | G14: =F14/F13-1 -> 0.015044037 | L14: Adjusted R Square | M14: 0.26665013 | V14: 608.8363 | W14: =V14/V13-1 -> -0.0085091787 | Z14: 300.92834 | AA14: =Z14/Z13-1 -> 0.023829254 | AC14: 3470.9106 | AD14: =AC14/AC13-1 -> 0.020447641 | AF14: 1466.9786 | AG14: =AF14/AF13-1 -> -0.0066158166
B15: 45565 | C15: 3008.366 | D15: =C15/C14-1 -> -0.071962541 | F15: 25014.6 | G15: =F15/F14-1 -> -0.04447656 | L15: Standard Error | M15: 0.029303635 | V15: 568.80914 | W15: =V15/V14-1 -> -0.065743715 | Z15: 284.14798 | AA15: =Z15/Z14-1 -> -0.055761995 | AC15: 3505.6392 | AD15: =AC15/AC14-1 -> 0.010005592 | AF15: 1455.9625 | AG15: =AF15/AF14-1 -> -0.007509389
B16: 45572 | C16: 2973.803 | D16: =C16/C15-1 -> -0.011488957 | F16: 24964.25 | G16: =F16/F15-1 -> -0.0020128089 | L16: Observations | M16: 104 | V16: 563.48529 | W16: =V16/V15-1 -> -0.0093596466 | Z16: 280.88913 | AA16: =Z16/Z15-1 -> -0.011468848 | AC16: 3782.9192 | AD16: =AC16/AC15-1 -> 0.079095428 | AF16: 1477.3467 | AG16: =AF16/AF15-1 -> 0.014687298
B17: 45579 | C17: 2929.6929 | D17: =C17/C16-1 -> -0.014832895 | F17: 24854.051 | G17: =F17/F16-1 -> -0.0044142812 | V17: 548.49982 | W17: =V17/V16-1 -> -0.026594259 | Z17: 279.23544 | AA17: =Z17/Z16-1 -> -0.0058873283 | AC17: 3588.3555 | AD17: =AC17/AC16-1 -> -0.051432164 | AF17: 1562.0856 | AG17: =AF17/AF16-1 -> 0.05735884
B18: 45586 | C18: 2896.2559 | D18: =C18/C17-1 -> -0.011413146 | F18: 24180.801 | G18: =F18/F17-1 -> -0.02708814 | L18: ANOVA | V18: 529.37354 | W18: =V18/V17-1 -> -0.03487017 | Z18: 271.55051 | AA18: =Z18/Z17-1 -> -0.027521351 | AC18: 3406.5449 | AD18: =AC18/AC17-1 -> -0.050666816 | AF18: 1596.5293 | AG18: =AF18/AF17-1 -> 0.022049833
B19: 45593 | C19: 2878.4849 | D19: =C19/C18-1 -> -0.0061358516 | F19: 24304.35 | G19: =F19/F18-1 -> 0.005109377 | M19: df | N19: SS | O19: MS | P19: F | Q19: Significance F | V19: 524.24695 | W19: =V19/V18-1 -> -0.0096842524 | Z19: 279.1868 | AA19: =Z19/Z18-1 -> 0.028121073 | AC19: 4145.897 | AD19: =AC19/AC18-1 -> 0.21703869 | AF19: 1671.1992 | AG19: =AF19/AF18-1 -> 0.046770154
B20: 45600 | C20: 2711.6416 | D20: =C20/C19-1 -> -0.057962181 | F20: 24148.199 | G20: =F20/F19-1 -> -0.006424792 | L20: Regression | M20: 1 | N20: 0.033018316 | O20: 0.033018316 | P20: 38.451379 | Q20: 1.2083881e-08 | V20: 497.13495 | W20: =V20/V19-1 -> -0.051716085 | Z20: 263.76828 | AA20: =Z20/Z19-1 -> -0.05522653 | AC20: 3754.5212 | AD20: =AC20/AC19-1 -> -0.094400738 | AF20: 1529.7352 | AG20: =AF20/AF19-1 -> -0.08464819
B21: 45607 | C21: 2431.3176 | D21: =C21/C20-1 -> -0.10337796 | F21: 23532.699 | G21: =F21/F20-1 -> -0.025488443 | L21: Residual | M21: 102 | N21: 0.087587711 | O21: 0.00085870305 | V21: 484.9592 | W21: =V21/V20-1 -> -0.024491842 | Z21: 252.19225 | AA21: =Z21/Z20-1 -> -0.043887137 | AC21: 3345.6204 | AD21: =AC21/AC20-1 -> -0.10890893 | AF21: 1495.5406 | AG21: =AF21/AF20-1 -> -0.022353267
B22: 45614 | C22: 2424.7454 | D22: =C22/C21-1 -> -0.0027031703 | F22: 23907.25 | G22: =F22/F21-1 -> 0.015916184 | L22: Total | M22: 103 | N22: 0.12060603 | V22: 469.53003 | W22: =V22/V21-1 -> -0.031815396 | Z22: 259.97449 | AA22: =Z22/Z21-1 -> 0.030858371 | AC22: 3403.2405 | AD22: =AC22/AC21-1 -> 0.017222551 | AF22: 1498.1825 | AG22: =AF22/AF21-1 -> 0.001766482
B23: 45621 | C23: 2432.0034 | D23: =C23/C22-1 -> 0.0029933274 | F23: 24131.1 | G23: =F23/F22-1 -> 0.0093632521 | V23: 486.73383 | W23: =V23/V22-1 -> 0.03664046 | Z23: 273.30148 | AA23: =Z23/Z22-1 -> 0.051262707 | AC23: 3467.0217 | AD23: =AC23/AC22-1 -> 0.018741329 | AF23: 1429.1453 | AG23: =AF23/AF22-1 -> -0.046080656
B24: 45628 | C24: 2383.061 | D24: =C24/C23-1 -> -0.020124307 | F24: 24677.801 | G24: =F24/F23-1 -> 0.02265546 | M24: Coefficients | N24: Standard Error | O24: t Stat | P24: P-value | Q24: Lower 95% | R24: Upper 95% | S24: Lower 95.0% | T24: Upper 95.0% | V24: 473.67081 | W24: =V24/V23-1 -> -0.026838116 | Z24: 270.28589 | AA24: =Z24/Z23-1 -> -0.011033948 | AC24: 3436.4871 | AD24: =AC24/AC23-1 -> -0.0088071753 | AF24: 1429.4941 | AG24: =AF24/AF23-1 -> 0.00024411581
B25: 45635 | C25: 2361.4343 | D25: =C25/C24-1 -> -0.0090751805 | F25: 24768.301 | G25: =F25/F24-1 -> 0.0036672636 | L25: Intercept | M25: -0.00047177079 | N25: 0.0028737226 | O25: -0.16416713 | P25: 0.86992445 | Q25: -0.006171786 | R25: 0.0052282444 | S25: -0.006171786 | T25: 0.0052282444 | V25: 468.29767 | W25: =V25/V24-1 -> -0.011343613 | Z25: 255.54834 | AA25: =Z25/Z24-1 -> -0.05452578 | AC25: 3318.2761 | AD25: =AC25/AC24-1 -> -0.034398773 | AF25: 1426.0547 | AG25: =AF25/AF24-1 -> -0.0024060631
B26: 45642 | C26: 2238.5396 | D26: =C26/C25-1 -> -0.052042428 | F26: 23587.5 | G26: =F26/F25-1 -> -0.047673871 | L26: X Variable 1 | M26: 0.96207015 | N26: 0.15514964 | O26: 6.2009176 | P26: 1.2083881e-08 | Q26: 0.65433157 | R26: 1.2698087 | S26: 0.65433157 | T26: 1.2698087 | V26: 438.5238 | W26: =V26/V25-1 -> -0.06357893 | Z26: 255.06194 | AA26: =Z26/Z25-1 -> -0.0019033754 | AC26: 3360.4077 | AD26: =AC26/AC25-1 -> 0.012696831 | AF26: 1404.6207 | AG26: =AF26/AF25-1 -> -0.015030251
B27: 45649 | C27: 2227.7998 | D27: =C27/C26-1 -> -0.0047976575 | F27: 23813.4 | G27: =F27/F26-1 -> 0.0095771231 | V27: 436.05905 | W27: =V27/V26-1 -> -0.0056205665 | Z27: 254.18645 | AA27: =Z27/Z26-1 -> -0.0034324537 | AC27: 3188.1882 | AD27: =AC27/AC26-1 -> -0.05124958 | AF27: 1329.8015 | AG27: =AF27/AF26-1 -> -0.053266489
B28: 45656 | C28: 2291.1108 | D28: =C28/C27-1 -> 0.028418638 | F28: 24004.75 | G28: =F28/F27-1 -> 0.0080353753 | V28: 451.38968 | W28: =V28/V27-1 -> 0.035157228 | Z28: 254.7701 | AA28: =Z28/Z27-1 -> 0.002296144 | AC28: 3273.2925 | AD28: =AC28/AC27-1 -> 0.026693608 | AF28: 1391.4614 | AG28: =AF28/AF27-1 -> 0.046367756
B29: 45663 | C29: 2276.2026 | D29: =C29/C28-1 -> -0.0065069759 | F29: 23431.5 | G29: =F29/F28-1 -> -0.02388069 | L29: SUMMARY OUTPUT- Berger Paints | V29: 454.34735 | W29: =V29/V28-1 -> 0.0065523698 | Z29: 246.89062 | AA29: =Z29/Z28-1 -> -0.03092777 | AC29: 3493.3481 | AD29: =AC29/AC28-1 -> 0.06722762 | AF29: 1283.8431 | AG29: =AF29/AF28-1 -> -0.077341911
B30: 45670 | C30: 2217.5994 | D30: =C30/C29-1 -> -0.02574607 | F30: 23203.199 | G30: =F30/F29-1 -> -0.0097433276 | V30: 462.18518 | W30: =V30/V29-1 -> 0.017250743 | Z30: 237.55196 | AA30: =Z30/Z29-1 -> -0.037825125 | AC30: 3591.8259 | AD30: =AC30/AC29-1 -> 0.028190086 | AF30: 1224.526 | AG30: =AF30/AF29-1 -> -0.046202793
B31: 45677 | C31: 2218.9724 | D31: =C31/C30-1 -> 0.00061915912 | F31: 23092.199 | G31: =F31/F30-1 -> -0.0047838231 | L31: Regression Statistics | V31: 473.32574 | W31: =V31/V30-1 -> 0.024104113 | Z31: 235.50914 | AA31: =Z31/Z30-1 -> -0.00859945 | AC31: 3602.8618 | AD31: =AC31/AC30-1 -> 0.003072501 | AF31: 1223.3795 | AG31: =AF31/AF30-1 -> -0.00093626789
B32: 45684 | C32: 2306.0188 | D32: =C32/C31-1 -> 0.039228242 | F32: 23482.15 | G32: =F32/F31-1 -> 0.016886706 | L32: Multiple R | M32: 0.49644711 | V32: 485.20569 | W32: =V32/V31-1 -> 0.025098875 | Z32: 233.4955 | AA32: =Z32/Z31-1 -> -0.0085501622 | AC32: 3550.9104 | AD32: =AC32/AC31-1 -> -0.014419486 | AF32: 1274.123 | AG32: =AF32/AF31-1 -> 0.041478159
B33: 45691 | C33: 2227.4075 | D33: =C33/C32-1 -> -0.03408963 | F33: 23559.949 | G33: =F33/F32-1 -> 0.0033131049 | L33: R Square | M33: 0.24645973 | V33: 472.5863 | W33: =V33/V32-1 -> -0.02600832 | Z33: 242.20183 | AA33: =Z33/Z32-1 -> 0.037286926 | AC33: 3385.6116 | AD33: =AC33/AC32-1 -> -0.046551112 | AF33: 1251.3431 | AG33: =AF33/AF32-1 -> -0.017878891
B34: 45698 | C34: 2188.4697 | D34: =C34/C33-1 -> -0.017481195 | F34: 22929.25 | G34: =F34/F33-1 -> -0.026769974 | L34: Adjusted R Square | M34: 0.23907208 | V34: 471.55112 | W34: =V34/V33-1 -> -0.0021904714 | Z34: 225.10042 | AA34: =Z34/Z33-1 -> -0.070608096 | AC34: 3038.8811 | AD34: =AC34/AC33-1 -> -0.10241295 | AF34: 1082.4139 | AG34: =AF34/AF33-1 -> -0.1349983
B35: 45705 | C35: 2214.2649 | D35: =C35/C34-1 -> 0.011786851 | F35: 22795.9 | G35: =F35/F34-1 -> -0.0058156987 | L35: Standard Error | M35: 0.030501994 | V35: 484.31839 | W35: =V35/V34-1 -> 0.027075056 | Z35: 235.05194 | AA35: =Z35/Z34-1 -> 0.04420926 | AC35: 3046.0359 | AD35: =AC35/AC34-1 -> 0.0023544143 | AF35: 1074.8373 | AG35: =AF35/AF34-1 -> -0.0069997807
B36: 45712 | C36: 2137.9089 | D36: =C36/C35-1 -> -0.03448366 | F36: 22124.699 | G36: =F36/F35-1 -> -0.029443942 | L36: Observations | M36: 104 | V36: 481.65646 | W36: =V36/V35-1 -> -0.0054962321 | Z36: 220.48947 | AA36: =Z36/Z35-1 -> -0.061954262 | AC36: 2908.7466 | AD36: =AC36/AC35-1 -> -0.045071467 | AF36: 1016.7164 | AG36: =AF36/AF35-1 -> -0.054074148
B37: 45719 | C37: 2226.4268 | D37: =C37/C36-1 -> 0.041403925 | F37: 22552.5 | G37: =F37/F36-1 -> 0.019335891 | V37: 502.16302 | W37: =V37/V36-1 -> 0.042575078 | Z37: 229.23473 | AA37: =Z37/Z36-1 -> 0.039662912 | AC37: 3076.3833 | AD37: =AC37/AC36-1 -> 0.057631944 | AF37: 1060.2323 | AG37: =AF37/AF36-1 -> 0.042800462
B38: 45726 | C38: 2188.4697 | D38: =C38/C37-1 -> -0.017048408 | F38: 22397.199 | G38: =F38/F37-1 -> -0.0068861892 | L38: ANOVA | V38: 481.31143 | W38: =V38/V37-1 -> -0.041523553 | Z38: 218.53418 | AA38: =Z38/Z37-1 -> -0.04667943 | AC38: 2922.0732 | AD38: =AC38/AC37-1 -> -0.050159568 | AF38: 987.20734 | AG38: =AF38/AF37-1 -> -0.068876381
B39: 45733 | C39: 2256.2429 | D39: =C39/C38-1 -> 0.030968303 | F39: 23350.4 | G39: =F39/F38-1 -> 0.042558945 | M39: df | N39: SS | O39: MS | P39: F | Q39: Significance F | V39: 493.24069 | W39: =V39/V38-1 -> 0.024784909 | Z39: 238.26208 | AA39: =Z39/Z38-1 -> 0.090273775 | AC39: 3156.6716 | AD39: =AC39/AC38-1 -> 0.08028491 | AF39: 991.39447 | AG39: =AF39/AF38-1 -> 0.0042413925
B40: 45740 | C40: 2295.7205 | D40: =C40/C39-1 -> 0.017497025 | F40: 23519.35 | G40: =F40/F39-1 -> 0.0072353885 | L40: Regression | M40: 1 | N40: 0.031038173 | O40: 0.031038173 | P40: 33.361048 | Q40: 8.340162e-08 | V40: 493.14212 | W40: =V40/V39-1 -> -0.00019984518 | Z40: 226.55959 | AA40: =Z40/Z39-1 -> -0.049116079 | AC40: 3364.8965 | AD40: =AC40/AC39-1 -> 0.065963419 | AF40: 939.80347 | AG40: =AF40/AF39-1 -> -0.052038825
B41: 45747 | C41: 2310.825 | D41: =C41/C40-1 -> 0.0065794126 | F41: 22904.449 | G41: =F41/F40-1 -> -0.026144447 | L41: Residual | M41: 102 | N41: 0.094897909 | O41: 0.00093037166 | V41: 504.82489 | W41: =V41/V40-1 -> 0.023690472 | Z41: 233.01883 | AA41: =Z41/Z40-1 -> 0.028510132 | AC41: 3276.7061 | AD41: =AC41/AC40-1 -> -0.026208958 | AF41: 960.24048 | AG41: =AF41/AF40-1 -> 0.021746048
B42: 45754 | C42: 2347.6543 | D42: =C42/C41-1 -> 0.015937748 | F42: 22828.551 | G42: =F42/F41-1 -> -0.0033136984 | L42: Total | M42: 103 | N42: 0.12593608 | V42: 523.01459 | W42: =V42/V41-1 -> 0.036031697 | Z42: 242.78551 | AA42: =Z42/Z41-1 -> 0.041913685 | AC42: 3283.0186 | AD42: =AC42/AC41-1 -> 0.0019264774 | AF42: 982.67133 | AG42: =AF42/AF41-1 -> 0.023359614
B43: 45761 | C43: 2420.5276 | D43: =C43/C42-1 -> 0.031040895 | F43: 23851.65 | G43: =F43/F42-1 -> 0.044816669 | V43: 535.92969 | W43: =V43/V42-1 -> 0.024693575 | Z43: 251.093 | AA43: =Z43/Z42-1 -> 0.034217426 | AC43: 3268.1023 | AD43: =AC43/AC42-1 -> -0.0045434589 | AF43: 1014.3238 | AG43: =AF43/AF42-1 -> 0.032210633
B44: 45768 | C44: 2384.9246 | D44: =C44/C43-1 -> -0.014708788 | F44: 24039.35 | G44: =F44/F43-1 -> 0.0078694437 | M44: Coefficients | N44: Standard Error | O44: t Stat | P44: P-value | Q44: Lower 95% | R44: Upper 95% | S44: Lower 95.0% | T44: Upper 95.0% | V44: 544.70416 | W44: =V44/V43-1 -> 0.016372437 | Z44: 255.07166 | AA44: =Z44/Z43-1 -> 0.015845336 | AC44: 3337.0273 | AD44: =AC44/AC43-1 -> 0.021090236 | AF44: 1002.4603 | AG44: =AF44/AF43-1 -> -0.011695934
B45: 45775 | C45: 2363.7393 | D45: =C45/C44-1 -> -0.0088830075 | F45: 24346.699 | G45: =F45/F44-1 -> 0.012785271 | L45: Intercept | M45: 0.0004840656 | N45: 0.0029912422 | O45: 0.16182762 | P45: 0.87176173 | Q45: -0.0054490491 | R45: 0.0064171803 | S45: -0.0054490491 | T45: 0.0064171803 | V45: 541.79572 | W45: =V45/V44-1 -> -0.0053394989 | Z45: 247.47429 | AA45: =Z45/Z44-1 -> -0.029785224 | AC45: 3226.5786 | AD45: =AC45/AC44-1 -> -0.03309794 | AF45: 985.2135 | AG45: =AF45/AF44-1 -> -0.017204497
B46: 45782 | C46: 2255.4587 | D46: =C46/C45-1 -> -0.045808994 | F46: 24008 | G46: =F46/F45-1 -> -0.013911505 | L46: X Variable 1 | M46: 0.93277598 | N46: 0.16149442 | O46: 5.7759023 | P46: 8.340162e-08 | Q46: 0.61245257 | R46: 1.2530994 | S46: 0.61245257 | T46: 1.2530994 | V46: 529.02844 | W46: =V46/V45-1 -> -0.023564736 | Z46: 250.73309 | AA46: =Z46/Z45-1 -> 0.013168254 | AC46: 3207.4067 | AD46: =AC46/AC45-1 -> -0.0059418589 | AF46: 947.42993 | AG46: =AF46/AF45-1 -> -0.038350641
B47: 45789 | C47: 2308.4219 | D47: =C47/C46-1 -> 0.023482201 | F47: 25019.801 | G47: =F47/F46-1 -> 0.042144318 | V47: 567.97113 | W47: =V47/V46-1 -> 0.073611709 | Z47: 256.42383 | AA47: =Z47/Z46-1 -> 0.022696385 | AC47: 3365.2708 | AD47: =AC47/AC46-1 -> 0.049218583 | AF47: 1025.0406 | AG47: =AF47/AF46-1 -> 0.081917106
B48: 45796 | C48: 2271.0532 | D48: =C48/C47-1 -> -0.016187965 | F48: 24853.15 | G48: =F48/F47-1 -> -0.0066607401 | V48: 547.07031 | W48: =V48/V47-1 -> -0.036799085 | Z48: 253.11639 | AA48: =Z48/Z47-1 -> -0.01289831 | AC48: 3363.0264 | AD48: =AC48/AC47-1 -> -0.00066692547 | AF48: 1028.6298 | AG48: =AF48/AF47-1 -> 0.0035014332
B49: 45803 | C49: 2215.7358 | D49: =C49/C48-1 -> -0.02435759 | F49: 24750.699 | G49: =F49/F48-1 -> -0.004122261 | V49: 560.28119 | W49: =V49/V48-1 -> 0.024148407 | Z49: 246.79333 | AA49: =Z49/Z48-1 -> -0.024980836 | AC49: 3129.0359 | AD49: =AC49/AC48-1 -> -0.069577355 | AF49: 1076.1332 | AG49: =AF49/AF48-1 -> 0.04618126
B50: 45810 | C50: 2202.1025 | D50: =C50/C49-1 -> -0.006152945 | F50: 25003.051 | G50: =F50/F49-1 -> 0.010195735 | L50: SUMMARY OUTPUT-Kansai Nerolac | V50: 573.29498 | W50: =V50/V49-1 -> 0.023227255 | Z50: 242.3672 | AA50: =Z50/Z49-1 -> -0.017934569 | AC50: 3029.8098 | AD50: =AC50/AC49-1 -> -0.031711389 | AF50: 1071.5973 | AG50: =AF50/AF49-1 -> -0.0042149882
B51: 45817 | C51: 2191.7344 | D51: =C51/C50-1 -> -0.0047083021 | F51: 24718.6 | G51: =F51/F50-1 -> -0.011376659 | V51: 562.1051 | W51: =V51/V50-1 -> -0.019518539 | Z51: 235.84961 | AA51: =Z51/Z50-1 -> -0.0268914 | AC51: 3028.5005 | AD51: =AC51/AC50-1 -> -0.00043214797 | AF51: 1091.2367 | AG51: =AF51/AF50-1 -> 0.018327225
B52: 45824 | C52: 2262.5088 | D52: =C52/C51-1 -> 0.032291511 | F52: 25112.4 | G52: =F52/F51-1 -> 0.015931355 | L52: Regression Statistics | V52: 528.19049 | W52: =V52/V51-1 -> -0.060335001 | Z52: 233.27176 | AA52: =Z52/Z51-1 -> -0.01093006 | AC52: 2898.6929 | AD52: =AC52/AC51-1 -> -0.04286201 | AF52: 1117.5555 | AG52: =AF52/AF51-1 -> 0.024118368
B53: 45831 | C53: 2334.7681 | D53: =C53/C52-1 -> 0.031937678 | F53: 25637.801 | G53: =F53/F52-1 -> 0.02092195 | L53: Multiple R | M53: 0.4356364 | V53: 575.71039 | W53: =V53/V52-1 -> 0.089967348 | Z53: 245.17995 | AA53: =Z53/Z52-1 -> 0.051048562 | AC53: 3197.1196 | AD53: =AC53/AC52-1 -> 0.10295218 | AF53: 1157.5323 | AG53: =AF53/AF52-1 -> 0.035771651
B54: 45838 | C54: 2399.6035 | D54: =C54/C53-1 -> 0.027769546 | F54: 25461 | G54: =F54/F53-1 -> -0.0068960978 | L54: R Square | M54: 0.18977907 | V54: 587.59039 | W54: =V54/V53-1 -> 0.020635384 | Z54: 247.10698 | AA54: =Z54/Z53-1 -> 0.0078596659 | AC54: 3218.5356 | AD54: =AC54/AC53-1 -> 0.0066985343 | AF54: 1195.8145 | AG54: =AF54/AF53-1 -> 0.033072168
B55: 45845 | C55: 2414.4514 | D55: =C55/C54-1 -> 0.0061876474 | F55: 25149.85 | G55: =F55/F54-1 -> -0.012220667 | L55: Adjusted R Square | M55: 0.18183573 | V55: 564.47125 | W55: =V55/V54-1 -> -0.039345675 | Z55: 243.35172 | AA55: =Z55/Z54-1 -> -0.015196917 | AC55: 3406.6072 | AD55: =AC55/AC54-1 -> 0.058433882 | AF55: 1196.5122 | AG55: =AF55/AF54-1 -> 0.0005834968
B56: 45852 | C56: 2358.2275 | D56: =C56/C55-1 -> -0.023286398 | F56: 24968.4 | G56: =F56/F55-1 -> -0.0072147238 | L56: Standard Error | M56: 0.033496747 | V56: 568.66125 | W56: =V56/V55-1 -> 0.0074228801 | Z56: 245.17995 | AA56: =Z56/Z55-1 -> 0.0075127139 | AC56: 3397.2551 | AD56: =AC56/AC55-1 -> -0.0027452683 | AF56: 1197.4094 | AG56: =AF56/AF55-1 -> 0.00074986013
B57: 45859 | C57: 2312.4963 | D57: =C57/C56-1 -> -0.019392192 | F57: 24837 | G57: =F57/F56-1 -> -0.0052626676 | L57: Observations | M57: 104 | V57: 550.12653 | W57: =V57/V56-1 -> -0.03259362 | Z57: 242.067 | AA57: =Z57/Z56-1 -> -0.012696575 | AC57: 3550.2644 | AD57: =AC57/AC56-1 -> 0.045039089 | AF57: 1136.896 | AG57: =AF57/AF56-1 -> -0.050536956
B58: 45866 | C58: 2406.3345 | D58: =C58/C57-1 -> 0.040578717 | F58: 24565.35 | G58: =F58/F57-1 -> -0.010937327 | V58: 558.90094 | W58: =V58/V57-1 -> 0.015949811 | Z58: 247.10698 | AA58: =Z58/Z57-1 -> 0.020820591 | AC58: 3426.8889 | AD58: =AC58/AC57-1 -> -0.03475107 | AF58: 1200.8987 | AG58: =AF58/AF57-1 -> 0.05629599
B59: 45873 | C59: 2450.4822 | D59: =C59/C58-1 -> 0.018346454 | F59: 24363.301 | G59: =F59/F58-1 -> -0.0082249523 | L59: ANOVA | V59: 546.92072 | W59: =V59/V58-1 -> -0.021435327 | Z59: 230.14896 | AA59: =Z59/Z58-1 -> -0.068626241 | AC59: 3435.0891 | AD59: =AC59/AC58-1 -> 0.0023928979 | AF59: 1148.8591 | AG59: =AF59/AF58-1 -> -0.04333384
B60: 45880 | C60: 2503.0432 | D60: =C60/C59-1 -> 0.021449262 | F60: 24631.301 | G60: =F60/F59-1 -> 0.011000152 | M60: df | N60: SS | O60: MS | P60: F | Q60: Significance F | V60: 529.45264 | W60: =V60/V59-1 -> -0.03193896 | Z60: 232.67882 | AA60: =Z60/Z59-1 -> 0.010992279 | AC60: 3368.5259 | AD60: =AC60/AC59-1 -> -0.01937744 | AF60: 1103.798 | AG60: =AF60/AF59-1 -> -0.039222526
B61: 45887 | C61: 2479.0889 | D61: =C61/C60-1 -> -0.0095700888 | F61: 24870.1 | G61: =F61/F60-1 -> 0.0096949337 | L61: Regression | M61: 1 | N61: 0.026807129 | O61: 0.026807129 | P61: 23.891589 | Q61: 3.8011282e-06 | V61: 523.05096 | W61: =V61/V60-1 -> -0.012091114 | Z61: 229.88213 | AA61: =Z61/Z60-1 -> -0.012019538 | AC61: 3347.4541 | AD61: =AC61/AC60-1 -> -0.0062554892 | AF61: 1133.5 | AG61: =AF61/AF60-1 -> 0.026908934
B62: 45894 | C62: 2493.0459 | D62: =C62/C61-1 -> 0.0056299036 | F62: 24426.85 | G62: =F62/F61-1 -> -0.017822607 | L62: Residual | M62: 102 | N62: 0.11444727 | O62: 0.0011220321 | V62: 529.00598 | W62: =V62/V61-1 -> 0.011385157 | Z62: 237.16539 | AA62: =Z62/Z61-1 -> 0.031682603 | AC62: 3358.2854 | AD62: =AC62/AC61-1 -> 0.0032356826 | AF62: 1099.7 | AG62: =AF62/AF61-1 -> -0.029819187
B63: 45901 | C63: 2553.7239 | D63: =C63/C62-1 -> 0.024338893 | F63: 24741 | G63: =F63/F62-1 -> 0.012860864 | L63: Total | M63: 103 | N63: 0.1412544 | V63: 534.66327 | W63: =V63/V62-1 -> 0.010694185 | Z63: 240.02138 | AA63: =Z63/Z62-1 -> 0.012042177 | AC63: 3330.9119 | AD63: =AC63/AC62-1 -> -0.0081510449 | AF63: 1145.4 | AG63: =AF63/AF62-1 -> 0.041556857
B64: 45908 | C64: 2520.4648 | D64: =C64/C63-1 -> -0.013023739 | F64: 25114 | G64: =F64/F63-1 -> 0.015076189 | V64: 535.30841 | W64: =V64/V63-1 -> 0.0012066316 | Z64: 244.62653 | AA64: =Z64/Z63-1 -> 0.019186409 | AC64: 3314.5664 | AD64: =AC64/AC63-1 -> -0.0049072025 | AF64: 1146.5 | AG64: =AF64/AF63-1 -> 0.00096034186
B65: 45915 | C65: 2456.52 | D65: =C65/C64-1 -> -0.02537025 | F65: 25327.051 | G65: =F65/F64-1 -> 0.0084833472 | M65: Coefficients | N65: Standard Error | O65: t Stat | P65: P-value | Q65: Lower 95% | R65: Upper 95% | S65: Lower 95.0% | T65: Upper 95.0% | V65: 527.61646 | W65: =V65/V64-1 -> -0.014369204 | Z65: 248.8858 | AA65: =Z65/Z64-1 -> 0.017411347 | AC65: 3323.0344 | AD65: =AC65/AC64-1 -> 0.0025547889 | AF65: 1123 | AG65: =AF65/AF64-1 -> -0.020497165
B66: 45922 | C66: 2319.0295 | D66: =C66/C65-1 -> -0.055969615 | F66: 24654.699 | G66: =F66/F65-1 -> -0.026546777 | L66: Intercept | M66: -0.0023904009 | N66: 0.003284929 | O66: -0.72768723 | P66: 0.46847217 | Q66: -0.0089060419 | R66: 0.0041252402 | S66: -0.0089060419 | T66: 0.0041252402 | V66: 517.54254 | W66: =V66/V65-1 -> -0.019093251 | Z66: 243.67783 | AA66: =Z66/Z65-1 -> -0.020925168 | AC66: 3303.1445 | AD66: =AC66/AC65-1 -> -0.0059854609 | AF66: 1090.6 | AG66: =AF66/AF65-1 -> -0.028851313
B67: 45929 | C67: 2333.8772 | D67: =C67/C66-1 -> 0.00640253 | F67: 24894.25 | G67: =F67/F66-1 -> 0.0097162322 | L67: X Variable 1 | M67: 0.86687091 | N67: 0.1773503 | O67: 4.8879023 | P67: 3.8011282e-06 | Q67: 0.51509744 | R67: 1.2186444 | S67: 0.51509744 | T67: 1.2186444 | V67: 538.53406 | W67: =V67/V66-1 -> 0.040559982 | Z67: 249.3898 | AA67: =Z67/Z66-1 -> 0.023440685 | AC67: 3292.51 | AD67: =AC67/AC66-1 -> -0.0032195144 | AF67: 1084.1 | AG67: =AF67/AF66-1 -> -0.0059600221
B68: 45936 | C68: 2316.4558 | D68: =C68/C67-1 -> -0.0074645687 | F68: 25285.35 | G68: =F68/F67-1 -> 0.01571044 | V68: 531.13989 | W68: =V68/V67-1 -> -0.013730172 | Z68: 244.58699 | AA68: =Z68/Z67-1 -> -0.019258248 | AC68: 3293.593 | AD68: =AC68/AC67-1 -> 0.00032893076 | AF68: 1051.4 | AG68: =AF68/AF67-1 -> -0.030163225
B69: 45943 | C69: 2482.3555 | D69: =C69/C68-1 -> 0.071617882 | F69: 25709.85 | G69: =F69/F68-1 -> 0.016788378 | L69: SUMMARY OUTPUT-JSW Delux | V69: 540.81683 | W69: =V69/V68-1 -> 0.018219194 | Z69: 250.27919 | AA69: =Z69/Z68-1 -> 0.0232727 | AC69: 3343.3184 | AD69: =AC69/AC68-1 -> 0.015097598 | AF69: 1028.6 | AG69: =AF69/AF68-1 -> -0.021685418
B70: 45950 | C70: 2476.2183 | D70: =C70/C69-1 -> -0.0024723321 | F70: 25795.15 | G70: =F70/F69-1 -> 0.003317825 | V70: 541.56122 | W70: =V70/V69-1 -> 0.0013764083 | Z70: 250.98085 | AA70: =Z70/Z69-1 -> 0.0028035098 | AC70: 3233.135 | AD70: =AC70/AC69-1 -> -0.032956284 | AF70: 1032.6 | AG70: =AF70/AF69-1 -> 0.003888781
B71: 45957 | C71: 2485.325 | D71: =C71/C70-1 -> 0.0036776602 | F71: 25722.1 | G71: =F71/F70-1 -> -0.002831958 | L71: Regression Statistics | V71: 538.03778 | W71: =V71/V70-1 -> -0.0065060743 | Z71: 245.0416 | AA71: =Z71/Z70-1 -> -0.023664175 | AC71: 3191.9761 | AD71: =AC71/AC70-1 -> -0.012730349 | AF71: 999.90002 | AG71: =AF71/AF70-1 -> -0.031667589
B72: 45964 | C72: 2587.2798 | D72: =C72/C71-1 -> 0.041022738 | F72: 25492.301 | G72: =F72/F71-1 -> -0.0089339063 | L72: Multiple R | M72: 0.23458556 | V72: 527.07062 | W72: =V72/V71-1 -> -0.02038363 | Z72: 243.4209 | AA72: =Z72/Z71-1 -> -0.006613967 | AC72: 3212.2603 | AD72: =AC72/AC71-1 -> 0.0063547405 | AF72: 1004.1 | AG72: =AF72/AF71-1 -> 0.0042003711
B73: 45971 | C73: 2876.9111 | D73: =C73/C72-1 -> 0.11194435 | F73: 25910.051 | G73: =F73/F72-1 -> 0.016387301 | L73: R Square | M73: 0.055030384 | V73: 575.20715 | W73: =V73/V72-1 -> 0.091328437 | Z73: 245.8717 | AA73: =Z73/Z72-1 -> 0.010068181 | AC73: 3307.7722 | AD73: =AC73/AC72-1 -> 0.029733569 | AF73: 1298.8 | AG73: =AF73/AF72-1 -> 0.29349674
B74: 45978 | C74: 2851.8574 | D74: =C74/C73-1 -> -0.0087085453 | F74: 26068.15 | G74: =F74/F73-1 -> 0.0061018641 | L74: Adjusted R Square | M74: 0.045765976 | V74: 575.20715 | W74: =V74/V73-1 -> 0 | Z74: 230.06001 | AA74: =Z74/Z73-1 -> -0.064308707 | AC74: 3333.0781 | AD74: =AC74/AC73-1 -> 0.0076504386 | AF74: 1281.2 | AG74: =AF74/AF73-1 -> -0.013551045
B75: 45985 | C75: 2849.676 | D75: =C75/C74-1 -> -0.00076490377 | F75: 26202.949 | G75: =F75/F74-1 -> 0.0051710162 | L75: Standard Error | M75: 0.046992033 | V75: 560.3692 | W75: =V75/V74-1 -> -0.02579584 | Z75: 233.70659 | AA75: =Z75/Z74-1 -> 0.015850542 | AC75: 3260.0161 | AD75: =AC75/AC74-1 -> -0.021920282 | AF75: 1283.65 | AG75: =AF75/AF74-1 -> 0.001912327
B76: 45992 | C76: 2942.9668 | D76: =C76/C75-1 -> 0.032737325 | F76: 26186.449 | G76: =F76/F75-1 -> -0.00062970011 | L76: Observations | M76: 104 | V76: 550.34491 | W76: =V76/V75-1 -> -0.017888728 | Z76: 225.42522 | AA76: =Z76/Z75-1 -> -0.035434911 | AC76: 3459.5085 | AD76: =AC76/AC75-1 -> 0.061193695 | AF76: 1235.5 | AG76: =AF76/AF75-1 -> -0.037510243
B77: 45999 | C77: 2741.019 | D77: =C77/C76-1 -> -0.068620466 | F77: 26046.949 | G77: =F77/F76-1 -> -0.0053271827 | V77: 537.19415 | W77: =V77/V76-1 -> -0.023895482 | Z77: 220.86948 | AA77: =Z77/Z76-1 -> -0.020209542 | AC77: 3545.9617 | AD77: =AC77/AC76-1 -> 0.024990002 | AF77: 1233.9 | AG77: =AF77/AF76-1 -> -0.0012950025
B78: 46006 | C78: 2775.8169 | D78: =C78/C77-1 -> 0.012695224 | F78: 25966.4 | G78: =F78/F77-1 -> -0.0030924477 | L78: ANOVA | V78: 533.96851 | W78: =V78/V77-1 -> -0.0060046204 | Z78: 220.35559 | AA78: =Z78/Z77-1 -> -0.0023266479 | AC78: 3101.0918 | AD78: =AC78/AC77-1 -> -0.12545817 | AF78: 1188.6 | AG78: =AF78/AF77-1 -> -0.036712901
B79: 46013 | C79: 2722.8765 | D79: =C79/C78-1 -> -0.019072018 | F79: 26042.301 | G79: =F79/F78-1 -> 0.0029230232 | M79: df | N79: SS | O79: MS | P79: F | Q79: Significance F | V79: 537.98816 | W79: =V79/V78-1 -> 0.0075278847 | Z79: 234.62563 | AA79: =Z79/Z78-1 -> 0.064759123 | AC79: 3075.8845 | AD79: =AC79/AC78-1 -> -0.0081285164 | AF79: 1127.5 | AG79: =AF79/AF78-1 -> -0.051404995
B80: 46020 | C80: 2748.752 | D80: =C80/C79-1 -> 0.0095029975 | F80: 26328.551 | G80: =F80/F79-1 -> 0.010991732 | L80: Regression | M80: 1 | N80: 0.013116964 | O80: 0.013116964 | P80: 5.9399785 | Q80: 0.016532292 | V80: 520.17267 | W80: =V80/V79-1 -> -0.033115024 | Z80: 238.24255 | AA80: =Z80/Z79-1 -> 0.015415742 | AC80: 3162.3379 | AD80: =AC80/AC79-1 -> 0.028106832 | AF80: 1171.2 | AG80: =AF80/AF79-1 -> 0.038758272
B81: 46027 | C81: 2801.1968 | D81: =C81/C80-1 -> 0.019079504 | F81: 25683.301 | G81: =F81/F80-1 -> -0.024507616 | L81: Residual | M81: 102 | N81: 0.22524162 | O81: 0.0022082512 | V81: 510.34689 | W81: =V81/V80-1 -> -0.018889449 | Z81: 229.72401 | AA81: =Z81/Z80-1 -> -0.035755743 | AC81: 3085.8296 | AD81: =AC81/AC80-1 -> -0.024193588 | AF81: 1200.3 | AG81: =AF81/AF80-1 -> 0.024846396
B82: 46034 | C82: 2733.1868 | D82: =C82/C81-1 -> -0.024278912 | F82: 25694.35 | G82: =F82/F81-1 -> 0.00043019502 | L82: Total | M82: 103 | N82: 0.23835858 | V82: 515.85529 | W82: =V82/V81-1 -> 0.010793428 | Z82: 228.70613 | AA82: =Z82/Z81-1 -> -0.0044308964 | AC82: 3041.4214 | AD82: =AC82/AC81-1 -> -0.01439101 | AF82: 1236.4 | AG82: =AF82/AF81-1 -> 0.030075793
B83: 46041 | C83: 2680.4443 | D83: =C83/C82-1 -> -0.019297046 | F83: 25048.65 | G83: =F83/F82-1 -> -0.025130008 | V83: 500.71957 | W83: =V83/V82-1 -> -0.029341003 | Z83: 224.40733 | AA83: =Z83/Z82-1 -> -0.018796163 | AC83: 2893.5254 | AD83: =AC83/AC82-1 -> -0.048627262 | AF83: 1047.5 | AG83: =AF83/AF82-1 -> -0.15278229
B84: 46048 | C84: 2336.7266 | D84: =C84/C83-1 -> -0.12823164 | F84: 24825.449 | G84: =F84/F83-1 -> -0.0089107065 | M84: Coefficients | N84: Standard Error | O84: t Stat | P84: P-value | Q84: Lower 95% | R84: Upper 95% | S84: Lower 95.0% | T84: Upper 95.0% | V84: 459.38168 | W84: =V84/V83-1 -> -0.08255697 | Z84: 222.72734 | AA84: =Z84/Z83-1 -> -0.0074863537 | AC84: 2682.9062 | AD84: =AC84/AC83-1 -> -0.072789802 | AF84: 1031.6 | AG84: =AF84/AF83-1 -> -0.015179021
B85: 46055 | C85: 2380.4473 | D85: =C85/C84-1 -> 0.018710235 | F85: 25693.699 | G85: =F85/F84-1 -> 0.034974191 | L85: Intercept | M85: 0.00079683602 | N85: 0.0046083725 | O85: 0.1729105 | P85: 0.86306443 | Q85: -0.0083438491 | R85: 0.0099375211 | S85: -0.0083438491 | T85: 0.0099375211 | V85: 468.86011 | W85: =V85/V84-1 -> 0.020633004 | Z85: 211.82716 | AA85: =Z85/Z84-1 -> -0.048939555 | AC85: 2873.8323 | AD85: =AC85/AC84-1 -> 0.071163883 | AF85: 1008.9 | AG85: =AF85/AF84-1 -> -0.022004606
B86: 46062 | C86: 2346.0457 | D86: =C86/C85-1 -> -0.014451743 | F86: 25471.1 | G86: =F86/F85-1 -> -0.0086635874 | L86: X Variable 1 | M86: 0.60638151 | N86: 0.2488018 | O86: 2.4372071 | P86: 0.016532292 | Q86: 0.11288432 | R86: 1.0998787 | S86: 0.11288432 | T86: 1.0998787 | V86: 458.53802 | W86: =V86/V85-1 -> -0.022015271 | Z86: 197.6757 | AA86: =Z86/Z85-1 -> -0.066806629 | AC86: 2905.6365 | AD86: =AC86/AC85-1 -> 0.011066825 | AF86: 973.09998 | AG86: =AF86/AF85-1 -> -0.035484238
B87: 46069 | C87: 2407.2151 | D87: =C87/C86-1 -> 0.02607342 | F87: 25571.25 | G87: =F87/F86-1 -> 0.0039319225 | V87: 452.03714 | W87: =V87/V86-1 -> -0.014177417 | Z87: 196.35147 | AA87: =Z87/Z86-1 -> -0.0066990226 | AC87: 3007.5491 | AD87: =AC87/AC86-1 -> 0.035074105 | AF87: 944 | AG87: =AF87/AF86-1 -> -0.029904405
B88: 46076 | C88: 2355.7615 | D88: =C88/C87-1 -> -0.021374747 | F88: 25178.65 | G88: =F88/F87-1 -> -0.015353165 | V88: 452.68225 | W88: =V88/V87-1 -> 0.0014271196 | Z88: 201.11475 | AA88: =Z88/Z87-1 -> 0.024258923 | AC88: 2890.2759 | AD88: =AC88/AC87-1 -> -0.038992944 | AF88: 936.79999 | AG88: =AF88/AF87-1 -> -0.0076271316
B89: 46083 | C89: 2259.8931 | D89: =C89/C88-1 -> -0.040695295 | F89: 24450.449 | G89: =F89/F88-1 -> -0.028921374 | L89: SUMMARY OUTPUT-Indigo Paints | V89: 437.00064 | W89: =V89/V88-1 -> -0.03464154 | Z89: 186.96329 | AA89: =Z89/Z88-1 -> -0.070365098 | AC89: 2732.2378 | AD89: =AC89/AC88-1 -> -0.054679239 | AF89: 873.5 | AG89: =AF89/AF88-1 -> -0.06757044
B90: 46090 | C90: 2177.9045 | D90: =C90/C89-1 -> -0.036279825 | F90: 23151.1 | G90: =F90/F89-1 -> -0.053142157 | V90: 404.74417 | W90: =V90/V89-1 -> -0.073813324 | Z90: 179.99626 | AA90: =Z90/Z89-1 -> -0.037264138 | AC90: 2822.0388 | AD90: =AC90/AC89-1 -> 0.032867207 | AF90: 786.84998 | AG90: =AF90/AF89-1 -> -0.099198654
B91: 46097 | C91: 2176.5164 | D91: =C91/C90-1 -> -0.00063739414 | F91: 23114.5 | G91: =F91/F90-1 -> -0.0015809016 | L91: Regression Statistics | V91: 413.57748 | W91: =V91/V90-1 -> 0.021824435 | Z91: 164.80717 | AA91: =Z91/Z90-1 -> -0.084385569 | AC91: 2840.8459 | AD91: =AC91/AC90-1 -> 0.0066643764 | AF91: 743.75 | AG91: =AF91/AF90-1 -> -0.054775341
B92: 46104 | C92: 2188.4133 | D92: =C92/C91-1 -> 0.0054660617 | F92: 22819.6 | G92: =F92/F91-1 -> -0.012758242 | L92: Multiple R | M92: 0.39671678 | V92: 411.54285 | W92: =V92/V91-1 -> -0.004919604 | Z92: 168.49327 | AA92: =Z92/Z91-1 -> 0.022366115 | AC92: 2902.2888 | AD92: =AC92/AC91-1 -> 0.021628371 | AF92: 730.79999 | AG92: =AF92/AF91-1 -> -0.017411781
B93: 46111 | C93: 2150.3438 | D93: =C93/C92-1 -> -0.017395973 | F93: 22713.1 | G93: =F93/F92-1 -> -0.0046670407 | L93: R Square | M93: 0.15738421 | V93: 419.08591 | W93: =V93/V92-1 -> 0.018328736 | Z93: 176.49794 | AA93: =Z93/Z92-1 -> 0.047507352 | AC93: 2945.9094 | AD93: =AC93/AC92-1 -> 0.015029726 | AF93: 767.59998 | AG93: =AF93/AF92-1 -> 0.050355759
B94: 46118 | C94: 2340.3948 | D94: =C94/C93-1 -> 0.088381695 | F94: 24050.6 | G94: =F94/F93-1 -> 0.058886723 | L94: Adjusted R Square | M94: 0.14912327 | V94: 450.59799 | W94: =V94/V93-1 -> 0.075192423 | Z94: 189.26587 | AA94: =Z94/Z93-1 -> 0.072340386 | AC94: 2930.0562 | AD94: =AC94/AC93-1 -> -0.0053814524 | AF94: 810.90002 | AG94: =AF94/AF93-1 -> 0.056409654
B95: 46125 | C95: 2442.8062 | D95: =C95/C94-1 -> 0.043758163 | F95: 24353.551 | G95: =F95/F94-1 -> 0.012596408 | L95: Standard Error | M95: 0.047381004 | V95: 465.08859 | W95: =V95/V94-1 -> 0.0321586 | Z95: 200.69969 | AA95: =Z95/Z94-1 -> 0.060411434 | AC95: 2880.4294 | AD95: =AC95/AC94-1 -> -0.016937119 | AF95: 838 | AG95: =AF95/AF94-1 -> 0.033419626
B96: 46132 | C96: 2463.7249 | D96: =C96/C95-1 -> 0.0085633898 | F96: 23897.949 | G96: =F96/F95-1 -> -0.018707808 | L96: Observations | M96: 104 | V96: 456.95001 | W96: =V96/V95-1 -> -0.017498989 | Z96: 194.82959 | AA96: =Z96/Z95-1 -> -0.029248186 | AC96: 2902.5842 | AD96: =AC96/AC95-1 -> 0.0076914868 | AF96: 860.04999 | AG96: =AF96/AF95-1 -> 0.026312635
B97: 46139 | C97: 2423.4739 | D97: =C97/C96-1 -> -0.016337448 | F97: 23997.551 | G97: =F97/F96-1 -> 0.004167787 | V97: 469.55487 | W97: =V97/V96-1 -> 0.027584764 | Z97: 194.86913 | AA97: =Z97/Z96-1 -> 0.0002029236 | AC97: 2905.4397 | AD97: =AC97/AC96-1 -> 0.00098376775 | AF97: 860.20001 | AG97: =AF97/AF96-1 -> 0.00017443685
B98: 46146 | C98: 2577.5371 | D98: =C98/C97-1 -> 0.063571237 | F98: 24176.15 | G98: =F98/F97-1 -> 0.0074424099 | L98: ANOVA | V98: 511.88525 | W98: =V98/V97-1 -> 0.090150025 | Z98: 217.75655 | AA98: =Z98/Z97-1 -> 0.11745021 | AC98: 2904.1594 | AD98: =AC98/AC97-1 -> -0.00044064705 | AF98: 974.15002 | AG98: =AF98/AF97-1 -> 0.13246921
B99: 46153 | C99: 2583.1885 | D99: =C99/C98-1 -> 0.0021925454 | F99: 23643.5 | G99: =F99/F98-1 -> -0.02203206 | M99: df | N99: SS | O99: MS | P99: F | Q99: Significance F | V99: 529.45264 | W99: =V99/V98-1 -> 0.034318986 | Z99: 219.45631 | AA99: =Z99/Z98-1 -> 0.0078058185 | AC99: 2891.7529 | AD99: =AC99/AC98-1 -> -0.0042719742 | AF99: 985.29999 | AG99: =AF99/AF98-1 -> 0.011445838
B100: 46160 | C100: 2617.0942 | D100: =C100/C99-1 -> 0.013125547 | F100: 23719.301 | G100: =F100/F99-1 -> 0.0032059882 | L100: Regression | M100: 1 | N100: 0.042770097 | O100: 0.042770097 | P100: 19.051612 | Q100: 3.0559214e-05 | V100: 497.39465 | W100: =V100/V99-1 -> -0.060549294 | Z100: 215.37491 | AA100: =Z100/Z99-1 -> -0.018597805 | AC100: 2852.5635 | AD100: =AC100/AC99-1 -> -0.013552144 | AF100: 1003.4 | AG100: =AF100/AF99-1 -> 0.018370077
B101: 46167 | C101: 2648.6206 | D101: =C101/C100-1 -> 0.012046325 | F101: 23547.75 | G101: =F101/F100-1 -> -0.0072325396 | L101: Residual | M101: 102 | N101: 0.22898587 | O101: 0.0022449595 | V101: 496.84879 | W101: =V101/V100-1 -> -0.0010974543 | Z101: 215.4935 | AA101: =Z101/Z100-1 -> 0.00055062732 | AC101: 3103.4551 | AD101: =AC101/AC100-1 -> 0.08795303 | AF101: 990.90002 | AG101: =AF101/AF100-1 -> -0.012457644
B102: 46174 | C102: 2663.5906 | D102: =C102/C101-1 -> 0.0056519876 | F102: 23366.699 | G102: =F102/F101-1 -> -0.0076886658 | L102: Total | M102: 103 | N102: 0.27175597 | V102: 486.57635 | W102: =V102/V101-1 -> -0.020675165 | Z102: 208.40788 | AA102: =Z102/Z101-1 -> -0.032880885 | AC102: 3063.1824 | AD102: =AC102/AC101-1 -> -0.012976732 | AF102: 954.20001 | AG102: =AF102/AF101-1 -> -0.037037048
B103: 46181 | C103: 2723.7686 | D103: =C103/C102-1 -> 0.022592804 | F103: 23622.9 | G103: =F103/F102-1 -> 0.010964372 | V103: 511.28979 | W103: =V103/V102-1 -> 0.050790466 | Z103: 213.95186 | AA103: =Z103/Z102-1 -> 0.026601565 | AC103: 3119.8003 | AD103: =AC103/AC102-1 -> 0.018483366 | AF103: 995.20001 | AG103: =AF103/AF102-1 -> 0.042967931
...

Sheet Analysis-Beta Regression
B2: Observation — Regression Beta Sheet
B4: 1. Beta was estimated using a 2-year weekly regression of stock returns against Nifty 50, applied consistently across all five peer companies and Asian Paints itself.
B5: 2. For Asian Paints, this produced a raw (levered) beta of 0.96, adjusted to 0.97 using a weighted blend toward the market beta of 1.0 — a Blume adjustment, the standard 67%/33%.
B6: 3. This regression serves as an independent cross-check on the peer-comps-derived beta (0.93) used in the main WACC calculation — the two estimates converge closely (0.93–0.97), supporting confidence in the figure used.
B7: 4. The regression's R-squared of 0.27 means only ~27% of Asian Paints' weekly return variation is explained by market movements, so any individual beta estimate carries meaningful statistical uncertainty and should be treated as a point estimate with a wide confidence band, not a precise figure.

Sheet WACC
B2: Weighted Average Cost of Capital
B4: All figures are in INR unless stated otherwise.
B6: Peer Comps
G7: Debt/ | H7: Debt/ | I7: Levered | J7: Unlevered
B8: Name | C8: Country | D8: Total Debt | E8: Total Equity | F8: Tax Rate 1 | G8: Equity | H8: Capital | I8: Beta 2 | J8: Beta 3
B9: Asian Paints | C9: India | D9: ='Beta-Comps'!F3 -> 3928.93 | E9: ='Beta-Comps'!E3 -> 262340.6 | F9: 0.25 | G9: =D9/E9 -> 0.014976447 | H9: =D9/(D9+E9) -> 0.014755462 | I9: ='Beta-Regression'!M7 -> 0.96207015 | J9: =I9/(1+(1-F9)*G9) -> 0.95138389
B10: Berger Paints | C10: India | D10: ='Beta-Comps'!F4 -> 635.13 | E10: ='Beta-Comps'!E4 -> 61862.28 | F10: 0.25 | G10: =D10/E10 -> 0.010266838 | H10: =D10/(D10+E10) -> 0.010162501 | I10: ='Beta-Regression'!M46 -> 0.93277598 | J10: =I10/(1+(1-F10)*G10) -> 0.92564837
B11: Kansai Nerolac | C11: India | D11: ='Beta-Comps'!F5 -> 302.73 | E11: ='Beta-Comps'!E5 -> 17173.05 | F11: 0.25 | G11: =D11/E11 -> 0.017628202 | H11: =D11/(D11+E11) -> 0.017322832 | I11: ='Beta-Regression'!M67 -> 0.86687091 | J11: =I11/(1+(1-F11)*G11) -> 0.85555943
B12: JSW Dulux | C12: India | D12: ='Beta-Comps'!F6 -> 79.1 | E12: ='Beta-Comps'!E6 -> 13715.38 | F12: 0.25 | G12: =D12/E12 -> 0.0057672482 | H12: =D12/(D12+E12) -> 0.0057341777 | I12: ='Beta-Regression'!M86 -> 0.60638151 | J12: =I12/(1+(1-F12)*G12) -> 0.60376994
B13: Indigo Paints | C13: India | D13: ='Beta-Comps'!F7 -> 18.37 | E13: ='Beta-Comps'!E7 -> 5348.44 | F13: 0.25 | G13: =D13/E13 -> 0.0034346464 | H13: =D13/(D13+E13) -> 0.0034228899 | I13: ='Beta-Regression'!M106 -> 1.0949629 | J13: =I13/(1+(1-F13)*G13) -> 1.0921495
E15: Average | F15: =AVERAGE(F9:F13) -> 0.25 | G15: =AVERAGE(G9:G13) -> 0.010414676 | H15: =AVERAGE(H9:H13) -> 0.010279573 | I15: =AVERAGE(I9:I13) -> 0.89261229 | J15: =AVERAGE(J9:J13) -> 0.88570223
E16: Median | F16: =MEDIAN(F9:F13) -> 0.25 | G16: =MEDIAN(G9:G13) -> 0.010266838 | H16: =MEDIAN(H9:H13) -> 0.010162501 | I16: =MEDIAN(I9:I13) -> 0.93277598 | J16: =MEDIAN(J9:J13) -> 0.92564837
B20: Cost of Debt | G20: Cost of Equity
B22: Pre-tax Cost of Debt | E22: =HistoricalFS!L21/3929 -> 0.049735302 | G22: Risk Free Rate | J22: 0.06766
B23: Tax Rate | E23: =F15 -> 0.25 | G23: Equity Risk Premium | J23: =Rm!F13-WACC!J22 -> 0.061843341
B24: After Tax Cost of Debt | E24: =E22*(1-E23) -> 0.037301476 | G24: Levered Beta 4 | J24: =J33 -> 0.93277598
G25: Cost of Equity | J25: =J22+(J23*J24) -> 0.12534598
B28: Capital Structure | G28: Levered Beta
D30: Current | E30: Target | G30: Comps Median Unlevered Beta | J30: =J16 -> 0.92564837
B31: Total Debt | C31: =D9 -> 3928.93 | D31: =C31/$C$33 -> 0.014755462 | E31: =H16 -> 0.010162501 | G31: Target Debt/ Equity | J31: =E35 -> 0.010266838
B32: Market Capitalization | C32: =E9 -> 262340.6 | D32: =C32/$C$33 -> 0.98524454 | E32: =E33-E31 -> 0.9898375 | G32: Tax Rate | J32: =E23 -> 0.25
B33: Total Capitalization | C33: =SUM(C31:C32) -> 266269.53 | D33: =C33/$C$33 -> 1 | E33: =D33 -> 1 | G33: Levered Beta | J33: =J30*(1+(1-J32)*J31) -> 0.93277598
B35: Debt / Equity | D35: =D31/D32 -> 0.014976447 | E35: =E31/E32 -> 0.010266838
G37: Weighted Average Cost of Capital
B38: 1. Tax Rate considered as Marginal Tax Rate for the country
B39: 2. Levered Beta is based on 2 year weekly data | G39: Cost of Equity | J39: =J25 -> 0.12534598
B40: 3. Unlevered Beta = Levered Beta/(1+(1-Tax Rate) x Debt/Equity) | G40: Equity Weight | J40: =E32 -> 0.9898375
B41: 3. Levered Beta = Unlevered Beta*(1+(1-Tax Rate) x Debt/Equity)
G42: Cost of Debt | J42: =E24 -> 0.037301476
G43: Debt Weight | J43: =E31 -> 0.010162501
G45: WACC | J45: =(J39*J40)+(J42*J43) -> 0.12445123

Sheet WACC-Observations
B2: Objective
B3: Estimate Asian Paints' Weighted Average Cost of Capital — the minimum return the company must earn on invested capital to satisfy both shareholders and lenders — using a bottom-up peer-comparison approach.
B5: Observations
B7: 1. Selected 5 listed Indian paint peers and calculated each one's levered beta via a 2-year weekly regression against Nifty 50, applied consistently across all peers and Asian Paints itself.
B8: 2. Unlevered each peer's beta to isolate business (not financing) risk, then took the median unlevered beta (0.93) as the industry benchmark — chosen over a size-weighted average since Asian Paints alone represents ≈73% of peer equity and would otherwise dominate the estimate.
B9: 3. Relevered the industry beta using Asian Paints' target capital structure, with a target Debt/Equity ratio of 1.03%, to reflect the financing risk applicable to Asian Paints.
B10: 4.Cross-checked the result against the same regression technique applied directly to Asian Paints' own stock (raw beta 0.96, adjusted 0.97) — the two estimates converge closely, supporting confidence in the peer-based figure used.
B11: 5.Computed Cost of Equity via CAPM (12.53%) and after-tax Cost of Debt (~0.92%) using a 25% tax rate reflecting the current assumption.
B12: 6.Weighted both by the target capital structure to arrive at a final WACC of 12.42%.
B13: 7. The final WACC of 12.42% is driven primarily by the cost of equity because Asian Paints is overwhelmingly equity financed, with only 1.02% of target capital funded through debt.
B15: Limitations
B17: 1. Small peer sample (5 companies) — sensitive to any one company's data quality.
... B20: 4. Target capital structure assumes total capitalization stays fixed while only the debt/equity mix shifts — a simplifying assumption, not a prediction of actual financing activity.

Sheet Intrinsic Growth
B2: Calculation of ROIC | G2: ='Raw FS'!$J$2 -> 44621 | H2: ='Raw FS'!$K$2 -> 44986 | I2: ='Raw FS'!$L$2 -> 45352 | J2: ='Raw FS'!$M$2 -> 45717 | K2: ='Raw FS'!$N$2 -> 46082
B4: Current Assets
B5: ='Raw FS'!B35 -> Inventories | G5: ='Raw FS'!J35 -> 6153 | H5: ='Raw FS'!K35 -> 6211 | I5: ='Raw FS'!L35 -> 5923 | J5: ='Raw FS'!M35 -> 6719 | K5: ='Raw FS'!N35 -> 5744
B6: ='Raw FS'!B36 -> Trade receivables | G6: ='Raw FS'!J36 -> 3871 | H6: ='Raw FS'!K36 -> 4637 | I6: ='Raw FS'!L36 -> 4889 | J6: ='Raw FS'!M36 -> 4314 | K6: ='Raw FS'!N36 -> 4462
B7: ='Raw FS'!B38 -> Loans n Advances | G7: ='Raw FS'!J38 -> 8 | H7: ='Raw FS'!K38 -> 12 | I7: ='Raw FS'!L38 -> 17 | J7: ='Raw FS'!M38 -> 22 | K7: ='Raw FS'!N38 -> 27
B8: ='Raw FS'!B39 -> Other asset items | G8: ='Raw FS'!J39 -> 2869 | H8: ='Raw FS'!K39 -> 3024 | I8: ='Raw FS'!L39 -> 3555 | J8: ='Raw FS'!M39 -> 3319 | K8: ='Raw FS'!N39 -> 4662
B9: Total Current Assets | G9: =SUM(G5:G8) -> 12901 | H9: =SUM(H5:H8) -> 13884 | I9: =SUM(I5:I8) -> 14384 | J9: =SUM(J5:J8) -> 14374 | K9: =SUM(K5:K8) -> 14895
B11: Current Liabilities
B12: ='Raw FS'!B13 -> Trade Payables | G12: ='Raw FS'!J13 -> 4164 | H12: ='Raw FS'!K13 -> 3635 | I12: ='Raw FS'!L13 -> 3831 | J12: ='Raw FS'!M13 -> 3848 | K12: ='Raw FS'!N13 -> 3863
B13: ='Raw FS'!B14 -> Advance from Customers | G13: ='Raw FS'!J14 -> 76 | H13: ='Raw FS'!K14 -> 108 | I13: ='Raw FS'!L14 -> 154 | J13: ='Raw FS'!M14 -> 174 | K13: ='Raw FS'!N14 -> 107
B14: ='Raw FS'!B15 -> Other liability items | G14: ='Raw FS'!J15 -> 2932 | H14: ='Raw FS'!K15 -> 3657 | I14: ='Raw FS'!L15 -> 4017 | J14: ='Raw FS'!M15 -> 3984 | K14: ='Raw FS'!N15 -> 4604
B15: Total Current Liabilities | G15: =SUM(G12:G14) -> 7172 | H15: =SUM(H12:H14) -> 7400 | I15: =SUM(I12:I14) -> 8002 | J15: =SUM(J12:J14) -> 8006 | K15: =SUM(K12:K14) -> 8574
A17: # | B17: Net Working Capital | G17: =G9-G15 -> 5729 | H17: =H9-H15 -> 6484 | I17: =I9-I15 -> 6382 | J17: =J9-J15 -> 6368 | K17: =K9-K15 -> 6321
B19: Non Current Assets
B20: ='Raw FS'!B19 -> Land | G20: ='Raw FS'!J19 -> 644 | H20: ='Raw FS'!K19 -> 804 | I20: ='Raw FS'!L19 -> 1126 | J20: ='Raw FS'!M19 -> 1035 | K20: ='Raw FS'!N19 -> 1204
B21: ='Raw FS'!B20 -> Building | G21: ='Raw FS'!J20 -> 2325 | H21: ='Raw FS'!K20 -> 2883 | I21: ='Raw FS'!L20 -> 3390 | J21: ='Raw FS'!M20 -> 3771 | K21: ='Raw FS'!N20 -> 4124
B22: ='Raw FS'!B21 -> Plant Machinery | G22: ='Raw FS'!J21 -> 4531 | H22: ='Raw FS'!K21 -> 4825 | I22: ='Raw FS'!L21 -> 5422 | J22: ='Raw FS'!M21 -> 7576 | K22: ='Raw FS'!N21 -> 8210
B23: ='Raw FS'!B22 -> Equipments | G23: ='Raw FS'!J22 -> 253 | H23: ='Raw FS'!K22 -> 270 | I23: ='Raw FS'!L22 -> 298 | J23: ='Raw FS'!M22 -> 325 | K23: ='Raw FS'!N22 -> 351
B24: ='Raw FS'!B23 -> Furniture n fittings | G24: ='Raw FS'!J23 -> 113 | H24: ='Raw FS'!K23 -> 146 | I24: ='Raw FS'!L23 -> 175 | J24: ='Raw FS'!M23 -> 203 | K24: ='Raw FS'!N23 -> 216
B25: ='Raw FS'!B24 -> Vehicles | G25: ='Raw FS'!J24 -> 32 | H25: ='Raw FS'!K24 -> 36 | I25: ='Raw FS'!L24 -> 40 | J25: ='Raw FS'!M24 -> 34 | K25: ='Raw FS'!N24 -> 45
B26: ='Raw FS'!B25 -> Intangible Assets | G26: ='Raw FS'!J25 -> 345 | H26: ='Raw FS'!K25 -> 422 | I26: ='Raw FS'!L25 -> 850 | J26: ='Raw FS'!M25 -> 827 | K26: ='Raw FS'!N25 -> 833
B27: ='Raw FS'!B26 -> Other fixed assets | G27: ='Raw FS'!J26 -> 294 | H27: ='Raw FS'!K26 -> 289 | I27: ='Raw FS'!L26 -> 321 | J27: ='Raw FS'!M26 -> 328 | K27: ='Raw FS'!N26 -> 335
B29: Gross Block | G29: =SUM(G20:G27) -> 8537 | H29: =SUM(H20:H27) -> 9675 | I29: =SUM(I20:I27) -> 11622 | J29: =SUM(J20:J27) -> 14099 | K29: =SUM(K20:K27) -> 15318
B30: Accumulated Depreciation | G30: =-'Raw FS'!C28 -> -1452 | H30: =-'Raw FS'!D28 -> -327 | I30: =-'Raw FS'!E28 -> -610 | J30: =-'Raw FS'!F28 -> -973 | K30: =-'Raw FS'!G28 -> -1644
A31: # | B31: Net Non Current Assets | G31: =SUM(G29:G30) -> 7085 | H31: =SUM(H29:H30) -> 9348 | I31: =SUM(I29:I30) -> 11012 | J31: =SUM(J29:J30) -> 13126 | K31: =SUM(K29:K30) -> 13674
A33: # | B33: Invested Capital | G33: =G31+G17 -> 12814 | H33: =H31+H17 -> 15832 | I33: =I31+I17 -> 17394 | J33: =J31+J17 -> 19494 | K33: =K31+K17 -> 19995
B34: EBIT | G34: =HistoricalFS!H27+HistoricalFS!H21 -> 5781.86 | H34: =HistoricalFS!I27+HistoricalFS!I21 -> 7438.23 | I34: =HistoricalFS!J27+HistoricalFS!J21 -> 9066.9 | J34: =HistoricalFS!K27+HistoricalFS!K21 -> 7585.65 | K34: =HistoricalFS!L27+HistoricalFS!L21 -> 8280.61
B35: EBIT(1-T) | G35: =G34*(1-G44) -> 4336.395 | H35: =H34*(1-H44) -> 5578.6725 | I35: =I34*(1-I44) -> 6800.175 | J35: =J34*(1-J44) -> 5689.2375 | K35: =K34*(1-K44) -> 6210.4575
A36: # | B36: ROIC | G36: =G35/G33 -> 0.33841072 | H36: =H35/H33 -> 0.35236688 | I36: =I35/I33 -> 0.39094947 | J36: =J35/J33 -> 0.29184557 | K36: =K35/K33 -> 0.31060053
B38: Calculation of Reinvestment Rate | G38: =G2 -> 44621 | H38: =H2 -> 44986 | I38: =I2 -> 45352 | J38: =J2 -> 45717 | K38: =K2 -> 46082
B40: Net Capex | G40: =-SUM('Raw FS'!J53:J54) -> 511 | H40: =-SUM('Raw FS'!K53:K54) -> 1420 | I40: =-SUM('Raw FS'!L53:L54) -> 2491 | J40: =-SUM('Raw FS'!M53:M54) -> 1820 | K40: =-SUM('Raw FS'!N53:N54) -> 1484
B41: Change in Working Capital | H41: =H17-G17 -> 755 | I41: =I17-H17 -> -102 | J41: =J17-I17 -> -14 | K41: =K17-J17 -> -47
B43: EBIT | G43: =G34 -> 5781.86 | H43: =H34 -> 7438.23 | I43: =I34 -> 9066.9 | J43: =J34 -> 7585.65 | K43: =K34 -> 8280.61
B44: Marginal Tax Rate | G44: 0.25 | H44: 0.25 | I44: 0.25 | J44: 0.25 | K44: 0.25
B45: EBIT(1-T) | G45: =G43*(1-G44) -> 4336.395 | H45: =H43*(1-H44) -> 5578.6725 | I45: =I43*(1-I44) -> 6800.175 | J45: =J43*(1-J44) -> 5689.2375 | K45: =K43*(1-K44) -> 6210.4575
B47: Reinvestment | H47: =SUM(H40:H41) -> 2175 | I47: =SUM(I40:I41) -> 2389 | J47: =SUM(J40:J41) -> 1806 | K47: =SUM(K40:K41) -> 1437
B49: Reinvestment rate | H49: =H47/H45 -> 0.3898777 | I49: =I47/I45 -> 0.35131449 | J49: =J47/J45 -> 0.31744148 | K49: =K47/K45 -> 0.23138392
J51: 4 Year Average | K51: =AVERAGE(H49:K49) -> 0.3225044
J52: 4 year Median | K52: =MEDIAN(H49:K49) -> 0.33437799
B54: Calculation of Growth Rate | G54: ='Raw FS'!$J$2 -> 44621 | H54: ='Raw FS'!$K$2 -> 44986 | I54: ='Raw FS'!$L$2 -> 45352 | J54: ='Raw FS'!$M$2 -> 45717 | K54: ='Raw FS'!$N$2 -> 46082
B56: Reinvestment rate | H56: =H49 -> 0.3898777 | I56: =I49 -> 0.35131449 | J56: =J49 -> 0.31744148 | K56: =K49 -> 0.23138392
B57: ROIC | H57: =H36 -> 0.35236688 | I57: =I36 -> 0.39094947 | J57: =J36 -> 0.29184557 | K57: =K36 -> 0.31060053
B59: Intrinsic Growth | H59: =H56*H57 -> 0.13737999 | I59: =I56*I57 -> 0.13734621 | J59: =J56*J57 -> 0.09264389 | K59: =K56*K57 -> 0.071867967
J61: 4 Year Average | K61: =AVERAGE(H59:K59) -> 0.10980951
J62: 4 year Median | K62: =MEDIAN(H59:K59) -> 0.11499505

Sheet Analysis-Intrinsic growth
B2: Observations
B3: A) On Invested Capital
B4: 1.Invested Capital = Net Working Capital + Net Non-Current Assets — i.e., total capital tied up in operations (working capital + net fixed assets), independent of how that capital was financed (debt vs. equity).
B5: 2.Invested Capital grew steadily from ₹12,814 Cr (Mar-22) to ₹19,995 Cr (Mar-26), roughly 56% growth over 4 years — driven mainly by a large increase in Non-Current Assets (Gross Block nearly doubled, ₹8,537 Cr → ₹15,318 Cr), while Net Working Capital stayed relatively flat (₹5,729 Cr → ₹6,321 Cr).
B7: B) On ROIC
B8: 3. ROIC = EBIT(1−T) ÷ Invested Capital
B9: 4. ROIC ranged from ~29% to ~39% over the 5 years, peaking in Mar-24 (39.09%) and dipping to its lowest in Mar-25 (29.18%).
B10: 5. The Mar-25 dip coincides with a large capex year — Gross Block jumped by ~₹2,477 Cr between Mar-24 and Mar-25 — a common pattern where large new asset additions temporarily depress ROIC before those assets start generating proportional returns.
B12: On Reinvestment Rate
B13: 6. Reinvestment Rate = (Net Capex + Change in Working Capital) ÷ EBIT(1−T) — the share of after-tax operating profit plowed back into the business.
B14: 7. Reinvestment Rate declined steadily and consistently every year: 38.99% (Mar-23) → 35.13% → 31.74% → 23.14% (Mar-26) — a clear downward trend, not just noise.
B15: 8. This decline could reflect either improving capital efficiency (needing less reinvestment to sustain/grow the business) or a maturing growth phase
... B20: 11.Intrinsic Growth fell from ~13.7% (Mar-23/24) to ~7.2% (Mar-26) — a clear decelerating trend, driven almost entirely by the falling Reinvestment Rate rather than by ROIC (which stayed range-bound).

Sheet CommonSize Statement
B2: ="Common Size Income Statement -"&'Data Sheet'!$B$1 -> Common Size Income Statement -ASIAN PAINTS LTD
B4: Particulars | D4: ='Data Sheet'!B16 -> 42825 | E4: ='Data Sheet'!C16 -> 43190 | F4: ='Data Sheet'!D16 -> 43555 | G4: ='Data Sheet'!E16 -> 43921 | H4: ='Data Sheet'!F16 -> 44286 | I4: ='Data Sheet'!G16 -> 44651 | J4: ='Data Sheet'!H16 -> 45016 | K4: ='Data Sheet'!I16 -> 45382 | ... M4: ='Data Sheet'!K16 -> 46112
B6: ='Data Sheet'!A17 -> Sales | D6: ='Data Sheet'!B17/'Data Sheet'!B$17 -> 1 | E6: ='Data Sheet'!C17/'Data Sheet'!C$17 -> 1 | F6: ='Data Sheet'!D17/'Data Sheet'!D$17 -> 1 | G6: ='Data Sheet'!E17/'Data Sheet'!E$17 -> 1 | H6: ='Data Sheet'!F17/'Data Sheet'!F$17 -> 1 | I6: ='Data Sheet'!G17/'Data Sheet'!G$17 -> 1 | J6: ='Data Sheet'!H17/'Data Sheet'!H$17 -> 1 | K6: ='Data Sheet'!I17/'Data Sheet'!I$17 -> 1 | ... M6: ='Data Sheet'!K17/'Data Sheet'!K$17 -> 1
B7: ='Data Sheet'!A18 -> Raw Material Cost | D7: ='Data Sheet'!B18/'Data Sheet'!B$17 -> 0.49479518 | E7: ='Data Sheet'!C18/'Data Sheet'!C$17 -> 0.48311366 | F7: ='Data Sheet'!D18/'Data Sheet'!D$17 -> 0.51841646 | G7: ='Data Sheet'!E18/'Data Sheet'!E$17 -> 0.49388286 | H7: ='Data Sheet'!F18/'Data Sheet'!F$17 -> 0.48015709 | I7: ='Data Sheet'!G18/'Data Sheet'!G$17 -> 0.58840195 | J7: ='Data Sheet'!H18/'Data Sheet'!H$17 -> 0.55048728 | K7: ='Data Sheet'!I18/'Data Sheet'!I$17 -> 0.49051902 | ... M7: ='Data Sheet'!K18/'Data Sheet'!K$17 -> 0.48173987
B8: ='Data Sheet'!A19 -> Change in Inventory | D8: ='Data Sheet'!B19/'Data Sheet'!B$17 -> 0.035094964 | E8: ='Data Sheet'!C19/'Data Sheet'!C$17 -> -0.0084477742 | F8: ='Data Sheet'!D19/'Data Sheet'!D$17 -> 0.015242101 | G8: ='Data Sheet'!E19/'Data Sheet'!E$17 -> 0.011832519 | H8: ='Data Sheet'!F19/'Data Sheet'!F$17 -> 0.0042578591 | I8: ='Data Sheet'!G19/'Data Sheet'!G$17 -> 0.045529612 | J8: ='Data Sheet'!H19/'Data Sheet'!H$17 -> 0.0089806513 | K8: ='Data Sheet'!I19/'Data Sheet'!I$17 -> -0.010249409 | ... M8: ='Data Sheet'!K19/'Data Sheet'!K$17 -> -0.016965147
B9: ='Data Sheet'!A20 -> Power and Fuel | D9: ='Data Sheet'!B20/'Data Sheet'!B$17 -> 0.0070389105 | E9: ='Data Sheet'!C20/'Data Sheet'!C$17 -> 0.006555896 | F9: ='Data Sheet'!D20/'Data Sheet'!D$17 -> 0.0062177335 | G9: ='Data Sheet'!E20/'Data Sheet'!E$17 -> 0.0048383945 | H9: ='Data Sheet'!F20/'Data Sheet'!F$17 -> 0.0039631019 | I9: ='Data Sheet'!G20/'Data Sheet'!G$17 -> 0.0040283451 | J9: ='Data Sheet'!H20/'Data Sheet'!H$17 -> 0.0040097319 | K9: ='Data Sheet'!I20/'Data Sheet'!I$17 -> 0.0037540784 | ... M9: ='Data Sheet'!K20/'Data Sheet'!K$17 -> 0.0046959915
B10: ='Data Sheet'!A21 -> Other Mfr. Exp | D10: ='Data Sheet'!B21/'Data Sheet'!B$17 -> 0.11039378 | E10: ='Data Sheet'!C21/'Data Sheet'!C$17 -> 0.10054831 | F10: ='Data Sheet'!D21/'Data Sheet'!D$17 -> 0.096795084 | G10: ='Data Sheet'!E21/'Data Sheet'!E$17 -> 0.096288948 | H10: ='Data Sheet'!F21/'Data Sheet'!F$17 -> 0.09525768 | I10: ='Data Sheet'!G21/'Data Sheet'!G$17 -> 0.098980182 | J10: ='Data Sheet'!H21/'Data Sheet'!H$17 -> 0.084555501 | K10: ='Data Sheet'!I21/'Data Sheet'!I$17 -> 0.077960306 | ... M10: ='Data Sheet'!K21/'Data Sheet'!K$17 -> 0.077763764
B11: ='Data Sheet'!A22 -> Employee Cost | D11: ='Data Sheet'!B22/'Data Sheet'!B$17 -> 0.069040678 | E11: ='Data Sheet'!C22/'Data Sheet'!C$17 -> 0.066681724 | F11: ='Data Sheet'!D22/'Data Sheet'!D$17 -> 0.064588441 | G11: ='Data Sheet'!E22/'Data Sheet'!E$17 -> 0.067846867 | H11: ='Data Sheet'!F22/'Data Sheet'!F$17 -> 0.071276423 | I11: ='Data Sheet'!G22/'Data Sheet'!G$17 -> 0.061667734 | J11: ='Data Sheet'!H22/'Data Sheet'!H$17 -> 0.059045905 | K11: ='Data Sheet'!I22/'Data Sheet'!I$17 -> 0.06578216 | ... M11: ='Data Sheet'!K22/'Data Sheet'!K$17 -> 0.078961509
B12: ='Data Sheet'!A23 -> Selling and admin | D12: ='Data Sheet'!B23/'Data Sheet'!B$17 -> 0.28973861 | E12: ='Data Sheet'!C23/'Data Sheet'!C$17 -> 0.13402558 | F12: ='Data Sheet'!D23/'Data Sheet'!D$17 -> 0.12301736 | G12: ='Data Sheet'!E23/'Data Sheet'!E$17 -> 0.11436749 | H12: ='Data Sheet'!F23/'Data Sheet'!F$17 -> 0.10342706 | I12: ='Data Sheet'!G23/'Data Sheet'!G$17 -> 0.10109452 | J12: ='Data Sheet'!H23/'Data Sheet'!H$17 -> 0.10150719 | K12: ='Data Sheet'!I23/'Data Sheet'!I$17 -> 0.10739228 | ... M12: ='Data Sheet'!K23/'Data Sheet'!K$17 -> 0.11556102
B13: ='Data Sheet'!A24 -> Other Expenses | D13: ='Data Sheet'!B24/'Data Sheet'!B$17 -> -0.13467477 | E13: ='Data Sheet'!C24/'Data Sheet'!C$17 -> 0.010190466 | F13: ='Data Sheet'!D24/'Data Sheet'!D$17 -> 0.010525397 | G13: ='Data Sheet'!E24/'Data Sheet'!E$17 -> 0.028694415 | H13: ='Data Sheet'!F24/'Data Sheet'!F$17 -> 0.026547947 | I13: ='Data Sheet'!G24/'Data Sheet'!G$17 -> 0.026291627 | J13: ='Data Sheet'!H24/'Data Sheet'!H$17 -> 0.027870377 | K13: ='Data Sheet'!I24/'Data Sheet'!I$17 -> 0.03064962 | ... M13: ='Data Sheet'!K24/'Data Sheet'!K$17 -> 0.036030985
B14: ='Data Sheet'!A25 -> Other Income | D14: ='Data Sheet'!B25/'Data Sheet'!B$17 -> 0.022433955 | E14: ='Data Sheet'!C25/'Data Sheet'!C$17 -> 0.019995186 | F14: ='Data Sheet'!D25/'Data Sheet'!D$17 -> 0.014229114 | G14: ='Data Sheet'!E25/'Data Sheet'!E$17 -> 0.017322036 | H14: ='Data Sheet'!F25/'Data Sheet'!F$17 -> 0.015274407 | I14: ='Data Sheet'!G25/'Data Sheet'!G$17 -> 0.01016725 | J14: ='Data Sheet'!H25/'Data Sheet'!H$17 -> 0.012510224 | K14: ='Data Sheet'!I25/'Data Sheet'!I$17 -> 0.023129067 | ... M14: ='Data Sheet'!K25/'Data Sheet'!K$17 -> 0.020458054
B15: ='Data Sheet'!A26 -> Depreciation | D15: ='Data Sheet'!B26/'Data Sheet'!B$17 -> 0.022227475 | E15: ='Data Sheet'!C26/'Data Sheet'!C$17 -> 0.021425239 | F15: ='Data Sheet'!D26/'Data Sheet'!D$17 -> 0.03233554 | G15: ='Data Sheet'!E26/'Data Sheet'!E$17 -> 0.038617107 | H15: ='Data Sheet'!F26/'Data Sheet'!F$17 -> 0.036442576 | I15: ='Data Sheet'!G26/'Data Sheet'!G$17 -> 0.028052374 | J15: ='Data Sheet'!H26/'Data Sheet'!H$17 -> 0.024878373 | K15: ='Data Sheet'!I26/'Data Sheet'!I$17 -> 0.024031737 | ... M15: ='Data Sheet'!K26/'Data Sheet'!K$17 -> 0.034534226
B16: ='Data Sheet'!A27 -> Interest | D16: ='Data Sheet'!B27/'Data Sheet'!B$17 -> 0.0024784242 | E16: ='Data Sheet'!C27/'Data Sheet'!C$17 -> 0.0024648505 | F16: ='Data Sheet'!D27/'Data Sheet'!D$17 -> 0.0057416452 | G16: ='Data Sheet'!E27/'Data Sheet'!E$17 -> 0.0050630218 | H16: ='Data Sheet'!F27/'Data Sheet'!F$17 -> 0.0042200933 | I16: ='Data Sheet'!G27/'Data Sheet'!G$17 -> 0.0032785499 | J16: ='Data Sheet'!H27/'Data Sheet'!H$17 -> 0.0041883417 | K16: ='Data Sheet'!I27/'Data Sheet'!I$17 -> 0.0057802947 | ... M16: ='Data Sheet'!K27/'Data Sheet'!K$17 -> 0.005491584
B17: ='Data Sheet'!A28 -> Profit before tax | D17: ='Data Sheet'!B28/'Data Sheet'!B$17 -> 0.19649064 | E17: ='Data Sheet'!C28/'Data Sheet'!C$17 -> 0.18654169 | F17: ='Data Sheet'!D28/'Data Sheet'!D$17 -> 0.17183356 | G17: ='Data Sheet'!E28/'Data Sheet'!E$17 -> 0.17955545 | H17: ='Data Sheet'!F28/'Data Sheet'!F$17 -> 0.1982403 | I17: ='Data Sheet'!G28/'Data Sheet'!G$17 -> 0.14390157 | J17: ='Data Sheet'!H28/'Data Sheet'!H$17 -> 0.16494818 | K17: ='Data Sheet'!I28/'Data Sheet'!I$17 -> 0.20701017 | ... M17: ='Data Sheet'!K28/'Data Sheet'!K$17 -> 0.16871396
... B20: ='Data Sheet'!A31 -> Dividend Amount | D20: ='Data Sheet'!B31/'Data Sheet'!B$17 -> 0.065594254 | E20: ='Data Sheet'!C31/'Data Sheet'!C$17 -> 0.049600138 | F20: ='Data Sheet'!D31/'Data Sheet'!D$17 -> 0.05234684 | G20: ='Data Sheet'!E31/'Data Sheet'!E$17 -> 0.056950461 | H20: ='Data Sheet'!F31/'Data Sheet'!F$17 -> 0.078855366 | I20: ='Data Sheet'!G31/'Data Sheet'!G$17 -> 0.063119904 | J20: ='Data Sheet'!H31/'Data Sheet'!H$17 -> 0.071338086 | K20: ='Data Sheet'!I31/'Data Sheet'!I$17 -> 0.089989134 | ... M20: ='Data Sheet'!K31/'Data Sheet'!K$17 -> 0.07412978
B24: ="Common Size Balance Sheet -"&'Data Sheet'!$B$1 -> Common Size Balance Sheet -ASIAN PAINTS LTD
B26: Particulars | D26: ='Data Sheet'!B56 -> 42825 | E26: ='Data Sheet'!C56 -> 43190 | F26: ='Data Sheet'!D56 -> 43555 | G26: ='Data Sheet'!E56 -> 43921 | H26: ='Data Sheet'!F56 -> 44286 | I26: ='Data Sheet'!G56 -> 44651 | J26: ='Data Sheet'!H56 -> 45016 | K26: ='Data Sheet'!I56 -> 45382 | ... M26: ='Data Sheet'!K56 -> 46112
B28: Total Liabilities | D28: ='Data Sheet'!B61/'Data Sheet'!B$61 -> 1 | E28: ='Data Sheet'!C61/'Data Sheet'!C$61 -> 1 | F28: ='Data Sheet'!D61/'Data Sheet'!D$61 -> 1 | G28: ='Data Sheet'!E61/'Data Sheet'!E$61 -> 1 | H28: ='Data Sheet'!F61/'Data Sheet'!F$61 -> 1 | I28: ='Data Sheet'!G61/'Data Sheet'!G$61 -> 1 | J28: ='Data Sheet'!H61/'Data Sheet'!H$61 -> 1 | K28: ='Data Sheet'!I61/'Data Sheet'!I$61 -> 1 | ... M28: ='Data Sheet'!K61/'Data Sheet'!K$61 -> 1
B29: ='Data Sheet'!A57 -> Equity Share Capital | D29: ='Data Sheet'!B57/'Data Sheet'!B$61 -> 0.0077322476 | E29: ='Data Sheet'!C57/'Data Sheet'!C$61 -> 0.0069691677 | F29: ='Data Sheet'!D57/'Data Sheet'!D$61 -> 0.0059031906 | G29: ='Data Sheet'!E57/'Data Sheet'!E$61 -> 0.0059437463 | H29: ='Data Sheet'!F57/'Data Sheet'!F$61 -> 0.004712277 | I29: ='Data Sheet'!G57/'Data Sheet'!G$61 -> 0.004177986 | J29: ='Data Sheet'!H57/'Data Sheet'!H$61 -> 0.0037208104 | K29: ='Data Sheet'!I57/'Data Sheet'!I$61 -> 0.0032079441 | ... M29: ='Data Sheet'!K57/'Data Sheet'!K$61 -> 0.0027787796
B30: ='Data Sheet'!A58 -> Reserves | D30: ='Data Sheet'!B58/'Data Sheet'!B$61 -> 0.60522813 | E30: ='Data Sheet'!C58/'Data Sheet'!C$61 -> 0.60408487 | F30: ='Data Sheet'!D58/'Data Sheet'!D$61 -> 0.57694149 | G30: ='Data Sheet'!E58/'Data Sheet'!E$61 -> 0.62177833 | H30: ='Data Sheet'!F58/'Data Sheet'!F$61 -> 0.62442435 | I30: ='Data Sheet'!G58/'Data Sheet'!G$61 -> 0.59741193 | J30: ='Data Sheet'!H58/'Data Sheet'!H$61 -> 0.61663007 | K30: ='Data Sheet'!I58/'Data Sheet'!I$61 -> 0.62314047 | ... M30: ='Data Sheet'!K58/'Data Sheet'!K$61 -> 0.61635111
B31: ='Data Sheet'!A59 -> Borrowings | D31: ='Data Sheet'!B59/'Data Sheet'!B$61 -> 0.045169804 | E31: ='Data Sheet'!C59/'Data Sheet'!C$61 -> 0.038756913 | F31: ='Data Sheet'!D59/'Data Sheet'!D$61 -> 0.081211951 | G31: ='Data Sheet'!E59/'Data Sheet'!E$61 -> 0.069308593 | H31: ='Data Sheet'!F59/'Data Sheet'!F$61 -> 0.053701879 | I31: ='Data Sheet'!G59/'Data Sheet'!G$61 -> 0.069119709 | J31: ='Data Sheet'!H59/'Data Sheet'!H$61 -> 0.074967813 | K31: ='Data Sheet'!I59/'Data Sheet'!I$61 -> 0.082753053 | ... M31: ='Data Sheet'!K59/'Data Sheet'!K$61 -> 0.11382017
B32: ='Data Sheet'!A60 -> Other Liabilities | D32: ='Data Sheet'!B60/'Data Sheet'!B$61 -> 0.34186981 | E32: ='Data Sheet'!C60/'Data Sheet'!C$61 -> 0.35018905 | F32: ='Data Sheet'!D60/'Data Sheet'!D$61 -> 0.33594337 | G32: ='Data Sheet'!E60/'Data Sheet'!E$61 -> 0.30296933 | H32: ='Data Sheet'!F60/'Data Sheet'!F$61 -> 0.31716149 | I32: ='Data Sheet'!G60/'Data Sheet'!G$61 -> 0.32929037 | J32: ='Data Sheet'!H60/'Data Sheet'!H$61 -> 0.30468131 | K32: ='Data Sheet'!I60/'Data Sheet'!I$61 -> 0.29089853 | ... M32: ='Data Sheet'!K60/'Data Sheet'!K$61 -> 0.26704994
B34: Total Assets | D34: ='Data Sheet'!B74/'Data Sheet'!B$74 -> 1 | E34: ='Data Sheet'!C74/'Data Sheet'!C$74 -> 1 | F34: ='Data Sheet'!D74/'Data Sheet'!D$74 -> 1 | G34: ='Data Sheet'!E74/'Data Sheet'!E$74 -> 1 | H34: ='Data Sheet'!F74/'Data Sheet'!F$74 -> 1 | I34: ='Data Sheet'!G74/'Data Sheet'!G$74 -> 1 | J34: ='Data Sheet'!H74/'Data Sheet'!H$74 -> 1 | K34: ='Data Sheet'!I74/'Data Sheet'!I$74 -> 1 | ... M34: ='Data Sheet'!K74/'Data Sheet'!K$74 -> 1
B35: ='Data Sheet'!A62 -> Net Block | D35: ='Data Sheet'!B62/'Data Sheet'!B$74 -> 0.26631918 | E35: ='Data Sheet'!C62/'Data Sheet'!C$74 -> 0.27116979 | F35: ='Data Sheet'!D62/'Data Sheet'!D$74 -> 0.39981685 | G35: ='Data Sheet'!E62/'Data Sheet'!E$74 -> 0.38866784 | H35: ='Data Sheet'!F62/'Data Sheet'!F$74 -> 0.28781244 | I35: ='Data Sheet'!G62/'Data Sheet'!G$74 -> 0.24039362 | J35: ='Data Sheet'!H62/'Data Sheet'!H$74 -> 0.22384057 | K35: ='Data Sheet'!I62/'Data Sheet'!I$74 -> 0.23901124 | ... M35: ='Data Sheet'!K62/'Data Sheet'!K$74 -> 0.27927663
B36: ='Data Sheet'!A63 -> Capital Work in Progress | D36: ='Data Sheet'!B63/'Data Sheet'!B$74 -> 0.020760665 | E36: ='Data Sheet'!C63/'Data Sheet'!C$74 -> 0.10208973 | F36: ='Data Sheet'!D63/'Data Sheet'!D$74 -> 0.01290369 | G36: ='Data Sheet'!E63/'Data Sheet'!E$74 -> 0.0086900645 | H36: ='Data Sheet'!F63/'Data Sheet'!F$74 -> 0.0089892873 | I36: ='Data Sheet'!G63/'Data Sheet'!G$74 -> 0.018574005 | J36: ='Data Sheet'!H63/'Data Sheet'!H$74 -> 0.039550679 | K36: ='Data Sheet'!I63/'Data Sheet'!I$74 -> 0.090244164 | ... M36: ='Data Sheet'!K63/'Data Sheet'!K$74 -> 0.053555531
B37: ='Data Sheet'!A64 -> Investments | D37: ='Data Sheet'!B64/'Data Sheet'!B$74 -> 0.21378068 | E37: ='Data Sheet'!C64/'Data Sheet'!C$74 -> 0.15553479 | F37: ='Data Sheet'!D64/'Data Sheet'!D$74 -> 0.15807775 | G37: ='Data Sheet'!E64/'Data Sheet'!E$74 -> 0.12509938 | H37: ='Data Sheet'!F64/'Data Sheet'!F$74 -> 0.23270552 | I37: ='Data Sheet'!G64/'Data Sheet'!G$74 -> 0.14145262 | J37: ='Data Sheet'!H64/'Data Sheet'!H$74 -> 0.165315 | K37: ='Data Sheet'!I64/'Data Sheet'!I$74 -> 0.15343819 | ... M37: ='Data Sheet'!K64/'Data Sheet'!K$74 -> 0.20457693
B38: ='Data Sheet'!A65 -> Other Assets | D38: ='Data Sheet'!B75/'Data Sheet'!B$74 -> 0.10617895 | E38: ='Data Sheet'!C75/'Data Sheet'!C$74 -> 0.1229224 | F38: ='Data Sheet'!D75/'Data Sheet'!D$74 -> 0.09058862 | G38: ='Data Sheet'!E75/'Data Sheet'!E$74 -> 0.10774032 | H38: ='Data Sheet'!F75/'Data Sheet'!F$74 -> 0.12603671 | I38: ='Data Sheet'!G75/'Data Sheet'!G$74 -> 0.12529864 | J38: ='Data Sheet'!H75/'Data Sheet'!H$74 -> 0.11777536 | K38: ='Data Sheet'!I75/'Data Sheet'!I$74 -> 0.11944141 | ... M38: ='Data Sheet'!K75/'Data Sheet'!K$74 -> 0.13583603
B39: ='Data Sheet'!A67 -> Receivables | D39: ='Data Sheet'!B67/'Data Sheet'!B$74 -> 0.11661248 | E39: ='Data Sheet'!C67/'Data Sheet'!C$74 -> 0.12574073 | F39: ='Data Sheet'!D67/'Data Sheet'!D$74 -> 0.11738253 | G39: ='Data Sheet'!E67/'Data Sheet'!E$74 -> 0.111242 | H39: ='Data Sheet'!F67/'Data Sheet'!F$74 -> 0.12783722 | I39: ='Data Sheet'!G67/'Data Sheet'!G$74 -> 0.16862826 | J39: ='Data Sheet'!H67/'Data Sheet'!H$74 -> 0.17987046 | K39: ='Data Sheet'!I67/'Data Sheet'!I$74 -> 0.16350917 | ... M39: ='Data Sheet'!K67/'Data Sheet'!K$74 -> 0.12925729
B40: ='Data Sheet'!A68 -> Inventory | D40: ='Data Sheet'!B68/'Data Sheet'!B$74 -> 0.21176137 | E40: ='Data Sheet'!C68/'Data Sheet'!C$74 -> 0.19314229 | F40: ='Data Sheet'!D68/'Data Sheet'!D$74 -> 0.19385138 | G40: ='Data Sheet'!E68/'Data Sheet'!E$74 -> 0.21005182 | H40: ='Data Sheet'!F68/'Data Sheet'!F$74 -> 0.18661442 | I40: ='Data Sheet'!G68/'Data Sheet'!G$74 -> 0.26800526 | J40: ='Data Sheet'!H68/'Data Sheet'!H$74 -> 0.24091549 | K40: ='Data Sheet'!I68/'Data Sheet'!I$74 -> 0.19810226 | ... M40: ='Data Sheet'!K68/'Data Sheet'!K$74 -> 0.16639334
B41: ='Data Sheet'!A69 -> Cash & Bank | D41: ='Data Sheet'!B69/'Data Sheet'!B$74 -> 0.064586677 | E41: ='Data Sheet'!C69/'Data Sheet'!C$74 -> 0.029400268 | F41: ='Data Sheet'!D69/'Data Sheet'!D$74 -> 0.027379185 | G41: ='Data Sheet'!E69/'Data Sheet'!E$74 -> 0.048508579 | H41: ='Data Sheet'!F69/'Data Sheet'!F$74 -> 0.030004412 | I41: ='Data Sheet'!G69/'Data Sheet'!G$74 -> 0.037647609 | J41: ='Data Sheet'!H69/'Data Sheet'!H$74 -> 0.032732426 | K41: ='Data Sheet'!I69/'Data Sheet'!I$74 -> 0.036253581 | ... M41: ='Data Sheet'!K69/'Data Sheet'!K$74 -> 0.031104255

Sheet DCF
B2: Calculation of PV of FCFF | E2: ='Intrinsic Growth'!K2 -> 46082 | F2: =E2+366 -> 46448 | G2: =F2+365 -> 46813 | H2: =G2+365 -> 47178 | I2: =H2+365 -> 47543 | J2: =I2+365 -> 47908
B4: EBIT | E4: ='Intrinsic Growth'!K34 -> 8280.61 | F4: =E4*(1+$E$14) -> 9232.8392 | G4: =F4*(1+$E$14) -> 10294.57 | H4: =G4*(1+$E$14) -> 11478.395 | I4: =H4*(1+$E$14) -> 12798.353 | J4: =I4*(1+$E$14) -> 14270.1
B5: Tax Rate | E5: 0.25 | F5: =E5 -> 0.25 | G5: =F5 -> 0.25 | H5: =G5 -> 0.25 | I5: =H5 -> 0.25 | J5: =I5 -> 0.25
B6: EBIT(1-T) | E6: =E4*(1-E5) -> 6210.4575 | F6: =F4*(1-F5) -> 6924.6294 | G6: =G4*(1-G5) -> 7720.9275 | H6: =H4*(1-H5) -> 8608.7959 | I6: =I4*(1-I5) -> 9598.7649 | J6: =J4*(1-J5) -> 10702.575
B7: Less:Reinvestment Rate | E7: ='Intrinsic Growth'!K52 -> 0.33437799 | F7: =E7+(($J$7-E7)/4) -> 0.35885795 | G7: =F7+(($J$7-F7)/4) -> 0.37721793 | H7: =G7+(($J$7-G7)/4) -> 0.39098791 | I7: =H7+(($J$7-H7)/4) -> 0.4013154 | J7: =D22/D21 -> 0.43229785
B8: Free Cash Flow to Firm(FCFF) | E8: =E6*(1-E7) -> 4133.8172 | F8: =F6*(1-F7) -> 4439.6711 | G8: =G6*(1-G7) -> 4808.4552 | H8: =H6*(1-H7) -> 5242.8608 | I8: =I6*(1-I7) -> 5746.6327 | J8: =J6*(1-J7) -> 6075.875
B9: Mid Year Convention | F9: 0.5 | G9: =1+F9 -> 1.5 | H9: =1+G9 -> 2.5 | I9: =1+H9 -> 3.5 | J9: =1+I9 -> 4.5
B10: Discounting Factor | F10: =1/(1+$E$16)^F9 -> 0.94303907 | G10: =1/(1+$E$16)^G9 -> 0.83866605 | H10: =1/(1+$E$16)^H9 -> 0.74584475 | I10: =1/(1+$E$16)^I9 -> 0.66329667 | J10: =1/(1+$E$16)^J9 -> 0.58988478
B12: PV of FCFF | F12: =F8*F10 -> 4186.7833 | G12: =G8*G10 -> 4032.6882 | H12: =H8*H10 -> 3910.3602 | I12: =I8*I10 -> 3811.7223 | J12: =J8*J10 -> 3584.0662
B14: Expected growth | E14: ='Intrinsic Growth'!K62 -> 0.11499505
B15: Terminal Growth | E15: 0.0538
B16: WACC | E16: =WACC!J45 -> 0.12445123
B18: Calculation of Terminal Value | F18: Sensitivity Analysis
F19: =D31 -> 72983.838 | G19: 0.1 | H19: 0.1245 | I19: 0.135 | J19: 0.145
B20: FCFF(n+1) | D20: =J8*(1+E15) -> 6402.7571 | F20: 0.03 | G20: 88547.937 | H20: 76568.23 | I20: 72765.149 | J20: 69655.239
B21: WACC | D21: =E16 -> 0.12445123 | F21: 0.04 | G21: 86663.624 | H21: 75054.725 | I21: 71369.361 | J21: 68355.713
B22: Terminal growth rate | D22: =E15 -> 0.0538 | F22: 0.0538 | G22: 84063.271 | H22: 72966.089 | I22: 69443.174 | J22: 66562.366
F23: 0.06 | G23: 82894.997 | H23: 72027.716 | I23: 68577.785 | J23: 65756.66
B24: Terminal Value | D24: =D20/(D21-D22) -> 90624.848 | F24: 0.07 | G24: 81010.684 | H24: 70514.211 | I24: 67181.998 | J24: 64457.133
B27: Calculation of Enterprise Value
F28: =D38 -> 746.54286 | G28: 0.1 | H28: 0.1245 | I28: 0.135 | J28: 0.145
B29: PV of FCFF | D29: =SUM(F12:J12) -> 19525.62 | F29: 0.03 | G29: 908.4511 | H29: 783.83012 | I29: 744.2679 | J29: 711.91653
B30: PV of Terminal value | D30: =D24*J10 -> 53458.218 | F30: 0.04 | G30: 888.8492 | H30: 768.08562 | I30: 729.74798 | J30: 698.39798
B31: Value of Operating Assets | D31: =SUM(D29:D30) -> 72983.838 | F31: 0.0538 | G31: 861.79859 | H31: 746.35822 | I31: 709.71048 | J31: 679.74238
F32: 0.06 | G32: 849.64541 | H32: 736.59663 | I32: 700.70813 | J32: 671.36088
B33: Add:Cash | D33: ='Data Sheet'!K69 -> 1073.68 | F33: 0.07 | G33: 830.04351 | H33: 720.85214 | I33: 686.18821 | J33: 657.84233
B34: Less:Debt | D34: =SUM('Raw FS'!N7:N8) -> 2293
B35: Value of Equity | D35: =D31+D33-D34 -> 71764.518
B36: No. of Shares | D36: ='Data Sheet'!B6 -> 96.129133
B38: Equity Value per Share | D38: =D35/D36 -> 746.54286
B40: Share price | D40: 2735
B41: Discount/Premium | D41: =D40/D38 -> 3.6635539

Sheet Analysis-Dcf
B2: Objective
B3: Estimate Asian Paints' intrinsic value per share using a Discounted Cash Flow approach based on forecast Free Cash Flow to Firm (FCFF).
B5: Assumptions
B6: Input | C6: Value | D6: Basis
B7: Expected growth rate | C7: 0.115 | D7: Median of intrinsic growth estimates
B8: Terminal growth rate | C8: 0.0538 | D8: Long-term growth assumption used for terminal value
B9: WACC | C9: 0.1242 | D9: Derived from WACC / peer-comparison analysis
B10: Tax rate | C10: 0.25 | D10: Tax assumption used in the DCF
B11: Valuation method | C11: FCFF-based DCF | D11: Enterprise valuation using FCFF
B12: Discounting convention | C12: Mid-year convention | D12: FCFF discounted using mid-year timing
B13: Forecast basis | C13: EBIT, reinvestment rate and resulting FCFF | D13: Operating forecast inputs
B14: Terminal value method | C14: Gordon Growth approach | D14: FCFFn+1​/(WACC−g)
B16: Observations
B17: 1. FCFF generation
B18: Forecast FCFF increases from ₹2,076.6 Cr to ₹5,259.2 Cr over the forecast period, reflecting growth in operating earnings and the resulting increase in cash available to all capital providers.
B19: 2. Reinvestment
B20: The reinvestment rate rises from 33.44% to 49.14%, indicating that an increasing proportion of after-tax operating earnings is assumed to be reinvested to support future growth.
B21: 3.Terminal value
B22: Terminal value contributes a significant portion of the DCF valuation: present value of terminal value is ₹46,514.4 Cr compared with ₹13,703.6 Cr of forecast-period FCFF.
B23: 4. Base valuation
B24: The base-case DCF produces an equity value of ₹58,998.7 Cr and an implied value of approximately ₹613.7 per share.
B25: 5. Market comparison
B26: The current share price used in the model is ₹2,735, substantially above the DCF-implied value of ₹613.7 per share, indicating a significant gap between the market price and the model's intrinsic-value estimate.
B27: 6. Sensitivity
... B50: A DCF is assumption-driven and may differ materially from market price because market participants can price in different growth, profitability and competitive expectations.

Sheet Beta-Comps
C2: Name | D2: CMP Rs. | E2: Mar Cap Rs.Cr. | F2: Debt Rs.Cr. | G2: Debt / Eq
B3: 1 | C3: Asian Paints | D3: 2735 | E3: 262340.6 | F3: 3928.93 | G3: 0.18
B4: 2 | C4: Berger Paints | D4: 530.55 | E4: 61862.28 | F4: 635.13 | G4: 0.09
B5: 3 | C5: Kansai Nerolac | D5: 212.35 | E5: 17173.05 | F5: 302.73 | G5: 0.05
B6: 4 | C6: JSW Dulux | D6: 3011.7 | E6: 13715.38 | F6: 79.1 | G6: 0.03
B7: 5 | C7: Indigo Paints | D7: 1120.5 | E7: 5348.44 | F7: 18.37 | G7: 0.02

Sheet Comps Value
B2: Amount in crores
B3: Comparable Company Valuation
D5: Market Data | K5: Financials | O5: Valuation
B6: Company | C6: Ticker | D6: Share Price | E6: Shares Outstanding | F6: Equity Value | G6: Net Debt | H6: Enterprise Value | K6: Revenue | L6: EBITDA | M6: Net Income | O6: EV/Revenue | P6: EV/EBITDA | Q6: P/E
B8: =Data_comps!C3 -> Asian Paints | C8: Asian Paints Ltd | D8: =Data_comps!D3 -> 2735 | E8: =Data_comps!E3 -> 95.92 | F8: =D8*E8 -> 262341.2 | G8: =Data_comps!I3 -> 2855.25 | H8: =F8+G8 -> 265196.45 | K8: =Data_comps!K3 -> 37186.93 | L8: =Data_comps!L3 -> 8181.1246 | M8: =Data_comps!M3 -> 4837.09 | O8: =$H8/K8 -> 7.1314424 | P8: =$H8/L8 -> 32.415647 | Q8: =F8/M8 -> 54.235336
B9: =Data_comps!C4 -> Berger Paints | C9: Berger Paints India Ltd | D9: =Data_comps!D4 -> 530.55 | E9: =Data_comps!E4 -> 116.6 | F9: =D9*E9 -> 61862.13 | G9: =Data_comps!I4 -> 329.82 | H9: =F9+G9 -> 62191.95 | K9: =Data_comps!K4 -> 12263.24 | L9: =Data_comps!L4 -> 2084.7508 | M9: =Data_comps!M4 -> 1217.99 | O9: =$H9/K9 -> 5.0714126 | P9: =$H9/L9 -> 29.831839 | Q9: =F9/M9 -> 50.790343
B10: =Data_comps!C5 -> Kansai Nerolac | C10: Kansai Nerolac Paints Ltd | D10: =Data_comps!D5 -> 212.35 | E10: =Data_comps!E5 -> 80.87 | F10: =D10*E10 -> 17172.745 | G10: =Data_comps!I5 -> 76.95 | H10: =F10+G10 -> 17249.695 | K10: =Data_comps!K5 -> 8263.47 | L10: =Data_comps!L5 -> 1156.8858 | M10: =Data_comps!M5 -> 588.66 | O10: =$H10/K10 -> 2.0874638 | P10: =$H10/L10 -> 14.910456 | Q10: =F10/M10 -> 29.172603
B11: =Data_comps!C6 -> JSW Dulux | C11: JSW Dulux Ltd | D11: =Data_comps!D6 -> 3011.7 | E11: =Data_comps!E6 -> 4.55 | F11: =D11*E11 -> 13703.235 | G11: =Data_comps!I6 -> -244.6 | H11: =F11+G11 -> 13458.635 | K11: =Data_comps!K6 -> 3599.2 | L11: =Data_comps!L6 -> 503.888 | M11: =Data_comps!M6 -> 1973.8 | O11: =$H11/K11 -> 3.7393407 | P11: =$H11/L11 -> 26.709576 | Q11: =F11/M11 -> 6.9425651
B12: =Data_comps!C7 -> Indigo Paints | C12: Indigo Paints Ltd | D12: =Data_comps!D7 -> 1120.5 | E12: =Data_comps!E7 -> 4.77 | F12: =D12*E12 -> 5344.785 | G12: =Data_comps!I7 -> -10.18 | H12: =F12+G12 -> 5334.605 | K12: =Data_comps!K7 -> 1330.12 | L12: =Data_comps!L7 -> 252.7228 | M12: =Data_comps!M7 -> 145.39 | O12: =$H12/K12 -> 4.0106193 | P12: =$H12/L12 -> 21.108523 | Q12: =F12/M12 -> 36.76171
B13: =Data_comps!C8 -> Sirca Paints | C13: Sirca Paints India Ltd | D13: =Data_comps!D8 -> 449.9 | E13: =Data_comps!E8 -> 5.68 | F13: =D13*E13 -> 2555.432 | G13: =Data_comps!I8 -> -25.66 | H13: =F13+G13 -> 2529.772 | K13: =Data_comps!K8 -> 508.26 | L13: =Data_comps!L8 -> 106.7346 | M13: =Data_comps!M8 -> 67.05 | O13: =$H13/K13 -> 4.9773187 | P13: =$H13/L13 -> 23.701518 | Q13: =F13/M13 -> 38.112334
B14: =Data_comps!C9 -> Shalimar Paints | C14: Shalimar Paints Ltd | D14: =Data_comps!D9 -> 84.47 | E14: =Data_comps!E9 -> 8.37 | F14: =D14*E14 -> 707.0139 | G14: =Data_comps!I9 -> 117.67 | H14: =F14+G14 -> 824.6839 | K14: =Data_comps!K9 -> 575.63 | L14: =Data_comps!L9 -> -17.2689 | M14: =Data_comps!M9 -> -64.95 | O14: =$H14/K14 -> 1.4326632 | P14: =$H14/L14 -> -47.755439 | Q14: =F14/M14 -> -10.88551
B15: =Data_comps!C10 -> Kamdhenu Venture | C15: Kamdhenu Ventures Ltd | D15: =Data_comps!D10 -> 4.59 | E15: =Data_comps!E10 -> 32.9 | F15: =D15*E15 -> 151.011 | G15: =Data_comps!I10 -> 14.35 | H15: =F15+G15 -> 165.361 | K15: =Data_comps!K10 -> 245.26 | L15: =Data_comps!L10 -> 9.8104 | M15: =Data_comps!M10 -> 0.2 | O15: =$H15/K15 -> 0.67422735 | P15: =$H15/L15 -> 16.855684 | Q15: =F15/M15 -> 755.055
B16: =Data_comps!C11 -> Siddhika Coatings | C16: Siddhika Coatings Ltd | D16: =Data_comps!D11 -> 209.25 | E16: =Data_comps!E11 -> 0.62 | F16: =D16*E16 -> 129.735 | G16: =Data_comps!I11 -> -8.73 | H16: =F16+G16 -> 121.005 | K16: =Data_comps!K11 -> 54.9 | L16: =Data_comps!L11 -> 13.176 | M16: =Data_comps!M11 -> 9.86 | O16: =$H16/K16 -> 2.2040984 | P16: =$H16/L16 -> 9.1837432 | Q16: =F16/M16 -> 13.157708
B17: =Data_comps!C12 -> Retina Paints | C17: Retina Paints Ltd | D17: =Data_comps!D12 -> 43 | E17: =Data_comps!E12 -> 1.53 | F17: =D17*E17 -> 65.79 | G17: =Data_comps!I12 -> 17.5 | H17: =F17+G17 -> 83.29 | K17: =Data_comps!K12 -> 23.74 | L17: =Data_comps!L12 -> 2.8488 | M17: =Data_comps!M12 -> 0.64 | O17: =$H17/K17 -> 3.5084246 | P17: =$H17/L17 -> 29.236872 | Q17: =F17/M17 -> 102.79688
B20: High | O20: =MAX(O8:O17) -> 7.1314424 | P20: =MAX(P8:P17) -> 32.415647 | Q20: =MAX(Q8:Q17) -> 755.055
B21: 75th Percentile | O21: =QUARTILE(O8:O17,3) -> 4.7356439 | P21: =QUARTILE(P8:P17,3) -> 28.605048 | Q21: =QUARTILE(Q8:Q17,3) -> 53.374088
B22: Average | O22: =AVERAGE(O8:O17) -> 3.4837011 | P22: =AVERAGE(P8:P17) -> 15.619842 | Q22: =AVERAGE(Q8:Q17) -> 107.6139
B23: Median | O23: =MEDIAN(O8:O17) -> 3.6238826 | P23: =MEDIAN(P8:P17) -> 22.40502 | Q23: =MEDIAN(Q8:Q17) -> 37.437022
B24: 25th Percentile | O24: =QUARTILE(O8:O17,1) -> 2.1166224 | P24: =QUARTILE(P8:P17,1) -> 15.396763 | Q24: =QUARTILE(Q8:Q17,1) -> 17.161432
B25: Low | O25: =MIN(O8:O17) -> 0.67422735 | P25: =MIN(P8:P17) -> -47.755439 | Q25: =MIN(Q8:Q17) -> -10.88551
B29: Asian Paints Comparable Valuation | O29: EV/Revenue | P29: EV/EBITDA | Q29: P/E
B31: Implied Enterprise Value | O31: =O$23*K8 -> 134761.07 | P31: =P$23*L8 -> 183298.26 | Q31: =Q33+Q32 -> 183941.49
B32: Net Debt | O32: =$G$8 -> 2855.25 | P32: =$G$8 -> 2855.25 | Q32: =$G$8 -> 2855.25
B33: Implied Market Value | O33: =O31-O32 -> 131905.82 | P33: =P31-P32 -> 180443.01 | Q33: =Q23*M8 -> 181086.24
B34: Shares Outstanding | O34: =$E$8 -> 95.92 | P34: =$E$8 -> 95.92 | Q34: =$E$8 -> 95.92
B36: Implied value per share | O36: =O33/O34 -> 1375.1649 | P36: =P33/P34 -> 1881.1824 | Q36: =Q33/Q34 -> 1887.8883
B38: Source:Screener.in
O39: =IF(O36>$D$8,"Undervalued","Overvalued") -> Overvalued | P39: =IF(P36>$D$8,"Undervalued","Overvalued") -> Overvalued | Q39: =IF(Q36>$D$8,"Undervalued","Overvalued") -> Overvalued

Sheet Analysis-Comps Value
B2: Objective
B3: Estimate Asian Paints' implied value per share using peer-company valuation multiples such as EV/Revenue, EV/EBITDA and P/E.
B5: Observations:
B7: Median peer multiples of 3.6× EV/Revenue, 22.4× EV/EBITDA and 37.4× P/E were applied to Asian Paints' financials to derive implied valuation.
B8: The three approaches produce implied values of approximately ₹1,375–₹1,888 per share, with EV/Revenue giving the lowest value and P/E giving the highest.
B9: All three implied values are below Asian Paints' current market price, indicating that the company trades at a premium to the valuation implied by the selected peer multiples.
B10: The difference across methods reflects the different aspects of the business captured by each multiple: revenue focuses on scale, EBITDA on operating profitability and P/E on earnings available to shareholders.
B12: Limitations:
B13: Peer comparability
B14: The peer set contains companies with materially different scale, profitability and business characteristics, so a single median multiple may not fully capture Asian Paints' relative quality.
B15: Negative/very low earnings
B16: Some peers have negative EBITDA or net income, making EV/EBITDA or P/E economically difficult to interpret and potentially affecting the observed range and summary statistics.
... B26: Valuation varies materially by the selected multiple, demonstrating that the implied value is sensitive to the valuation methodology.

Sheet Football field Analysis
M4: Football field Analysis-Data
O5: OpenLow | P5: Low | Q5: OpenHigh | R5: High
M6: Comps | O6: ='Comps Value'!$O$36 -> 1375.1649 | P6: ='Comps Value'!$O$36 -> 1375.1649 | Q6: ='Comps Value'!$Q$36 -> 1887.8883 | R6: ='Comps Value'!$Q$36 -> 1887.8883
M7: DCF Bear | O7: =DCF!$J$29 -> 711.91653 | P7: =DCF!$J$29 -> 711.91653 | Q7: =DCF!$J$33 -> 657.84233 | R7: =DCF!$J$33 -> 657.84233
M8: DCF Base | O8: =DCF!$H$29 -> 783.83012 | P8: =DCF!$H$29 -> 783.83012 | Q8: =DCF!$H$33 -> 720.85214 | R8: =DCF!$H$33 -> 720.85214
M9: DCF Bull | O9: =DCF!$G$29 -> 908.4511 | P9: =DCF!$G$29 -> 908.4511 | Q9: =DCF!$G$33 -> 830.04351 | R9: =DCF!$G$33 -> 830.04351
M10: 52W H/L | O10: 2115 | P10: 2115 | Q10: 2985.7 | R10: 2985.7

Sheet analysis football field
B2: Observations
B3: 1. Valuation range
B4: The valuation methods produce a wide range, with DCF values ranging from ₹425–₹1,264.8 per share and comparable-company valuation ranging from ₹1,375.2–₹1,887.9 per share.
B5: 2. DCF vs Comps
B6: Comparable-company valuation is materially higher than the DCF range, indicating that the market-based peer multiples imply a higher value than the cash-flow-based intrinsic valuation.
B7: 3. Market price comparison
B8: Both valuation approaches remain below the current market price of ₹2,735 and the 52-week range of ₹2,115–₹2,985.7, indicating that the market price reflects expectations stronger than those captured in the current DCF and peer-based valuation.
B9: 4. Valuation dispersion
B10: The wide spread between the DCF and peer-based valuations highlights significant sensitivity to the valuation methodology and underlying assumptions.
B11: 5. Overall interpretation
B12: The football field suggests that Asian Paints is currently trading at a substantial premium to the values implied by both intrinsic-value and comparable-company approaches.

Sheet Rm
B6: Return on Markets
B8: Year | C8: Annual
B9: 2000 | C9: -0.1465
B10: 2001 | C10: -0.1618
B11: 2002 | C11: 0.0325 | E11: Geometric mean | F11: {=PRODUCT(1+C9:C34)^(1/COUNT(C9:C34))-1} -> 0.11650334
B12: 2003 | C12: 0.719 | E12: Dividend Yield | F12: 0.013
B13: 2004 | C13: 0.1068 | E13: Total market return | F13: =SUM(F11:F12) -> 0.12950334
B14: 2005 | C14: 0.3634
B15: 2006 | C15: 0.3983
B16: 2007 | C16: 0.5477
B17: 2008 | C17: -0.5179
B18: 2009 | C18: 0.7576
B19: 2010 | C19: 0.1795
B20: 2011 | C20: -0.2462
B21: 2012 | C21: 0.277
B22: 2013 | C22: 0.0676
B23: 2014 | C23: 0.3139
B24: 2015 | C24: -0.0406
B25: 2016 | C25: 0.0301
... B34: 2025 | C34: 0.1051
B35: 2026

Sheet VAR
B2: Date | C2: Adj Close | D2: Return | E2: Sorted Returns | G2: Calculation of Value at Risk-Asian Paints(Historical)
B3: 40109 | C3: 143.64825 | D3: =(C3-C4)/C4 -> 1.2447388 | E3: 0.096586558
B4: 39097 | C4: 63.993305 | D4: =(C4-C5)/C5 -> -0.301991 | E4: 0.092896233 | G4: Mean | K4: =AVERAGE(Table6[Sorted Returns]) -> 0.00098491976
B5: 39380 | C5: 91.679771 | D5: =(C5-C6)/C6 -> -0.94443549 | E5: 0.091229707 | G5: Std Deviation | K5: =_xlfn.STDEV.S(Table6[Sorted Returns]) -> 0.016381223
B6: 43910 | C6: 1649.97 | D6: =(C6-C7)/C7 -> -0.37330913 | E6: 0.088527235 | G6: Min | K6: =MIN(Table6[Sorted Returns]) -> -0.14027939
B7: 44330 | C7: 2632.8291 | D7: =(C7-C8)/C8 -> 143.32206 | E7: 0.085400251 | G7: Max | K7: =MAX(Table6[Sorted Returns]) -> 0.096586558
B8: 37757 | C8: 18.242735 | D8: =(C8-C9)/C9 -> -0.59139552 | E8: 0.083062628 | G8: Current MP | K8: 2608.7
B9: 38877 | C9: 44.646439 | D9: =(C9-C10)/C10 -> -0.97368495 | E9: 0.082636462
B10: 43731 | C10: 1696.6125 | D10: =(C10-C11)/C11 -> 17.037937 | E10: 0.07884516 | G10: Percentile | H10: Confidence | I10: VAR% | J10: Stock Price | K10: VAR(INR)
B11: 39475 | C11: 94.058014 | D11: =(C11-C12)/C12 -> -0.78066633 | E11: 0.076603137 | G11: 0.05 | H11: =100%-G11 -> 0.95 | I11: =_xlfn.PERCENTILE.INC(Table6[Sorted Returns],G11) -> -0.023978648 | J11: =$K$8*(1+I11) -> 2546.1469 | K11: =$K$8-J11 -> 62.5531
B12: 41536 | C12: 428.83527 | D12: =(C12-C13)/C13 -> -0.72731143 | E12: 0.075420713 | G12: 0.01 | H12: =100%-G12 -> 0.99 | I12: =_xlfn.PERCENTILE.INC(Table6[Sorted Returns],G12) -> -0.041732231 | J12: =$K$8*(1+I12) -> 2499.8331 | K12: =$K$8-J12 -> 108.86687
B13: 43728 | C13: 1572.6191 | D13: =(C13-C14)/C14 -> 15.886466 | E13: 0.075358776 | G13: 0.005 | H13: =100%-G13 -> 0.995 | I13: =_xlfn.PERCENTILE.INC(Table6[Sorted Returns],G13) -> -0.051610343 | J13: =$K$8*(1+I13) -> 2474.0641 | K13: =$K$8-J13 -> 134.6359
B14: 39954 | C14: 93.128967 | D14: =(C14-C15)/C15 -> 4.310004 | E14: 0.075121075 | G14: 0.1 | H14: =100%-G14 -> 0.9 | I14: =_xlfn.PERCENTILE.INC(Table6[Sorted Returns],G14) -> -0.016596699 | J14: =$K$8*(1+I14) -> 2565.4042 | K14: =$K$8-J14 -> 43.295809
B15: 37743 | C15: 17.538399 | D15: =(C15-C16)/C16 -> -0.79831767 | E15: 0.074728903
B16: 39742 | C16: 86.96051 | D16: =(C16-C17)/C17 -> -0.87963231 | E16: 0.072365886
B17: 41974 | C17: 722.45728 | D17: =(C17-C18)/C18 -> 31.562062 | E17: 0.070296429
B18: 38125 | C18: 22.187086 | D18: =(C18-C19)/C19 -> -0.98556634 | E18: 0.069988914
B19: 43928 | C19: 1537.1763 | D19: =(C19-C20)/C20 -> 58.144791 | E19: 0.067657293
B20: 38009 | C20: 25.990053 | D20: =(C20-C21)/C21 -> -0.6495329 | E20: 0.066739394
B21: 39918 | C21: 74.158325 | D21: =(C21-C22)/C22 -> -0.2468807 | E21: 0.066402774
B22: 39477 | C22: 98.468231 | D22: =(C22-C23)/C23 -> 0.7325454 | E22: 0.065174009
B23: 38754 | C23: 56.834431 | D23: =(C23-C24)/C24 -> -0.92356617 | E23: 0.06330642
B24: 42012 | C24: 743.5769 | D24: =(C24-C25)/C25 -> 6.3496338 | E24: 0.063042532
B25: 39454 | C25: 101.17197 | D25: =(C25-C26)/C26 -> -0.90239312 | E25: 0.062669969
B26: 42579 | C26: 1036.5249 | D26: =(C26-C27)/C27 -> 3.6232895 | E26: 0.062346723
... B6001: 43913 | C6001: 1418.5132 | D6001: =(C6001-C6002)/C6002 -> #DIV/0! | E6001: -0.14027939

Sheet Monte Carlo Simulation
B2: Date | C2: Adj Close | D2: Return | E2: Sorted Returns | G2: Replication | H2: Simulated Returns | J2: Calculation of Value at Risk-Asian Paints(Simulation)
B3: 40109 | C3: 143.64825 | D3: =(C3-C4)/C4 -> 1.2447388 | E3: 0.096586558 | G3: 1 | H3: =_xlfn.NORM.INV(RAND(),N$5,N$6) -> 0.028084457
B4: 39097 | C4: 63.993305 | D4: =(C4-C5)/C5 -> -0.301991 | E4: 0.092896233 | G4: 2 | H4: =_xlfn.NORM.INV(RAND(),N$5,N$6) -> -0.013102763 | J4: Historical Approach
B5: 39380 | C5: 91.679771 | D5: =(C5-C6)/C6 -> -0.94443549 | E5: 0.091229707 | G5: 3 | H5: =_xlfn.NORM.INV(RAND(),N$5,N$6) -> 0.0087697881 | J5: Mean | N5: =AVERAGE(Table68[Sorted Returns]) -> 0.00098491976
B6: 43910 | C6: 1649.97 | D6: =(C6-C7)/C7 -> -0.37330913 | E6: 0.088527235 | G6: 4 | H6: =_xlfn.NORM.INV(RAND(),N$5,N$6) -> 0.013876631 | J6: Std Deviation | N6: =_xlfn.STDEV.S(Table68[Sorted Returns]) -> 0.016381223
B7: 44330 | C7: 2632.8291 | D7: =(C7-C8)/C8 -> 143.32206 | E7: 0.085400251 | G7: 5 | H7: =_xlfn.NORM.INV(RAND(),N$5,N$6) -> 0.018319412 | J7: Min | N7: =MIN(Table68[Sorted Returns]) -> -0.14027939
B8: 37757 | C8: 18.242735 | D8: =(C8-C9)/C9 -> -0.59139552 | E8: 0.083062628 | G8: 6 | H8: =_xlfn.NORM.INV(RAND(),N$5,N$6) -> 0.0069292857 | J8: Max | N8: =MAX(Table68[Sorted Returns]) -> 0.096586558
B9: 38877 | C9: 44.646439 | D9: =(C9-C10)/C10 -> -0.97368495 | E9: 0.082636462 | G9: 7 | H9: =_xlfn.NORM.INV(RAND(),N$5,N$6) -> -0.0094180293 | J9: Current MP | N9: 2608.7
B10: 43731 | C10: 1696.6125 | D10: =(C10-C11)/C11 -> 17.037937 | E10: 0.07884516 | G10: 8 | H10: =_xlfn.NORM.INV(RAND(),N$5,N$6) -> 0.0067208255
B11: 39475 | C11: 94.058014 | D11: =(C11-C12)/C12 -> -0.78066633 | E11: 0.076603137 | G11: 9 | H11: =_xlfn.NORM.INV(RAND(),N$5,N$6) -> -0.00035846431 | J11: Monte Carlo Simulation
B12: 41536 | C12: 428.83527 | D12: =(C12-C13)/C13 -> -0.72731143 | E12: 0.075420713 | G12: 10 | H12: =_xlfn.NORM.INV(RAND(),N$5,N$6) -> -0.024319667 | J12: Mean | N12: =AVERAGE(H3:H10002) -> 0.00098022418
B13: 43728 | C13: 1572.6191 | D13: =(C13-C14)/C14 -> 15.886466 | E13: 0.075358776 | G13: 11 | H13: =_xlfn.NORM.INV(RAND(),N$5,N$6) -> 0.035866511 | J13: Std Deviation | N13: =_xlfn.STDEV.S(H3:H10002) -> 0.016375571
B14: 39954 | C14: 93.128967 | D14: =(C14-C15)/C15 -> 4.310004 | E14: 0.075121075 | G14: 12 | H14: =_xlfn.NORM.INV(RAND(),N$5,N$6) -> 0.02053443 | J14: Min | N14: =MIN(H3:H10002) -> -0.062741201
B15: 37743 | C15: 17.538399 | D15: =(C15-C16)/C16 -> -0.79831767 | E15: 0.074728903 | G15: 13 | H15: =_xlfn.NORM.INV(RAND(),N$5,N$6) -> -0.0033112295 | J15: Max | N15: =MAX(H3:H10002) -> 0.067100125
B16: 39742 | C16: 86.96051 | D16: =(C16-C17)/C17 -> -0.87963231 | E16: 0.072365886 | G16: 14 | H16: =_xlfn.NORM.INV(RAND(),N$5,N$6) -> 0.018213715 | J16: Current MP | N16: 2608.7
B17: 41974 | C17: 722.45728 | D17: =(C17-C18)/C18 -> 31.562062 | E17: 0.070296429 | G17: 15 | H17: =_xlfn.NORM.INV(RAND(),N$5,N$6) -> -0.016800883
B18: 38125 | C18: 22.187086 | D18: =(C18-C19)/C19 -> -0.98556634 | E18: 0.069988914 | G18: 16 | H18: =_xlfn.NORM.INV(RAND(),N$5,N$6) -> -0.014656655
B19: 43928 | C19: 1537.1763 | D19: =(C19-C20)/C20 -> 58.144791 | E19: 0.067657293 | G19: 17 | H19: =_xlfn.NORM.INV(RAND(),N$5,N$6) -> 0.0086118364 | J19: Percentile | K19: Confidence | L19: VAR% | M19: Stock Price | N19: VAR(INR)
B20: 38009 | C20: 25.990053 | D20: =(C20-C21)/C21 -> -0.6495329 | E20: 0.066739394 | G20: 18 | H20: =_xlfn.NORM.INV(RAND(),N$5,N$6) -> 0.027433365 | J20: 0.05 | K20: =100%-J20 -> 0.95 | L20: =_xlfn.PERCENTILE.INC(H3:$H$10002,J20) -> -0.025782279 | M20: =$N$9*(1+L20) -> 2541.4418 | N20: =$N$9-M20 -> 67.258232
B21: 39918 | C21: 74.158325 | D21: =(C21-C22)/C22 -> -0.2468807 | E21: 0.066402774 | G21: 19 | H21: =_xlfn.NORM.INV(RAND(),N$5,N$6) -> 0.024527369 | J21: 0.01 | K21: =100%-J21 -> 0.99 | L21: =_xlfn.PERCENTILE.INC(H4:$H$10002,J21) -> -0.037768385 | M21: =$N$9*(1+L21) -> 2510.1736 | N21: =$N$9-M21 -> 98.526385
B22: 39477 | C22: 98.468231 | D22: =(C22-C23)/C23 -> 0.7325454 | E22: 0.065174009 | G22: 20 | H22: =_xlfn.NORM.INV(RAND(),N$5,N$6) -> 0.01026692 | J22: 0.005 | K22: =100%-J22 -> 0.995 | L22: =_xlfn.PERCENTILE.INC(H5:$H$10002,J22) -> -0.040923936 | M22: =$N$9*(1+L22) -> 2501.9417 | N22: =$N$9-M22 -> 106.75827
B23: 38754 | C23: 56.834431 | D23: =(C23-C24)/C24 -> -0.92356617 | E23: 0.06330642 | G23: 21 | H23: =_xlfn.NORM.INV(RAND(),N$5,N$6) -> 0.0010023516 | J23: 0.1 | K23: =100%-J23 -> 0.9 | L23: =_xlfn.PERCENTILE.INC(H6:$H$10002,J23) -> -0.020044657 | M23: =$N$9*(1+L23) -> 2556.4095 | N23: =$N$9-M23 -> 52.290497
B24: 42012 | C24: 743.5769 | D24: =(C24-C25)/C25 -> 6.3496338 | E24: 0.063042532 | G24: 22 | H24: =_xlfn.NORM.INV(RAND(),N$5,N$6) -> -0.0033443025
B25: 39454 | C25: 101.17197 | D25: =(C25-C26)/C26 -> -0.90239312 | E25: 0.062669969 | G25: 23 | H25: =_xlfn.NORM.INV(RAND(),N$5,N$6) -> -0.0043000273
B26: 42579 | C26: 1036.5249 | D26: =(C26-C27)/C27 -> 3.6232895 | E26: 0.062346723 | G26: 24 | H26: =_xlfn.NORM.INV(RAND(),N$5,N$6) -> 0.018726104
B27: 40387 | C27: 224.19641 | D27: =(C27-C28)/C28 -> 1.2417881 | E27: 0.060614686 | G27: 25 | H27: =_xlfn.NORM.INV(RAND(),N$5,N$6) -> -0.00034853951
B28: 39505 | C28: 100.00785 | D28: =(C28-C29)/C29 -> -0.41312194 | E28: 0.059684293 | G28: 26 | H28: =_xlfn.NORM.INV(RAND(),N$5,N$6) -> 0.019850509
B29: 40240 | C29: 170.40652 | D29: =(C29-C30)/C30 -> -0.94343508 | E29: 0.059493417 | G29: 27 | H29: =_xlfn.NORM.INV(RAND(),N$5,N$6) -> 0.01799456
B30: 44397 | C30: 3012.5833 | D30: =(C30-C31)/C31 -> 5.525192 | E30: 0.059390671 | G30: 28 | H30: =_xlfn.NORM.INV(RAND(),N$5,N$6) -> -0.019902072
B31: 41568 | C31: 461.685 | D31: =(C31-C32)/C32 -> 1.0108473 | E31: 0.059355142 | G31: 29 | H31: =_xlfn.NORM.INV(RAND(),N$5,N$6) -> -0.0087199537
B32: 40479 | C32: 229.59724 | D32: =(C32-C33)/C33 -> 1.8540848 | E32: 0.058279452 | G32: 30 | H32: =_xlfn.NORM.INV(RAND(),N$5,N$6) -> 0.022010068
B33: 39946 | C33: 80.445137 | D33: =(C33-C34)/C34 -> -0.93272012 | E33: 0.058118465 | G33: 31 | H33: =_xlfn.NORM.INV(RAND(),N$5,N$6) -> 0.0063889868
B34: 43231 | C34: 1195.679 | D34: =(C34-C35)/C35 -> -0.4258163 | E34: 0.056459013 | G34: 32 | H34: =_xlfn.NORM.INV(RAND(),N$5,N$6) -> 0.0041870143
B35: 44131 | C35: 2082.3979 | D35: =(C35-C36)/C36 -> 19.025303 | E35: 0.056406417 | G35: 33 | H35: =_xlfn.NORM.INV(RAND(),N$5,N$6) -> -0.022883879
... B6001: 43913 | C6001: 1418.5132 | D6001: =(C6001-C6002)/C6002 -> #DIV/0! | E6001: -0.14027939 | G6001: 5999 | H6001: =_xlfn.NORM.INV(RAND(),N$5,N$6) -> 0.030304453
G6002: 6000 | H6002: =_xlfn.NORM.INV(RAND(),N$5,N$6) -> -0.0033339895
G6003: 6001 | H6003: =_xlfn.NORM.INV(RAND(),N$5,N$6) -> -0.0053155068
G6004: 6002 | H6004: =_xlfn.NORM.INV(RAND(),N$5,N$6) -> -0.0049605256
G6005: 6003 | H6005: =_xlfn.NORM.INV(RAND(),N$5,N$6) -> 0.0091338364
G6006: 6004 | H6006: =_xlfn.NORM.INV(RAND(),N$5,N$6) -> 0.027012868
G6007: 6005 | H6007: =_xlfn.NORM.INV(RAND(),N$5,N$6) -> 0.0041750734
G6008: 6006 | H6008: =_xlfn.NORM.INV(RAND(),N$5,N$6) -> -0.025593019
G6009: 6007 | H6009: =_xlfn.NORM.INV(RAND(),N$5,N$6) -> 0.0077336272
G6010: 6008 | H6010: =_xlfn.NORM.INV(RAND(),N$5,N$6) -> 0.0065559292
G6011: 6009 | H6011: =_xlfn.NORM.INV(RAND(),N$5,N$6) -> 0.027512968
G6012: 6010 | H6012: =_xlfn.NORM.INV(RAND(),N$5,N$6) -> 0.0097009781
G6013: 6011 | H6013: =_xlfn.NORM.INV(RAND(),N$5,N$6) -> -0.0028257901
... G10002: 10000 | H10002: =_xlfn.NORM.INV(RAND(),N$5,N$6) -> 0.020828569

Sheet Observations
B2: Ratio Analysis
B3: Area | C3: Overall Observation
B4: Revenue | C4: Revenue growth recovered to 4.95% in FY26 after a 4.48% decline in FY25, indicating a recovery in business momentum.
B5: Profit Growth | C5: EBITDA grew 10.42% vs sales growth of 4.95%, showing that profitability recovered faster than revenue.
B6: Margins | C6: Gross margin rose 40.61% → 41.88% and EBITDA margin 25.40% → 26.72%, indicating stronger earnings conversion.
B7: Operating Profit | C7: EBIT margin improved 22.37% → 23.27%, despite higher depreciation from continued asset investment
B8: Finance Cost | C8: EBT margin improved 21.70% → 22.72%, supported by the decline in finance cost from ₹227 Cr to ₹195 Cr.
B9: Net Profit | C9: Net profit margin increased 17.59% → 18.20%, showing that the improvement in operating profitability translated into the bottom line.
B10: Operating Expenses | C10: Sales expenses remained almost unchanged at ~15% of sales, indicating that the higher profitability was not driven by a major reduction in this expense ratio.
B11: Working Capital | C11: The major efficiency improvement came from inventory: inventory days fell 122 → 101, while debtor days stayed at 46 days.
B12: Cash Conversion | C12: CCC fell sharply 75 → 53 days, primarily because inventory was converted into sales faster.
B13: Operating Cash | C13: CFO/Sales increased 13.05% → 19.92%, showing a substantial improvement in conversion of business activity into cash.
B14: Asset Utilisation | C14: Fixed-asset turnover remained almost unchanged at ~3.7×, while capital turnover fell 1.57× → 1.41×.
... B20: Key Concern | C20: ROCE and capital turnover declined, so the key question is whether ongoing capacity and asset investments will generate sufficient incremental returns.
B23: Overall, FY26 appears to be a recovery year for Asian Paints: revenue returned to growth, profitability strengthened faster than sales, inventory and cash-conversion efficiency improved significantly, and operating cash generation strengthened. The main area to monitor is capital productivity, as ROCE and capital turnover declined despite continued investment in the business.
B26: Forecasting
B27: Area | C27: Overall Observation
B28: Forecast Baseline | C28: Regression implies FY27 growth of 14.34% in Sales, 11.13% in EBITDA and 14.12% in EPS based on historical trends.
B29: Forecast Validation | C29: Back-testing gives MAPE of 14.25% for Sales, 11.69% for EBITDA and 12.79% for EPS, indicating meaningful forecast uncertainty.
B30: Forecast Limitation | C30: The model captures historical trends but excludes business drivers such as volume, pricing, competition, raw-material costs and macro conditions.
B31: Investor Use | C31: Forecasts should be treated as statistical benchmarks and validated against management guidance and business fundamentals before investment decisions.
B33: WACC
B34: Peer Comps
B35: Unlevered betas of 5 listed Indian paint companies; median (0.93) used as the industry benchmark rather than a size-weighted average, since Asian Paints alone is ≈73% of total peer equity and would otherwise dominate the figure.
B37: Cost of Debt
B38: Pre-tax cost of debt of 1.22% is adjusted using a 25% tax rate to arrive at an after-tax cost of debt of 0.92%.
B40: Cost of Equity
B41: Calculated via CAPM using the risk-free rate, equity risk premium and relevered target beta (0.93); resulting Cost of Equity is 12.53%.
B43: Regression Beta
B44: Direct 2-year weekly regression of Asian Paints' stock returns against Nifty 50 (raw beta 0.96, adjusted 0.97) — used as a standalone cross-check on the peer-comps beta, not as the WACC input itself.
B46: Capital Structure
B47: Target Debt/Equity set to the peer-median (1.03%) rather than Asian Paints' current ratio (1.50%), applied by re-splitting existing total capitalization rather than modeling new financing.
B49: WACC
... B67: Comps Value
B69: Area | C69: Overall Observation
B70: Comparable Valuation | C70: Peer-multiple valuation gives an implied value of approximately ₹1,375–₹1,888/share across EV/Revenue, EV/EBITDA and P/E.
B71: Relative Valuation | C71: All three implied values are below the market price, indicating that Asian Paints trades at a premium to selected peer multiples.
B72: Key Limitation | C72: Valuation is sensitive to peer comparability and the inclusion of low/negative-profit companies, which can distort multiples and the overall range.
B75: DCF
B76: Area | C76: Overall Observation
B77: DCF Valuation | C77: Base DCF implies ₹614/share versus the modelled market price of ₹2,735, indicating a substantial valuation gap.
B78: DCF Sensitivity | C78: At 12.42% WACC, the DCF value ranges from ₹491–₹758/share as terminal growth varies from 3%–7%, showing high sensitivity to long-term assumptions.
B79: DCF Limitation | C79: Valuation is heavily dependent on forecast FCFF, reinvestment assumptions, WACC and terminal growth, so the result should be treated as assumption-sensitive rather than definitive.
B82: Football Field Analysis
B84: Area | C84: Overall Observation
B85: Football Field | C85: DCF and comparable-company valuation produce materially different ranges, with comps higher than DCF, highlighting sensitivity to valuation methodology.
B86: Valuation Conclusion | C86: Both approaches remain below the ₹2,735 market price / ₹2,115–₹2,985.7 52-week range, indicating that the market embeds stronger expectations than the current model assumptions.

Sheet Data Room>

Sheet Data Sheet
A1: COMPANY NAME | B1: ASIAN PAINTS LTD | E1: =IF(B2<>B3, "A NEW VERSION OF THE WORKSHEET IS AVAILABLE", "")
A2: LATEST VERSION | B2: 2.1 | E2: PLEASE DO NOT MAKE ANY CHANGES TO THIS SHEET
A3: CURRENT VERSION | B3: 2.1
A5: META
A6: Number of shares | B6: =IF(B9>0, B9/B8, 0) -> 96.129133
A7: Face Value | B7: 1
A8: Current Price | B8: 2735
A9: Market Capitalization | B9: 262913.18
A15: PROFIT & LOSS
A16: Report Date | B16: 42825 | C16: 43190 | D16: 43555 | E16: 43921 | F16: 44286 | G16: 44651 | H16: 45016 | I16: 45382 | J16: 45747 | K16: 46112
A17: Sales | B17: 15061.99 | C17: 16824.55 | D17: 19240.13 | E17: 20211.25 | F17: 21712.79 | G17: 29101.28 | H17: 34488.59 | I17: 35494.73 | J17: 33905.62 | K17: 35583.54
A18: Raw Material Cost | B18: 7452.6 | C18: 8128.17 | D18: 9974.4 | E18: 9981.99 | F18: 10425.55 | G18: 17123.25 | H18: 18985.53 | I18: 17410.84 | J18: 17504.51 | K18: 17142.01
A19: Change in Inventory | B19: 528.6 | C19: -142.13 | D19: 293.26 | E19: 239.15 | F19: 92.45 | G19: 1324.97 | H19: 309.73 | I19: -363.8 | J19: 205 | K19: -603.68
A20: Power and Fuel | B20: 106.02 | C20: 110.3 | D20: 119.63 | E20: 97.79 | F20: 86.05 | G20: 117.23 | H20: 138.29 | I20: 133.25 | J20: 148.58 | K20: 167.1
A21: Other Mfr. Exp | B21: 1662.75 | C21: 1691.68 | D21: 1862.35 | E21: 1946.12 | F21: 2068.31 | G21: 2880.45 | H21: 2916.2 | I21: 2767.18 | J21: 2687.4 | K21: 2767.11
A22: Employee Cost | B22: 1039.89 | C22: 1121.89 | D22: 1242.69 | E22: 1371.27 | F22: 1547.61 | G22: 1794.61 | H22: 2036.41 | I22: 2334.92 | J22: 2605.78 | K22: 2809.73
A23: Selling and admin | B23: 4364.04 | C23: 2254.92 | D23: 2366.87 | E23: 2311.51 | F23: 2245.69 | G23: 2941.98 | H23: 3500.84 | I23: 3811.86 | J23: 3874.94 | K23: 4112.07
A24: Other Expenses | B24: -2028.47 | C24: 171.45 | D24: 202.51 | E24: 579.95 | F24: 576.43 | G24: 765.12 | H24: 961.21 | I24: 1087.9 | J24: 1283.2 | K24: 1282.11
A25: Other Income | B25: 337.9 | C25: 336.41 | D25: 273.77 | E25: 350.1 | F25: 331.65 | G25: 295.88 | H25: 431.46 | I25: 820.96 | J25: 350.22 | K25: 727.97
A26: Depreciation | B26: 334.79 | C26: 360.47 | D26: 622.14 | E26: 780.5 | F26: 791.27 | G26: 816.36 | H26: 858.02 | I26: 853 | J26: 1026.34 | K26: 1228.85
A27: Interest | B27: 37.33 | C27: 41.47 | D27: 110.47 | E27: 102.33 | F27: 91.63 | G27: 95.41 | H27: 144.45 | I27: 205.17 | J27: 227.02 | K27: 195.41
... A31: Dividend Amount | B31: 987.98 | C31: 834.5 | D31: 1007.16 | E31: 1151.04 | F31: 1712.17 | G31: 1836.87 | H31: 2460.35 | I31: 3194.14 | J31: 2378.82 | K31: 2637.8
A40: Quarters
A41: Report Date | B41: 45382 | C41: 45473 | D41: 45565 | E41: 45657 | F41: 45747 | G41: 45838 | H41: 45930 | I41: 46022 | J41: 46112 | K41: 46203
A42: Sales | B42: 8730.76 | C42: 8969.73 | D42: 8027.54 | E42: 8549.44 | F42: 8358.91 | G42: 8938.55 | H42: 8531.27 | I42: 8867.02 | J42: 9246.7 | K42: 10541.94
A43: Expenses | B43: 7039.39 | C43: 7275.96 | D43: 6788.03 | E43: 6912.71 | F43: 6922.71 | G43: 7313.58 | H43: 7027.89 | I43: 7086.06 | J43: 7460.09 | K43: 8373.18
A44: Other Income | B44: 212.43 | C44: 192.93 | D44: 24.53 | E44: 192.82 | F44: -60.06 | G44: 229.11 | H44: 236.94 | I44: 69.14 | J44: 196.59 | K44: 279.01
A45: Depreciation | B45: 225.61 | C45: 227.7 | D45: 241.99 | E45: 255.55 | F45: 301.1 | G45: 300.87 | H45: 304.93 | I45: 313.07 | J45: 309.98 | K45: 304.19
A46: Interest | B46: 54.1 | C46: 55.38 | D46: 63.01 | E46: 55.84 | F46: 52.79 | G46: 44.5 | H46: 43.87 | I46: 47.94 | J46: 59.1 | K46: 47.83
A47: Profit before tax | B47: 1624.09 | C47: 1603.62 | D47: 959.04 | E47: 1518.16 | F47: 1022.25 | G47: 1508.71 | H47: 1391.52 | I47: 1489.09 | J47: 1614.12 | K47: 2095.75
A48: Tax | B48: 348.79 | C48: 416.83 | D48: 265.38 | E48: 389.73 | F48: 321.42 | G48: 391.66 | H48: 373.29 | I48: 415.17 | J48: 428.63 | K48: 536.3
A49: Net profit | B49: 1256.72 | C49: 1169.98 | D49: 694.64 | E49: 1110.48 | F49: 692.13 | G49: 1099.77 | H49: 993.59 | I49: 1059.87 | J49: 1172.12 | K49: 1539.25
A50: Operating Profit | B50: 1691.37 | C50: 1693.77 | D50: 1239.51 | E50: 1636.73 | F50: 1436.2 | G50: 1624.97 | H50: 1503.38 | I50: 1780.96 | J50: 1786.61 | K50: 2168.76
A55: BALANCE SHEET
A56: Report Date | B56: 42825 | C56: 43190 | D56: 43555 | E56: 43921 | F56: 44286 | G56: 44651 | H56: 45016 | I56: 45382 | J56: 45747 | K56: 46112
A57: Equity Share Capital | B57: 95.92 | C57: 95.92 | D57: 95.92 | E57: 95.92 | F57: 95.92 | G57: 95.92 | H57: 95.92 | I57: 95.92 | J57: 95.92 | K57: 95.92
A58: Reserves | B58: 7507.97 | C58: 8314.31 | D58: 9374.63 | E58: 10034.24 | F58: 12710.37 | G58: 13715.64 | H58: 15896.31 | I58: 18632.38 | J58: 19303.89 | K58: 21275.67
A59: Borrowings | B59: 560.34 | C59: 533.43 | D59: 1319.6 | E59: 1118.5 | F59: 1093.12 | G59: 1586.88 | H59: 1932.62 | I59: 2474.38 | J59: 2290.29 | K59: 3928.93
A60: Other Liabilities | B60: 4240.96 | C60: 4819.82 | D60: 5458.69 | E60: 4889.31 | F60: 6455.93 | G60: 7559.99 | H60: 7854.48 | I60: 8698.09 | J60: 8665.15 | K60: 9218.23
A61: Total | B61: 12405.19 | C61: 13763.48 | D61: 16248.84 | E61: 16137.97 | F61: 20355.34 | G61: 22958.43 | H61: 25779.33 | I61: 29900.77 | J61: 30355.25 | K61: 34518.75
A62: Net Block | B62: 3303.74 | C62: 3732.24 | D62: 6496.56 | E62: 6272.31 | F62: 5858.52 | G62: 5519.06 | H62: 5770.46 | I62: 7146.62 | J62: 9220.1 | K62: 9640.28
A63: Capital Work in Progress | B63: 257.54 | C63: 1405.11 | D63: 209.67 | E63: 140.24 | F63: 182.98 | G63: 426.43 | H63: 1019.59 | I63: 2698.37 | J63: 1254.49 | K63: 1848.67
A64: Investments | B64: 2651.99 | C64: 2140.7 | D64: 2568.58 | E64: 2018.85 | F64: 4736.8 | G64: 3247.53 | H64: 4261.71 | I64: 4587.92 | J64: 4724.75 | K64: 7061.74
A65: Other Assets | B65: 6191.92 | C65: 6485.43 | D65: 6974.03 | E65: 7706.57 | F65: 9577.04 | G65: 13765.41 | H65: 14727.57 | I65: 15467.86 | J65: 15155.91 | K65: 15968.06
A66: Total | B66: 12405.19 | C66: 13763.48 | D66: 16248.84 | E66: 16137.97 | F66: 20355.34 | G66: 22958.43 | H66: 25779.33 | I66: 29900.77 | J66: 30355.25 | K66: 34518.75
A67: Receivables | B67: 1446.6 | C67: 1730.63 | D67: 1907.33 | E67: 1795.22 | F67: 2602.17 | G67: 3871.44 | H67: 4636.94 | I67: 4889.05 | J67: 4313.65 | K67: 4461.8
... A70: No. of Equity Shares | B70: 959197790 | C70: 959197790 | D70: 959197790 | E70: 959197790 | F70: 959197790 | G70: 959197790 | H70: 959197790 | I70: 959197790 | J70: 959197790 | K70: 959197790
A71: New Bonus Shares
A72: Face value | B72: 1 | C72: 1 | D72: 1 | E72: 1 | F72: 1 | G72: 1 | H72: 1 | I72: 1 | J72: 1 | K72: 1
A74: Total Asset | B74: =B61 -> 12405.19 | C74: =C61 -> 13763.48 | D74: =D61 -> 16248.84 | E74: =E61 -> 16137.97 | F74: =F61 -> 20355.34 | G74: =G61 -> 22958.43 | H74: =H61 -> 25779.33 | I74: =I61 -> 29900.77 | ... K74: =K61 -> 34518.75
A75: Other asset | B75: =B65-SUM(B67:B69) -> 1317.17 | C75: =C65-SUM(C67:C69) -> 1691.84 | D75: =D65-SUM(D67:D69) -> 1471.96 | E75: =E65-SUM(E67:E69) -> 1738.71 | F75: =F65-SUM(F67:F69) -> 2565.52 | G75: =G65-SUM(G67:G69) -> 2876.66 | H75: =H65-SUM(H67:H69) -> 3036.17 | I75: =I65-SUM(I67:I69) -> 3571.39 | ... K75: =K65-SUM(K67:K69) -> 4688.89
A80: CASH FLOW:
A81: Report Date | B81: 42825 | C81: 43190 | D81: 43555 | E81: 43921 | F81: 44286 | G81: 44651 | H81: 45016 | I81: 45382 | J81: 45747 | K81: 46112
A82: Cash from Operating Activity | B82: 1527.33 | C82: 2113.44 | D82: 2469.54 | E82: 3038.15 | F82: 3683.35 | G82: 986.49 | H82: 4193.43 | I82: 6103.6 | J82: 4423.96 | K82: 7088.18
A83: Cash from Investing Activity | B83: -681.11 | C83: -1556.14 | D83: -917.79 | E83: -517.91 | F83: -540.54 | G83: -316.75 | H83: -1282.34 | I83: -2548.48 | J83: -940.91 | K83: -1328.23
A84: Cash from Financing Activity | B84: -756.43 | C84: -1379.14 | D84: -1117.46 | E84: -2871.46 | F84: -650.4 | G84: -1807.61 | H84: -2140.05 | I84: -2982.5 | J84: -3752.58 | K84: -2376.51
A85: Net Cash Flow | B85: 89.79 | C85: -821.84 | D85: 434.29 | E85: -351.22 | F85: 2492.41 | G85: -1137.87 | H85: 771.04 | I85: 572.62 | J85: -269.53 | K85: 3383.44
A90: PRICE: | B90: 1073.5 | C90: 1120.4 | D90: 1492.7 | E90: 1666.5 | F90: 2537.4 | G90: 3079.95 | H90: 2761.65 | I90: 2846.75 | J90: 2340.65 | K90: 2165.2
A92: DERIVED:
A93: Adjusted Equity Shares in Cr | B93: 95.92 | C93: 95.92 | D93: 95.92 | E93: 95.92 | F93: 95.92 | G93: 95.92 | H93: 95.92 | I93: 95.92 | J93: 95.92 | K93: 95.92

Sheet Raw FS
B2: Particulars | C2: 42064 | D2: 42430 | E2: 42795 | F2: 43160 | G2: 43525 | H2: 43891 | I2: 44256 | J2: 44621 | K2: 44986 | L2: 45352 | M2: 45717 | N2: 46082
B4: Equity Capital | C4: 96 | D4: 96 | E4: 96 | F4: 96 | G4: 96 | H4: 96 | I4: 96 | J4: 96 | K4: 96 | L4: 96 | M4: 96 | N4: 96
B5: Reserves | C5: 4646 | D5: 6429 | E5: 7508 | F5: 8314 | G5: 9375 | H5: 10034 | I5: 12710 | J5: 13716 | K5: 15896 | L5: 18632 | M5: 19304 | N5: 21276
B6: Borrowings -
B7: Long term Borrowings | C7: 78 | D7: 73 | E7: 41 | F7: 28 | G7: 19 | H7: 19 | I7: 15 | J7: 45 | K7: 76 | L7: 54 | M7: 260 | N7: 1247
B8: Short term Borrowings | C8: 332 | D8: 231 | E8: 504 | F8: 492 | G8: 597 | H8: 321 | I8: 334 | J8: 731 | K8: 896 | L8: 1053 | M8: 604 | N8: 1046
B9: Lease Liabilities | C9: 0 | D9: 0 | E9: 0 | F9: 0 | G9: 693 | H9: 764 | I9: 745 | J9: 811 | K9: 960 | L9: 1367 | M9: 1427 | N9: 1636
B10: Other Borrowings | C10: 8 | D10: 20 | E10: 15 | F10: 13 | G10: 11 | H10: 15 | I10: 0 | J10: 0 | K10: 0 | L10: 0 | M10: 0 | N10: 0
B11: Other Liabilities -
B12: Non controlling int | C12: 264 | D12: 384 | E12: 375 | F12: 328 | G12: 361 | H12: 404 | I12: 423 | J12: 388 | K12: 454 | L12: 695 | M12: 659 | N12: 643
B13: Trade Payables | C13: 1549 | D13: 1565 | E13: 1923 | F13: 2160 | G13: 2394 | H13: 2137 | I13: 3379 | J13: 4164 | K13: 3635 | L13: 3831 | M13: 3848 | N13: 3863
B14: Advance from Customers | C14: 5 | D14: 12 | E14: 17 | F14: 16 | G14: 13 | H14: 29 | I14: 41 | J14: 76 | K14: 108 | L14: 154 | M14: 174 | N14: 107
B15: Other liability items | C15: 1937 | D15: 1750 | E15: 1925 | F15: 2316 | G15: 2690 | H15: 2320 | I15: 2613 | J15: 2932 | K15: 3657 | L15: 4017 | M15: 3984 | N15: 4604
B16: Total Liabilities | C16: 8914 | D16: 10559 | E16: 12405 | F16: 13763 | G16: 16249 | H16: 16138 | I16: 20355 | J16: 22958 | K16: 25779 | L16: 29901 | M16: 30355 | N16: 34519
B18: Fixed Assets -
B19: Land | C19: 251 | D19: 429 | E19: 408 | F19: 586 | G19: 605 | H19: 640 | I19: 644 | J19: 644 | K19: 804 | L19: 1126 | M19: 1035 | N19: 1204
B20: Building | C20: 962 | D20: 923 | E20: 931 | F20: 957 | G20: 2402 | H20: 2257 | I20: 2249 | J20: 2325 | K20: 2883 | L20: 3390 | M20: 3771 | N20: 4124
B21: Plant Machinery | C21: 2132 | D21: 1793 | E21: 1980 | F21: 2157 | G21: 4006 | H21: 4208 | I21: 4340 | J21: 4531 | K21: 4825 | L21: 5422 | M21: 7576 | N21: 8210
B22: Equipments | C22: 171 | D22: 97 | E22: 119 | F22: 200 | G22: 221 | H22: 241 | I22: 243 | J22: 253 | K22: 270 | L22: 298 | M22: 325 | N22: 351
B23: Furniture n fittings | C23: 83 | D23: 49 | E23: 59 | F23: 72 | G23: 88 | H23: 94 | I23: 99 | J23: 113 | K23: 146 | L23: 175 | M23: 203 | N23: 216
B24: Vehicles | C24: 18 | D24: 11 | E24: 14 | F24: 27 | G24: 47 | H24: 43 | I24: 38 | J24: 32 | K24: 36 | L24: 40 | M24: 34 | N24: 45
B25: Intangible Assets | C25: 351 | D25: 339 | E25: 276 | F25: 468 | G25: 512 | H25: 505 | I25: 476 | J25: 345 | K25: 422 | L25: 850 | M25: 827 | N25: 833
B26: Other fixed assets | C26: 145 | D26: 103 | E26: 128 | F26: 238 | G26: 261 | H26: 293 | I26: 302 | J26: 294 | K26: 289 | L26: 321 | M26: 328 | N26: 335
B27: Gross Block | C27: 4112 | D27: 3744 | E27: 3914 | F27: 4705 | G27: 8141 | H27: 8282 | I27: 8392 | J27: 8538 | K27: 9676 | L27: 11622 | M27: 14099 | N27: 15316
B28: Accumulated Depreciation | C28: 1452 | D28: 327 | E28: 610 | F28: 973 | G28: 1644 | H28: 2010 | I28: 2533 | J28: 3019 | K28: 3905 | L28: 4475 | M28: 4879 | N28: 5676
B29: Net Block | C29: =C27-C28 -> 2660 | D29: =D27-D28 -> 3417 | E29: =E27-E28 -> 3304 | F29: =F27-F28 -> 3732 | G29: =G27-G28 -> 6497 | H29: =H27-H28 -> 6272 | I29: =I27-I28 -> 5859 | J29: =J27-J28 -> 5519 | ... N29: =N27-N28 -> 9640
B31: CWIP | C31: 196 | D31: 107 | E31: 258 | F31: 1405 | G31: 210 | H31: 140 | I31: 183 | J31: 426 | K31: 1020 | L31: 2698 | M31: 1254 | N31: 1849
B32: Investments | C32: 1588 | D32: 2712 | E32: 2652 | F32: 2141 | G32: 2569 | H32: 2019 | I32: 4737 | J32: 3248 | K32: 4262 | L32: 4588 | M32: 4725 | N32: 7062
B34: Other Assets -
B35: Inventories | C35: 2259 | D35: 1998 | E35: 2627 | F35: 2658 | G35: 3150 | H35: 3390 | I35: 3799 | J35: 6153 | K35: 6211 | L35: 5923 | M35: 6719 | N35: 5744
B36: Trade receivables | C36: 1182 | D36: 1187 | E36: 1447 | F36: 1731 | G36: 1907 | H36: 1795 | I36: 2602 | J36: 3871 | K36: 4637 | L36: 4889 | M36: 4314 | N36: 4462
B37: Cash Equivalents | C37: 204 | D37: 424 | E37: 801 | F37: 405 | G37: 445 | H37: 783 | I37: 611 | J37: 864 | K37: 844 | L37: 1084 | M37: 782 | N37: 1074
B38: Loans n Advances | C38: 8 | D38: 9 | E38: 14 | F38: 13 | G38: 16 | H38: 12 | I38: 11 | J38: 8 | K38: 12 | L38: 17 | M38: 22 | N38: 27
B39: Other asset items | C39: 817 | D39: 705 | E39: 1303 | F39: 1678 | G39: 1456 | H39: 1727 | I39: 2555 | J39: 2869 | K39: 3024 | L39: 3555 | M39: 3319 | N39: 4662
B40: Total Assets | C40: 8914 | D40: 10559 | E40: 12405 | F40: 13763 | G40: 16249 | H40: 16138 | I40: 20355 | J40: 22958 | K40: 25779 | L40: 29901 | M40: 30355 | N40: 34519
B44: Cash from Operating Activity | C44: 1188 | D44: 2243 | E44: 1527 | F44: 2113 | G44: 2470 | H44: 3038 | I44: 3683 | J44: 986 | K44: 4193 | L44: 6104 | M44: 4424 | N44: 7088
B45: Profit from operations | C45: 2271 | D45: 2848 | E45: 3056 | F45: 3274 | G45: 3861 | H45: 4380 | I45: 4970 | J45: 4957 | K45: 6460 | L45: 7929 | M45: 6390 | N45: 7186
B46: Receivables | C46: -155 | D46: -146 | E46: -475 | F46: -483 | G46: -205 | H46: 160 | I46: -849 | J46: -1326 | K46: -834 | L46: -362 | M46: 282 | N46: -274
B47: Inventory | C47: -144 | D47: 202 | E47: -629 | F47: -39 | G47: -492 | H47: -251 | I47: -409 | J47: -2354 | K47: -56 | L47: 315 | M47: -805 | N47: 976
B48: Payables | C48: -151 | D48: 142 | E48: 501 | F48: 442 | G48: 287 | H48: -241 | I48: 1143 | J48: 644 | K48: -539 | L48: 269 | M48: -160 | N48: 396
B49: Other WC items | C49: 0 | D49: 0 | E49: 0 | F49: 0 | G49: 0 | H49: 0 | I49: -92 | J49: 242 | K49: 657 | L49: -212 | M49: 114 | N49: 378
... B71: Net Cash Flow | C71: 147 | D71: 528 | E71: 90 | F71: -822 | G71: 434 | H71: -351 | I71: 2492 | J71: -1138 | K71: 771 | L71: 573 | M71: -270 | N71: 3383

Sheet Cash flow data
C2: 42064 | D2: 42430 | E2: 42795 | F2: 43160 | G2: 43525 | H2: 43891 | I2: 44256 | J2: 44621 | K2: 44986 | L2: 45352 | M2: 45717 | N2: 46082
B3: Cash from Operating Activity - | C3: 1144 | D3: 1980 | E3: 1420 | F3: 2136 | G3: 2395 | H3: 2407 | I3: 3459 | J3: 1260 | K3: 4222 | L3: 5757 | M3: 4124 | N3: 6761
B4: Profit from operations | C4: 2077 | D4: 2577 | E4: 2809 | F4: 3081 | G4: 3644 | H4: 4116 | I4: 4699 | J4: 4868 | K4: 6089 | L4: 7406 | M4: 6076 | N4: 6670
B5: Receivables | C5: -91 | D5: -35 | E5: -241 | F5: -150 | G5: -114 | H5: 116 | I5: -724 | J5: -1142 | K5: -582 | L5: -267 | M5: 259 | N5: -139
B6: Inventory | C6: -131 | D6: 192 | E6: -584 | F6: 16 | G6: -407 | H6: -242 | I6: -297 | J6: -2153 | K6: -44 | L6: 264 | M6: -693 | N6: 1023
B7: Payables | C7: -166 | D7: 98 | E7: 464 | F7: 365 | G7: 174 | H7: -774 | I7: 961 | J7: 593 | K7: -442 | L7: 272 | M7: -318 | N7: 375
B8: Loans Advances | C8: 32 | D8: -99 | E8: 0 | F8: 0 | G8: 0 | H8: 0 | I8: 0 | J8: 0 | K8: 0 | L8: 0 | M8: 0 | N8: 0
B9: Other WC items | C9: 12 | D9: 7 | E9: -185 | F9: -191 | G9: 13 | H9: 125 | I9: -164 | J9: 202 | K9: 615 | L9: -185 | M9: 108 | N9: 296
B10: Working capital changes | C10: -344 | D10: 164 | E10: -546 | F10: 40 | G10: -335 | H10: -775 | I10: -225 | J10: -2499 | K10: -453 | L10: 83 | M10: -644 | N10: 1555
B11: Direct taxes | C11: -589 | D11: -761 | E11: -843 | F11: -986 | G11: -914 | H11: -933 | I11: -1015 | J11: -1109 | K11: -1415 | L11: -1732 | M11: -1308 | N11: -1465
B12: Cash from Investing Activity - | C12: -292 | D12: -863 | E12: -584 | F12: -1371 | G12: -833 | H12: -775 | I12: -436 | J12: -340 | K12: -1397 | L12: -2270 | M12: -746 | N12: -1190
B13: Fixed assets purchased | C13: -336 | D13: -687 | E13: -611 | F13: -1358 | G13: -1067 | H13: -316 | I13: -218 | J13: -415 | K13: -1224 | L13: -2190 | M13: -1486 | N13: -1196
B14: Fixed assets sold | C14: 1 | D14: 12 | E14: 2 | F14: 9 | G14: 15 | H14: 26 | I14: 26 | J14: 27 | K14: 16 | L14: 5 | M14: 8 | N14: 2
... B31: Net Cash Flow | C31: 124 | D31: 413 | E31: -120 | F31: -474 | G31: 473 | H31: -462 | I31: 2440 | J31: -1069 | K31: 640 | L31: 540 | M31: -38 | N31: 3426

Sheet Data_comps
B2: S.No. | C2: Name | D2: CMP Rs. | E2: No. Eq. Shares Cr. | F2: Market Cap | G2: Debt Rs.Cr. | H2: Cash End Rs.Cr. | I2: Net Debt | J2: EV | K2: Sales Rs.Cr. | L2: EBITDA Margins | M2: NP 12M Rs.Cr.
B3: 1 | C3: Asian Paints | D3: 2735 | E3: 95.92 | F3: =D3*E3 -> 262341.2 | G3: 3928.93 | H3: 1073.68 | I3: =G3-H3 -> 2855.25 | J3: =F3+G3-H3 -> 265196.45 | K3: 37186.93 | L3: 8181.1246 | M3: 4837.09
B4: 2 | C4: Berger Paints | D4: 530.55 | E4: 116.6 | F4: =D4*E4 -> 61862.13 | G4: 635.13 | H4: 305.31 | I4: =G4-H4 -> 329.82 | J4: =F4+G4-H4 -> 62191.95 | K4: 12263.24 | L4: 2084.7508 | M4: 1217.99
B5: 3 | C5: Kansai Nerolac | D5: 212.35 | E5: 80.87 | F5: =D5*E5 -> 17172.745 | G5: 302.73 | H5: 225.78 | I5: =G5-H5 -> 76.95 | J5: =F5+G5-H5 -> 17249.695 | K5: 8263.47 | L5: 1156.8858 | M5: 588.66
B6: 4 | C6: JSW Dulux | D6: 3011.7 | E6: 4.55 | F6: =D6*E6 -> 13703.235 | G6: 79.1 | H6: 323.7 | I6: =G6-H6 -> -244.6 | J6: =F6+G6-H6 -> 13458.635 | K6: 3599.2 | L6: 503.888 | M6: 1973.8
B7: 5 | C7: Indigo Paints | D7: 1120.5 | E7: 4.77 | F7: =D7*E7 -> 5344.785 | G7: 18.37 | H7: 28.55 | I7: =G7-H7 -> -10.18 | J7: =F7+G7-H7 -> 5334.605 | K7: 1330.12 | L7: 252.7228 | M7: 145.39
B8: 6 | C8: Sirca Paints | D8: 449.9 | E8: 5.68 | F8: =D8*E8 -> 2555.432 | G8: 32.32 | H8: 57.98 | I8: =G8-H8 -> -25.66 | J8: =F8+G8-H8 -> 2529.772 | K8: 508.26 | L8: 106.7346 | M8: 67.05
B9: 7 | C9: Shalimar Paints | D9: 84.47 | E9: 8.37 | F9: =D9*E9 -> 707.0139 | G9: 164.76 | H9: 47.09 | I9: =G9-H9 -> 117.67 | J9: =F9+G9-H9 -> 824.6839 | K9: 575.63 | L9: -17.2689 | M9: -64.95
B10: 8 | C10: Kamdhenu Venture | D10: 4.59 | E10: 32.9 | F10: =D10*E10 -> 151.011 | G10: 34.1 | H10: 19.75 | I10: =G10-H10 -> 14.35 | J10: =F10+G10-H10 -> 165.361 | K10: 245.26 | L10: 9.8104 | M10: 0.2
B11: 9 | C11: Siddhika Coatings | D11: 209.25 | E11: 0.62 | F11: =D11*E11 -> 129.735 | G11: 0 | H11: 8.73 | I11: =G11-H11 -> -8.73 | J11: =F11+G11-H11 -> 121.005 | K11: 54.9 | L11: 13.176 | M11: 9.86
B12: 10 | C12: Retina Paints | D12: 43 | E12: 1.53 | F12: =D12*E12 -> 65.79 | G12: 18.39 | H12: 0.89 | I12: =G12-H12 -> 17.5 | J12: =F12+G12-H12 -> 83.29 | K12: 23.74 | L12: 2.8488 | M12: 0.64

Sheet Companion sheet>
